Workbook

Sheet Mode d'emploi
A1: Comparateur d'offres fournisseurs — {{NOM_BOUTIQUE}}
A2: AUCUN PRIX RÉEL. Seules les lignes marquées FICTIF (fournisseurs FICTIF_FOURNISSEUR_A et _B, référence FICTIF_R00) sont remplies, pour montrer le calcul. Les supprimer avant usage réel.
A3: Source : BP du 4.10.2026, §1 (devis sur les mêmes références), §2 (demande commerciale), §4 (coût rendu et prix plancher), §5 (règles), §13 (même panier aux 3 fournisseurs FR).
A4: Paramètres de prix : config/pricing_rules.v1.yaml, version v1-2026-10-04 (hypothèses BP §4-5, à confirmer par devis).
A6: MODE D'EMPLOI
A7: 1. Paramètres : choisir le mode TVA de l'entité (B4) selon la décision de la fiduciaire (B10). Les autres valeurs viennent du fichier de règles : ne les modifier qu'en créant une nouvelle version.
A8: 2. Fournisseurs : une ligne par fournisseur. Saisir pays d'expédition, devise, taux de change vers CHF (source + date), TVA facturée par le fournisseur (0 si facture d'export HT) et son pays, port amont et frais fixes de la commande (en devise), frais de dédouanement (CHF). Une case vide = fournisseur INCOMPLET.
A9: 3. Offres : une ligne par couple (référence, fournisseur), à partir du devis écrit. Saisir unités par conditionnement, prix du conditionnement, HT ou TTC, remise du palier atteint pour la quantité commandée, quantité commandée (en conditionnements), MOQ, disponibilité, allocation ferme, et la référence marché (médiane du prix total livré, docs/01-marche/GRILLE_CONCURRENCE.csv).
A10: 4. Les colonnes grises se calculent seules : coût rendu C par unité (CHF), prix plancher, écart au marché, contribution au prix marché, statut, rang.
A11: 5. Classement : meilleur et 2e fournisseur par référence. Synthèse fournisseurs : couverture du panier, valeur de la commande, minimum de commande atteint.
A13: RÈGLES DE CALCUL (identiques au moteur pokeshop.pricing)
A14: C = achat HT unitaire en CHF + TVA fournisseur non récupérable + port et frais ventilés + dédouanement ventilé + TVA import (seulement si NOT_REGISTERED). La TVA fournisseur n'est récupérable que si elle est suisse ET l'entité assujettie (EFFECTIVE). Port, frais et dédouanement sont ventilés au prorata de la valeur HT des lignes du même fournisseur. Droits de douane = 0 (produits industriels, depuis le 1.1.2024).
... A26: - Valider le fournisseur retenu par référence (C08) ; le classement est une aide, pas une décision.

Sheet Paramètres
A1: Paramètres de calcul
A2: Source : config/pricing_rules.v1.yaml (v1-2026-10-04) — hypothèses BP §4-5, à confirmer.
A3: Paramètre | B3: Valeur | C3: Note
A4: Mode TVA de l'entité (EFFECTIVE / NOT_REGISTERED) | B4: EFFECTIVE | C4: Décision de la fiduciaire (B10). EFFECTIVE = hypothèse du BP §10.
A5: t — TVA sur ventes | B5: =IF(Paramètres!$B$4="EFFECTIVE",Paramètres!$B$13,0) -> 0.081 | C5: 0 si non assujetti (BP §4).
A6: r — frais de paiement proportionnels | B6: 0.025 | C6: Hypothèse BP §4 ; contrat PSP.
A7: b — frais fixes de paiement (CHF/commande) | B7: 0.3 | C7: Hypothèse BP §4.
A8: L — logistique nette (CHF/commande) | B8: 3 | C8: Hypothèse BP §4 ; devis transporteur.
A9: R — provision SAV (CHF/commande) | B9: 1 | C9: Hypothèse BP §4.
A10: A — acquisition attribuée (CHF/commande) | B10: 5 | C10: Hypothèse BP §4.
A11: m — contribution cible (% du CA net) | B11: 0.2 | C11: BP §5.
A12: Seuil « au-dessus du marché » | B12: 0.1 | C12: BP §5 : > 10 % ⇒ à revoir.
A13: Taux normal de TVA suisse | B13: 0.081 | C13: Au 4.10.2026 [S6] ; à confirmer.
A14: Taux de TVA à l'importation (estimation) | B14: 0.081 | C14: Estimation ; la base réelle se lit sur le décompte OFDF [S7].
A15: Plancher dur (% du CA net) | B15: 0.12 | C15: BP §5 = stop-loss produit.
A16: Plancher dur (CHF/commande) | B16: 8 | C16: BP §5 = stop-loss produit.
A17: Version des règles | B17: v1-2026-10-04 | C17: Recopiée dans chaque décision de prix.

Sheet Fournisseurs
A1: Fournisseurs — conditions communes à toutes les lignes d'un même fournisseur
A2: Aucune donnée réelle : les 6 fournisseurs du BP (et la piste hors BP) sont à compléter à réception des devis. Lignes orange = FICTIF.
A4: Fournisseur | B4: Pays d'expédition (ISO2) | C4: Devise | D4: Taux → CHF (CHF pour 1 unité) | E4: Source du taux | F4: Date du taux | G4: TVA facturée par le fournisseur (taux) | H4: Pays de cette TVA (ISO2) | I4: Incoterm | J4: Port amont total de la commande (devise) | K4: Frais fixes de commande (devise) | L4: Dédouanement / transitaire total (CHF) | M4: Minimum de commande (devise) | N4: Délai annoncé (jours ouvrés) | O4: Paiement | P4: Flux de données | Q4: Exemple de fichier reçu (O/N) | R4: Statut | S4: Fictif (O/N) | T4: Complet (calculé)
A5: Asmodee France | R5: non contacté | S5: N | T5: =IF(A5="","",IF(AND(B5<>"",C5<>"",D5<>"",E5<>"",F5<>"",G5<>"",H5<>"",J5<>"",K5<>"",L5<>""),1,0)) -> 0
A6: Matoo et Miao | R6: non contacté | S6: N | T6: =IF(A6="","",IF(AND(B6<>"",C6<>"",D6<>"",E6<>"",F6<>"",G6<>"",H6<>"",J6<>"",K6<>"",L6<>""),1,0)) -> 0
A7: TCG Distribution | R7: non contacté | S7: N | T7: =IF(A7="","",IF(AND(B7<>"",C7<>"",D7<>"",E7<>"",F7<>"",G7<>"",H7<>"",J7<>"",K7<>"",L7<>""),1,0)) -> 0
A8: OtakuWorld | R8: non contacté | S8: N | T8: =IF(A8="","",IF(AND(B8<>"",C8<>"",D8<>"",E8<>"",F8<>"",G8<>"",H8<>"",J8<>"",K8<>"",L8<>""),1,0)) -> 0
A9: CardCosmos | R9: non contacté | S9: N | T9: =IF(A9="","",IF(AND(B9<>"",C9<>"",D9<>"",E9<>"",F9<>"",G9<>"",H9<>"",J9<>"",K9<>"",L9<>""),1,0)) -> 0
A10: Carletto AG (hors BP) | R10: non contacté | S10: N | T10: =IF(A10="","",IF(AND(B10<>"",C10<>"",D10<>"",E10<>"",F10<>"",G10<>"",H10<>"",J10<>"",K10<>"",L10<>""),1,0)) -> 0
A11: FICTIF_FOURNISSEUR_A | B11: FR | C11: EUR | D11: 0.94 | E11: FICTIF – exemple | F11: 46299 | G11: 0 | H11: FR | I11: DAP | J11: 40 | K11: 0 | L11: 25 | M11: 500 | N11: 5 | O11: Prépaiement | P11: CSV | Q11: N | R11: FICTIF | S11: O | T11: =IF(A11="","",IF(AND(B11<>"",C11<>"",D11<>"",E11<>"",F11<>"",G11<>"",H11<>"",J11<>"",K11<>"",L11<>""),1,0)) -> 1
A12: FICTIF_FOURNISSEUR_B | B12: CH | C12: CHF | D12: 1 | E12: CHF (aucune conversion) | F12: 46299 | G12: 0.081 | H12: CH | I12: DAP | J12: 15 | K12: 0 | L12: 0 | M12: 300 | N12: 2 | O12: 30 jours | P12: XLSX | Q12: N | R12: FICTIF | S12: O | T12: =IF(A12="","",IF(AND(B12<>"",C12<>"",D12<>"",E12<>"",F12<>"",G12<>"",H12<>"",J12<>"",K12<>"",L12<>""),1,0)) -> 1
T13: =IF(A13="","",IF(AND(B13<>"",C13<>"",D13<>"",E13<>"",F13<>"",G13<>"",H13<>"",J13<>"",K13<>"",L13<>""),1,0))
T14: =IF(A14="","",IF(AND(B14<>"",C14<>"",D14<>"",E14<>"",F14<>"",G14<>"",H14<>"",J14<>"",K14<>"",L14<>""),1,0))
T15: =IF(A15="","",IF(AND(B15<>"",C15<>"",D15<>"",E15<>"",F15<>"",G15<>"",H15<>"",J15<>"",K15<>"",L15<>""),1,0))
T16: =IF(A16="","",IF(AND(B16<>"",C16<>"",D16<>"",E16<>"",F16<>"",G16<>"",H16<>"",J16<>"",K16<>"",L16<>""),1,0))
T17: =IF(A17="","",IF(AND(B17<>"",C17<>"",D17<>"",E17<>"",F17<>"",G17<>"",H17<>"",J17<>"",K17<>"",L17<>""),1,0))
T18: =IF(A18="","",IF(AND(B18<>"",C18<>"",D18<>"",E18<>"",F18<>"",G18<>"",H18<>"",J18<>"",K18<>"",L18<>""),1,0))
T19: =IF(A19="","",IF(AND(B19<>"",C19<>"",D19<>"",E19<>"",F19<>"",G19<>"",H19<>"",J19<>"",K19<>"",L19<>""),1,0))
T20: =IF(A20="","",IF(AND(B20<>"",C20<>"",D20<>"",E20<>"",F20<>"",G20<>"",H20<>"",J20<>"",K20<>"",L20<>""),1,0))
T21: =IF(A21="","",IF(AND(B21<>"",C21<>"",D21<>"",E21<>"",F21<>"",G21<>"",H21<>"",J21<>"",K21<>"",L21<>""),1,0))
T22: =IF(A22="","",IF(AND(B22<>"",C22<>"",D22<>"",E22<>"",F22<>"",G22<>"",H22<>"",J22<>"",K22<>"",L22<>""),1,0))
T23: =IF(A23="","",IF(AND(B23<>"",C23<>"",D23<>"",E23<>"",F23<>"",G23<>"",H23<>"",J23<>"",K23<>"",L23<>""),1,0))
T24: =IF(A24="","",IF(AND(B24<>"",C24<>"",D24<>"",E24<>"",F24<>"",G24<>"",H24<>"",J24<>"",K24<>"",L24<>""),1,0))

Sheet Offres
A1: Offres — une ligne par couple (référence, fournisseur), à partir d'un devis écrit
A2: Aucun prix réel. Lignes 6-7 = exemple FICTIF. Lignes suivantes = panier pilote pré-rempli pour les 3 fournisseurs FR prioritaires (BP §13), à compléter avec leurs devis.
A3: Saisie : colonnes A à S (jaune). Calcul : colonnes T à AT (gris).
A5: ref_id | B5: Désignation (format + extension + langue) | C5: Fournisseur | D5: SKU fournisseur | E5: EAN / GTIN | F5: Langue confirmée | G5: Extension | H5: Format | I5: Unités par conditionnement | J5: Prix du conditionnement (devise, avant remise) | K5: Base de prix (HT/TTC) | L5: Remise du palier atteint (fraction) | M5: Quantité commandée (conditionnements) | N5: MOQ (conditionnements) | O5: Disponibilité annoncée (unités) | P5: Allocation ferme (O/N) | Q5: Date de dispo / sortie | R5: Prix marché observé TTC (CHF, médiane) | S5: Fictif (O/N) | T5: Devise | U5: Taux → CHF | V5: TVA fournisseur (taux) | W5: Pays TVA | X5: Pays d'expédition | Y5: Complet (1/0) | Z5: Prix cond. après remise (devise) | AA5: Prix HT cond. (devise) | AB5: TVA fournisseur cond. (devise) | AC5: Valeur ligne HT (CHF) | AD5: Part de la commande fournisseur | AE5: Port + frais ventilés / unité (CHF) | AF5: Dédouanement ventilé / unité (CHF) | AG5: Achat HT / unité (CHF) | AH5: TVA fournisseur / unité (CHF) | AI5: TVA fournisseur récupérable (1/0) | AJ5: TVA import estimée / unité (CHF) | AK5: COÛT RENDU C / unité (CHF) | AL5: Prix plancher TTC (CHF) | AM5: Écart plancher / marché | AN5: Contribution au prix marché (CHF) | AO5: Contribution au prix marché (% CA net) | AP5: Statut | AQ5: Alertes | AR5: Rang (1 = moins cher) | AS5: Clé de classement | AT5: Total ligne rendu (CHF)
A6: FICTIF_R00 | B6: FICTIF – ETB d'exemple (aucun produit réel) | C6: FICTIF_FOURNISSEUR_A | D6: FICTIF-A-001 | E6: 2000000001012 | F6: FR | G6: FICTIF | H6: etb | I6: 1 | J6: 40 | K6: HT | L6: 0.05 | M6: 10 | N6: 6 | O6: 50 | P6: N | Q6: 46328 | R6: 69.9 | S6: O | T6: =IF($C6="","",IFERROR(INDEX(Fournisseurs!$C$5:$C$24,MATCH($C6,Fournisseurs!$A$5:$A$24,0)),"")) -> EUR | U6: =IF($C6="","",IFERROR(INDEX(Fournisseurs!$D$5:$D$24,MATCH($C6,Fournisseurs!$A$5:$A$24,0)),"")) -> 0.94 | V6: =IF($C6="","",IFERROR(INDEX(Fournisseurs!$G$5:$G$24,MATCH($C6,Fournisseurs!$A$5:$A$24,0)),"")) -> 0 | W6: =IF($C6="","",IFERROR(INDEX(Fournisseurs!$H$5:$H$24,MATCH($C6,Fournisseurs!$A$5:$A$24,0)),"")) -> FR | X6: =IF($C6="","",IFERROR(INDEX(Fournisseurs!$B$5:$B$24,MATCH($C6,Fournisseurs!$A$5:$A$24,0)),"")) -> FR | Y6: =IF($A6="","",IF(AND($A6<>"",$C6<>"",ISNUMBER($I6),ISNUMBER($J6),ISNUMBER($M6)),IF(AND($I6>=1,$J6>0,OR($K6="HT",$K6="TTC"),$M6>=1,IFERROR(INDEX(Fournisseurs!$T$5:$T$24,MATCH($C6,Fournisseurs!$A$5:$A$24,0)),0)=1),1,0),0)) -> 1 | Z6: =IF($Y6=1,$J6*(1-N($L6)),"") -> 38 | AA6: =IF($Y6=1,IF($K6="TTC",$Z6/(1+$V6),$Z6),"") -> 38 | AB6: =IF($Y6=1,IF($K6="TTC",$Z6-$AA6,$AA6*$V6),"") -> 0 | AC6: =IF($Y6=1,$AA6*$U6*$M6,"") -> 357.2 | AD6: =IF($Y6=1,$AC6/SUMIFS($AC$6:$AC$205,$C$6:$C$205,$C6,$Y$6:$Y$205,1),"") -> 1 | AE6: =IF($Y6=1,(INDEX(Fournisseurs!$J$5:$J$24,MATCH($C6,Fournisseurs!$A$5:$A$24,0))+INDEX(Fournisseurs!$K$5:$K$24,MATCH($C6,Fournisseurs!$A$5:$A$24,0)))*$U6*$AD6/($I6*$M6),"") -> 3.76 | AF6: =IF($Y6=1,INDEX(Fournisseurs!$L$5:$L$24,MATCH($C6,Fournisseurs!$A$5:$A$24,0))*$AD6/($I6*$M6),"") -> 2.5 | AG6: =IF($Y6=1,$AA6*$U6/$I6,"") -> 35.72 | AH6: =IF($Y6=1,$AB6*$U6/$I6,"") -> 0 | AI6: =IF($Y6=1,IF(AND(Paramètres!$B$4="EFFECTIVE",$W6="CH",$AB6>0),1,0),"") -> 0 | AJ6: =IF($Y6=1,IF($X6<>"CH",($AG6+$AE6+$AF6)*Paramètres!$B$14,0),"") -> 3.40038 | AK6: =IF($Y6=1,$AG6+IF($AI6=1,0,$AH6)+$AE6+$AF6+IF(Paramètres!$B$4="NOT_REGISTERED",$AJ6,0),"") -> 41.98 | AL6: =IF($Y6=1,($AK6+Paramètres!$B$7+Paramètres!$B$8+Paramètres!$B$9+Paramètres!$B$10)/((1-Paramètres!$B$11)/(1+Paramètres!$B$5)-Paramètres!$B$6),"") -> 71.714713 | AM6: =IF(AND($Y6=1,ISNUMBER($R6)),IF($R6>0,$AL6/$R6-1,""),"") -> 0.025961554 | AN6: =IF(AND($Y6=1,ISNUMBER($R6)),IF($R6>0,$R6/(1+Paramètres!$B$5)-$AK6-($R6*Paramètres!$B$6+Paramètres!$B$7)-Paramètres!$B$8-Paramètres!$B$9-Paramètres!$B$10,""),"") -> 11.63485 | AO6: =IF(ISNUMBER($AN6),$AN6/($R6/(1+Paramètres!$B$5)),"") -> 0.17993237 | AP6: =IF($A6="","",IF($Y6<>1,"INCOMPLET",IF(NOT(ISNUMBER($AM6)),"SANS RÉF. MARCHÉ",IF($AM6<=Paramètres!$B$12,"OK",IF(AND($AO6>=Paramètres!$B$15,$AN6>=Paramètres!$B$16),"À REVOIR","NON RENTABLE"))))) -> OK | AQ6: =TRIM(IF(AND($Y6=1,ISNUMBER($N6)),IF($M6<$N6,"MOQ ",""),"")&IF(AND($Y6=1,ISNUMBER($O6)),IF($O6<$I6*$M6,"DISPO ",""),"")&IF($S6="O","FICTIF ","")&IF($Y6=1,IF(AND($K6="TTC",$W6<>"CH"),"TVA-ÉTRANGÈRE ",""),"")) -> FICTIF | AR6: =IF($Y6=1,COUNTIFS($A$6:$A$205,$A6,$AK$6:$AK$205,"<"&$AK6,$Y$6:$Y$205,1)+1,"") -> 1 | AS6: =IF(ISNUMBER($AR6),$A6&"|"&$AR6,"") -> FICTIF_R00|1 | AT6: =IF($Y6=1,$AK6*$I6*$M6,"") -> 419.8
A7: FICTIF_R00 | B7: FICTIF – ETB d'exemple (aucun produit réel) | C7: FICTIF_FOURNISSEUR_B | D7: FICTIF-B-001 | E7: 2000000001012 | F7: FR | G7: FICTIF | H7: etb | I7: 1 | J7: 49.9 | K7: TTC | M7: 10 | N7: 1 | O7: 20 | P7: N | Q7: 46315 | R7: 69.9 | S7: O | T7: =IF($C7="","",IFERROR(INDEX(Fournisseurs!$C$5:$C$24,MATCH($C7,Fournisseurs!$A$5:$A$24,0)),"")) -> CHF | U7: =IF($C7="","",IFERROR(INDEX(Fournisseurs!$D$5:$D$24,MATCH($C7,Fournisseurs!$A$5:$A$24,0)),"")) -> 1 | V7: =IF($C7="","",IFERROR(INDEX(Fournisseurs!$G$5:$G$24,MATCH($C7,Fournisseurs!$A$5:$A$24,0)),"")) -> 0.081 | W7: =IF($C7="","",IFERROR(INDEX(Fournisseurs!$H$5:$H$24,MATCH($C7,Fournisseurs!$A$5:$A$24,0)),"")) -> CH | X7: =IF($C7="","",IFERROR(INDEX(Fournisseurs!$B$5:$B$24,MATCH($C7,Fournisseurs!$A$5:$A$24,0)),"")) -> CH | Y7: =IF($A7="","",IF(AND($A7<>"",$C7<>"",ISNUMBER($I7),ISNUMBER($J7),ISNUMBER($M7)),IF(AND($I7>=1,$J7>0,OR($K7="HT",$K7="TTC"),$M7>=1,IFERROR(INDEX(Fournisseurs!$T$5:$T$24,MATCH($C7,Fournisseurs!$A$5:$A$24,0)),0)=1),1,0),0)) -> 1 | Z7: =IF($Y7=1,$J7*(1-N($L7)),"") -> 49.9 | AA7: =IF($Y7=1,IF($K7="TTC",$Z7/(1+$V7),$Z7),"") -> 46.160962 | AB7: =IF($Y7=1,IF($K7="TTC",$Z7-$AA7,$AA7*$V7),"") -> 3.7390379 | AC7: =IF($Y7=1,$AA7*$U7*$M7,"") -> 461.60962 | AD7: =IF($Y7=1,$AC7/SUMIFS($AC$6:$AC$205,$C$6:$C$205,$C7,$Y$6:$Y$205,1),"") -> 1 | AE7: =IF($Y7=1,(INDEX(Fournisseurs!$J$5:$J$24,MATCH($C7,Fournisseurs!$A$5:$A$24,0))+INDEX(Fournisseurs!$K$5:$K$24,MATCH($C7,Fournisseurs!$A$5:$A$24,0)))*$U7*$AD7/($I7*$M7),"") -> 1.5 | AF7: =IF($Y7=1,INDEX(Fournisseurs!$L$5:$L$24,MATCH($C7,Fournisseurs!$A$5:$A$24,0))*$AD7/($I7*$M7),"") -> 0 | AG7: =IF($Y7=1,$AA7*$U7/$I7,"") -> 46.160962 | AH7: =IF($Y7=1,$AB7*$U7/$I7,"") -> 3.7390379 | AI7: =IF($Y7=1,IF(AND(Paramètres!$B$4="EFFECTIVE",$W7="CH",$AB7>0),1,0),"") -> 1 | AJ7: =IF($Y7=1,IF($X7<>"CH",($AG7+$AE7+$AF7)*Paramètres!$B$14,0),"") -> 0 | AK7: =IF($Y7=1,$AG7+IF($AI7=1,0,$AH7)+$AE7+$AF7+IF(Paramètres!$B$4="NOT_REGISTERED",$AJ7,0),"") -> 47.660962 | AL7: =IF($Y7=1,($AK7+Paramètres!$B$7+Paramètres!$B$8+Paramètres!$B$9+Paramètres!$B$10)/((1-Paramètres!$B$11)/(1+Paramètres!$B$5)-Paramètres!$B$6),"") -> 79.659497 | AM7: =IF(AND($Y7=1,ISNUMBER($R7)),IF($R7>0,$AL7/$R7-1,""),"") -> 0.13962085 | AN7: =IF(AND($Y7=1,ISNUMBER($R7)),IF($R7>0,$R7/(1+Paramètres!$B$5)-$AK7-($R7*Paramètres!$B$6+Paramètres!$B$7)-Paramètres!$B$8-Paramètres!$B$9-Paramètres!$B$10,""),"") -> 5.9538876 | AO7: =IF(ISNUMBER($AN7),$AN7/($R7/(1+Paramètres!$B$5)),"") -> 0.092076574 | AP7: =IF($A7="","",IF($Y7<>1,"INCOMPLET",IF(NOT(ISNUMBER($AM7)),"SANS RÉF. MARCHÉ",IF($AM7<=Paramètres!$B$12,"OK",IF(AND($AO7>=Paramètres!$B$15,$AN7>=Paramètres!$B$16),"À REVOIR","NON RENTABLE"))))) -> NON RENTABLE | AQ7: =TRIM(IF(AND($Y7=1,ISNUMBER($N7)),IF($M7<$N7,"MOQ ",""),"")&IF(AND($Y7=1,ISNUMBER($O7)),IF($O7<$I7*$M7,"DISPO ",""),"")&IF($S7="O","FICTIF ","")&IF($Y7=1,IF(AND($K7="TTC",$W7<>"CH"),"TVA-ÉTRANGÈRE ",""),"")) -> FICTIF | AR7: =IF($Y7=1,COUNTIFS($A$6:$A$205,$A7,$AK$6:$AK$205,"<"&$AK7,$Y$6:$Y$205,1)+1,"") -> 2 | AS7: =IF(ISNUMBER($AR7),$A7&"|"&$AR7,"") -> FICTIF_R00|2 | AT7: =IF($Y7=1,$AK7*$I7*$M7,"") -> 476.60962
A8: REF-06 | B8: Display 36 boosters Méga-Évolution – Nuit Noire (ME05) – FR | C8: Asmodee France | G8: Méga-Évolution – Nuit Noire | H8: display | S8: N | T8: =IF($C8="","",IFERROR(INDEX(Fournisseurs!$C$5:$C$24,MATCH($C8,Fournisseurs!$A$5:$A$24,0)),"")) -> 0 | U8: =IF($C8="","",IFERROR(INDEX(Fournisseurs!$D$5:$D$24,MATCH($C8,Fournisseurs!$A$5:$A$24,0)),"")) -> 0 | V8: =IF($C8="","",IFERROR(INDEX(Fournisseurs!$G$5:$G$24,MATCH($C8,Fournisseurs!$A$5:$A$24,0)),"")) -> 0 | W8: =IF($C8="","",IFERROR(INDEX(Fournisseurs!$H$5:$H$24,MATCH($C8,Fournisseurs!$A$5:$A$24,0)),"")) -> 0 | X8: =IF($C8="","",IFERROR(INDEX(Fournisseurs!$B$5:$B$24,MATCH($C8,Fournisseurs!$A$5:$A$24,0)),"")) -> 0 | Y8: =IF($A8="","",IF(AND($A8<>"",$C8<>"",ISNUMBER($I8),ISNUMBER($J8),ISNUMBER($M8)),IF(AND($I8>=1,$J8>0,OR($K8="HT",$K8="TTC"),$M8>=1,IFERROR(INDEX(Fournisseurs!$T$5:$T$24,MATCH($C8,Fournisseurs!$A$5:$A$24,0)),0)=1),1,0),0)) -> 0 | Z8: =IF($Y8=1,$J8*(1-N($L8)),"") | AA8: =IF($Y8=1,IF($K8="TTC",$Z8/(1+$V8),$Z8),"") | AB8: =IF($Y8=1,IF($K8="TTC",$Z8-$AA8,$AA8*$V8),"") | AC8: =IF($Y8=1,$AA8*$U8*$M8,"") | AD8: =IF($Y8=1,$AC8/SUMIFS($AC$6:$AC$205,$C$6:$C$205,$C8,$Y$6:$Y$205,1),"") | AE8: =IF($Y8=1,(INDEX(Fournisseurs!$J$5:$J$24,MATCH($C8,Fournisseurs!$A$5:$A$24,0))+INDEX(Fournisseurs!$K$5:$K$24,MATCH($C8,Fournisseurs!$A$5:$A$24,0)))*$U8*$AD8/($I8*$M8),"") | AF8: =IF($Y8=1,INDEX(Fournisseurs!$L$5:$L$24,MATCH($C8,Fournisseurs!$A$5:$A$24,0))*$AD8/($I8*$M8),"") | AG8: =IF($Y8=1,$AA8*$U8/$I8,"") | AH8: =IF($Y8=1,$AB8*$U8/$I8,"") | AI8: =IF($Y8=1,IF(AND(Paramètres!$B$4="EFFECTIVE",$W8="CH",$AB8>0),1,0),"") | AJ8: =IF($Y8=1,IF($X8<>"CH",($AG8+$AE8+$AF8)*Paramètres!$B$14,0),"") | AK8: =IF($Y8=1,$AG8+IF($AI8=1,0,$AH8)+$AE8+$AF8+IF(Paramètres!$B$4="NOT_REGISTERED",$AJ8,0),"") | AL8: =IF($Y8=1,($AK8+Paramètres!$B$7+Paramètres!$B$8+Paramètres!$B$9+Paramètres!$B$10)/((1-Paramètres!$B$11)/(1+Paramètres!$B$5)-Paramètres!$B$6),"") | AM8: =IF(AND($Y8=1,ISNUMBER($R8)),IF($R8>0,$AL8/$R8-1,""),"") | AN8: =IF(AND($Y8=1,ISNUMBER($R8)),IF($R8>0,$R8/(1+Paramètres!$B$5)-$AK8-($R8*Paramètres!$B$6+Paramètres!$B$7)-Paramètres!$B$8-Paramètres!$B$9-Paramètres!$B$10,""),"") | AO8: =IF(ISNUMBER($AN8),$AN8/($R8/(1+Paramètres!$B$5)),"") | AP8: =IF($A8="","",IF($Y8<>1,"INCOMPLET",IF(NOT(ISNUMBER($AM8)),"SANS RÉF. MARCHÉ",IF($AM8<=Paramètres!$B$12,"OK",IF(AND($AO8>=Paramètres!$B$15,$AN8>=Paramètres!$B$16),"À REVOIR","NON RENTABLE"))))) -> INCOMPLET | AQ8: =TRIM(IF(AND($Y8=1,ISNUMBER($N8)),IF($M8<$N8,"MOQ ",""),"")&IF(AND($Y8=1,ISNUMBER($O8)),IF($O8<$I8*$M8,"DISPO ",""),"")&IF($S8="O","FICTIF ","")&IF($Y8=1,IF(AND($K8="TTC",$W8<>"CH"),"TVA-ÉTRANGÈRE ",""),"")) | AR8: =IF($Y8=1,COUNTIFS($A$6:$A$205,$A8,$AK$6:$AK$205,"<"&$AK8,$Y$6:$Y$205,1)+1,"") | AS8: =IF(ISNUMBER($AR8),$A8&"|"&$AR8,"") | AT8: =IF($Y8=1,$AK8*$I8*$M8,"")
A9: REF-09 | B9: Display 36 boosters Méga-Évolution – Chaos Ascendant – FR | C9: Asmodee France | G9: Méga-Évolution – Chaos Ascendant | H9: display | S9: N | T9: =IF($C9="","",IFERROR(INDEX(Fournisseurs!$C$5:$C$24,MATCH($C9,Fournisseurs!$A$5:$A$24,0)),"")) -> 0 | U9: =IF($C9="","",IFERROR(INDEX(Fournisseurs!$D$5:$D$24,MATCH($C9,Fournisseurs!$A$5:$A$24,0)),"")) -> 0 | V9: =IF($C9="","",IFERROR(INDEX(Fournisseurs!$G$5:$G$24,MATCH($C9,Fournisseurs!$A$5:$A$24,0)),"")) -> 0 | W9: =IF($C9="","",IFERROR(INDEX(Fournisseurs!$H$5:$H$24,MATCH($C9,Fournisseurs!$A$5:$A$24,0)),"")) -> 0 | X9: =IF($C9="","",IFERROR(INDEX(Fournisseurs!$B$5:$B$24,MATCH($C9,Fournisseurs!$A$5:$A$24,0)),"")) -> 0 | Y9: =IF($A9="","",IF(AND($A9<>"",$C9<>"",ISNUMBER($I9),ISNUMBER($J9),ISNUMBER($M9)),IF(AND($I9>=1,$J9>0,OR($K9="HT",$K9="TTC"),$M9>=1,IFERROR(INDEX(Fournisseurs!$T$5:$T$24,MATCH($C9,Fournisseurs!$A$5:$A$24,0)),0)=1),1,0),0)) -> 0 | Z9: =IF($Y9=1,$J9*(1-N($L9)),"") | AA9: =IF($Y9=1,IF($K9="TTC",$Z9/(1+$V9),$Z9),"") | AB9: =IF($Y9=1,IF($K9="TTC",$Z9-$AA9,$AA9*$V9),"") | AC9: =IF($Y9=1,$AA9*$U9*$M9,"") | AD9: =IF($Y9=1,$AC9/SUMIFS($AC$6:$AC$205,$C$6:$C$205,$C9,$Y$6:$Y$205,1),"") | AE9: =IF($Y9=1,(INDEX(Fournisseurs!$J$5:$J$24,MATCH($C9,Fournisseurs!$A$5:$A$24,0))+INDEX(Fournisseurs!$K$5:$K$24,MATCH($C9,Fournisseurs!$A$5:$A$24,0)))*$U9*$AD9/($I9*$M9),"") | AF9: =IF($Y9=1,INDEX(Fournisseurs!$L$5:$L$24,MATCH($C9,Fournisseurs!$A$5:$A$24,0))*$AD9/($I9*$M9),"") | AG9: =IF($Y9=1,$AA9*$U9/$I9,"") | AH9: =IF($Y9=1,$AB9*$U9/$I9,"") | AI9: =IF($Y9=1,IF(AND(Paramètres!$B$4="EFFECTIVE",$W9="CH",$AB9>0),1,0),"") | AJ9: =IF($Y9=1,IF($X9<>"CH",($AG9+$AE9+$AF9)*Paramètres!$B$14,0),"") | AK9: =IF($Y9=1,$AG9+IF($AI9=1,0,$AH9)+$AE9+$AF9+IF(Paramètres!$B$4="NOT_REGISTERED",$AJ9,0),"") | AL9: =IF($Y9=1,($AK9+Paramètres!$B$7+Paramètres!$B$8+Paramètres!$B$9+Paramètres!$B$10)/((1-Paramètres!$B$11)/(1+Paramètres!$B$5)-Paramètres!$B$6),"") | AM9: =IF(AND($Y9=1,ISNUMBER($R9)),IF($R9>0,$AL9/$R9-1,""),"") | AN9: =IF(AND($Y9=1,ISNUMBER($R9)),IF($R9>0,$R9/(1+Paramètres!$B$5)-$AK9-($R9*Paramètres!$B$6+Paramètres!$B$7)-Paramètres!$B$8-Paramètres!$B$9-Paramètres!$B$10,""),"") | AO9: =IF(ISNUMBER($AN9),$AN9/($R9/(1+Paramètres!$B$5)),"") | AP9: =IF($A9="","",IF($Y9<>1,"INCOMPLET",IF(NOT(ISNUMBER($AM9)),"SANS RÉF. MARCHÉ",IF($AM9<=Paramètres!$B$12,"OK",IF(AND($AO9>=Paramètres!$B$15,$AN9>=Paramètres!$B$16),"À REVOIR","NON RENTABLE"))))) -> INCOMPLET | AQ9: =TRIM(IF(AND($Y9=1,ISNUMBER($N9)),IF($M9<$N9,"MOQ ",""),"")&IF(AND($Y9=1,ISNUMBER($O9)),IF($O9<$I9*$M9,"DISPO ",""),"")&IF($S9="O","FICTIF ","")&IF($Y9=1,IF(AND($K9="TTC",$W9<>"CH"),"TVA-ÉTRANGÈRE ",""),"")) | AR9: =IF($Y9=1,COUNTIFS($A$6:$A$205,$A9,$AK$6:$AK$205,"<"&$AK9,$Y$6:$Y$205,1)+1,"") | AS9: =IF(ISNUMBER($AR9),$A9&"|"&$AR9,"") | AT9: =IF($Y9=1,$AK9*$I9*$M9,"")
A10: REF-01 | B10: Coffret Dresseur d'Élite (ETB) 30ᵉ Anniversaire – FR | C10: Asmodee France | G10: 30ᵉ Anniversaire | H10: etb | S10: N | T10: =IF($C10="","",IFERROR(INDEX(Fournisseurs!$C$5:$C$24,MATCH($C10,Fournisseurs!$A$5:$A$24,0)),"")) -> 0 | U10: =IF($C10="","",IFERROR(INDEX(Fournisseurs!$D$5:$D$24,MATCH($C10,Fournisseurs!$A$5:$A$24,0)),"")) -> 0 | V10: =IF($C10="","",IFERROR(INDEX(Fournisseurs!$G$5:$G$24,MATCH($C10,Fournisseurs!$A$5:$A$24,0)),"")) -> 0 | W10: =IF($C10="","",IFERROR(INDEX(Fournisseurs!$H$5:$H$24,MATCH($C10,Fournisseurs!$A$5:$A$24,0)),"")) -> 0 | X10: =IF($C10="","",IFERROR(INDEX(Fournisseurs!$B$5:$B$24,MATCH($C10,Fournisseurs!$A$5:$A$24,0)),"")) -> 0 | Y10: =IF($A10="","",IF(AND($A10<>"",$C10<>"",ISNUMBER($I10),ISNUMBER($J10),ISNUMBER($M10)),IF(AND($I10>=1,$J10>0,OR($K10="HT",$K10="TTC"),$M10>=1,IFERROR(INDEX(Fournisseurs!$T$5:$T$24,MATCH($C10,Fournisseurs!$A$5:$A$24,0)),0)=1),1,0),0)) -> 0 | Z10: =IF($Y10=1,$J10*(1-N($L10)),"") | AA10: =IF($Y10=1,IF($K10="TTC",$Z10/(1+$V10),$Z10),"") | AB10: =IF($Y10=1,IF($K10="TTC",$Z10-$AA10,$AA10*$V10),"") | AC10: =IF($Y10=1,$AA10*$U10*$M10,"") | AD10: =IF($Y10=1,$AC10/SUMIFS($AC$6:$AC$205,$C$6:$C$205,$C10,$Y$6:$Y$205,1),"") | AE10: =IF($Y10=1,(INDEX(Fournisseurs!$J$5:$J$24,MATCH($C10,Fournisseurs!$A$5:$A$24,0))+INDEX(Fournisseurs!$K$5:$K$24,MATCH($C10,Fournisseurs!$A$5:$A$24,0)))*$U10*$AD10/($I10*$M10),"") | AF10: =IF($Y10=1,INDEX(Fournisseurs!$L$5:$L$24,MATCH($C10,Fournisseurs!$A$5:$A$24,0))*$AD10/($I10*$M10),"") | AG10: =IF($Y10=1,$AA10*$U10/$I10,"") | AH10: =IF($Y10=1,$AB10*$U10/$I10,"") | AI10: =IF($Y10=1,IF(AND(Paramètres!$B$4="EFFECTIVE",$W10="CH",$AB10>0),1,0),"") | AJ10: =IF($Y10=1,IF($X10<>"CH",($AG10+$AE10+$AF10)*Paramètres!$B$14,0),"") | AK10: =IF($Y10=1,$AG10+IF($AI10=1,0,$AH10)+$AE10+$AF10+IF(Paramètres!$B$4="NOT_REGISTERED",$AJ10,0),"") | AL10: =IF($Y10=1,($AK10+Paramètres!$B$7+Paramètres!$B$8+Paramètres!$B$9+Paramètres!$B$10)/((1-Paramètres!$B$11)/(1+Paramètres!$B$5)-Paramètres!$B$6),"") | AM10: =IF(AND($Y10=1,ISNUMBER($R10)),IF($R10>0,$AL10/$R10-1,""),"") | AN10: =IF(AND($Y10=1,ISNUMBER($R10)),IF($R10>0,$R10/(1+Paramètres!$B$5)-$AK10-($R10*Paramètres!$B$6+Paramètres!$B$7)-Paramètres!$B$8-Paramètres!$B$9-Paramètres!$B$10,""),"") | AO10: =IF(ISNUMBER($AN10),$AN10/($R10/(1+Paramètres!$B$5)),"") | AP10: =IF($A10="","",IF($Y10<>1,"INCOMPLET",IF(NOT(ISNUMBER($AM10)),"SANS RÉF. MARCHÉ",IF($AM10<=Paramètres!$B$12,"OK",IF(AND($AO10>=Paramètres!$B$15,$AN10>=Paramètres!$B$16),"À REVOIR","NON RENTABLE"))))) -> INCOMPLET | AQ10: =TRIM(IF(AND($Y10=1,ISNUMBER($N10)),IF($M10<$N10,"MOQ ",""),"")&IF(AND($Y10=1,ISNUMBER($O10)),IF($O10<$I10*$M10,"DISPO ",""),"")&IF($S10="O","FICTIF ","")&IF($Y10=1,IF(AND($K10="TTC",$W10<>"CH"),"TVA-ÉTRANGÈRE ",""),"")) | AR10: =IF($Y10=1,COUNTIFS($A$6:$A$205,$A10,$AK$6:$AK$205,"<"&$AK10,$Y$6:$Y$205,1)+1,"") | AS10: =IF(ISNUMBER($AR10),$A10&"|"&$AR10,"") | AT10: =IF($Y10=1,$AK10*$I10*$M10,"")
A11: REF-07 | B11: Coffret Dresseur d'Élite (ETB) Méga-Évolution – Nuit Noire – FR | C11: Asmodee France | G11: Méga-Évolution – Nuit Noire | H11: etb | S11: N | T11: =IF($C11="","",IFERROR(INDEX(Fournisseurs!$C$5:$C$24,MATCH($C11,Fournisseurs!$A$5:$A$24,0)),"")) -> 0 | U11: =IF($C11="","",IFERROR(INDEX(Fournisseurs!$D$5:$D$24,MATCH($C11,Fournisseurs!$A$5:$A$24,0)),"")) -> 0 | V11: =IF($C11="","",IFERROR(INDEX(Fournisseurs!$G$5:$G$24,MATCH($C11,Fournisseurs!$A$5:$A$24,0)),"")) -> 0 | W11: =IF($C11="","",IFERROR(INDEX(Fournisseurs!$H$5:$H$24,MATCH($C11,Fournisseurs!$A$5:$A$24,0)),"")) -> 0 | X11: =IF($C11="","",IFERROR(INDEX(Fournisseurs!$B$5:$B$24,MATCH($C11,Fournisseurs!$A$5:$A$24,0)),"")) -> 0 | Y11: =IF($A11="","",IF(AND($A11<>"",$C11<>"",ISNUMBER($I11),ISNUMBER($J11),ISNUMBER($M11)),IF(AND($I11>=1,$J11>0,OR($K11="HT",$K11="TTC"),$M11>=1,IFERROR(INDEX(Fournisseurs!$T$5:$T$24,MATCH($C11,Fournisseurs!$A$5:$A$24,0)),0)=1),1,0),0)) -> 0 | Z11: =IF($Y11=1,$J11*(1-N($L11)),"") | AA11: =IF($Y11=1,IF($K11="TTC",$Z11/(1+$V11),$Z11),"") | AB11: =IF($Y11=1,IF($K11="TTC",$Z11-$AA11,$AA11*$V11),"") | AC11: =IF($Y11=1,$AA11*$U11*$M11,"") | AD11: =IF($Y11=1,$AC11/SUMIFS($AC$6:$AC$205,$C$6:$C$205,$C11,$Y$6:$Y$205,1),"") | AE11: =IF($Y11=1,(INDEX(Fournisseurs!$J$5:$J$24,MATCH($C11,Fournisseurs!$A$5:$A$24,0))+INDEX(Fournisseurs!$K$5:$K$24,MATCH($C11,Fournisseurs!$A$5:$A$24,0)))*$U11*$AD11/($I11*$M11),"") | AF11: =IF($Y11=1,INDEX(Fournisseurs!$L$5:$L$24,MATCH($C11,Fournisseurs!$A$5:$A$24,0))*$AD11/($I11*$M11),"") | AG11: =IF($Y11=1,$AA11*$U11/$I11,"") | AH11: =IF($Y11=1,$AB11*$U11/$I11,"") | AI11: =IF($Y11=1,IF(AND(Paramètres!$B$4="EFFECTIVE",$W11="CH",$AB11>0),1,0),"") | AJ11: =IF($Y11=1,IF($X11<>"CH",($AG11+$AE11+$AF11)*Paramètres!$B$14,0),"") | AK11: =IF($Y11=1,$AG11+IF($AI11=1,0,$AH11)+$AE11+$AF11+IF(Paramètres!$B$4="NOT_REGISTERED",$AJ11,0),"") | AL11: =IF($Y11=1,($AK11+Paramètres!$B$7+Paramètres!$B$8+Paramètres!$B$9+Paramètres!$B$10)/((1-Paramètres!$B$11)/(1+Paramètres!$B$5)-Paramètres!$B$6),"") | AM11: =IF(AND($Y11=1,ISNUMBER($R11)),IF($R11>0,$AL11/$R11-1,""),"") | AN11: =IF(AND($Y11=1,ISNUMBER($R11)),IF($R11>0,$R11/(1+Paramètres!$B$5)-$AK11-($R11*Paramètres!$B$6+Paramètres!$B$7)-Paramètres!$B$8-Paramètres!$B$9-Paramètres!$B$10,""),"") | AO11: =IF(ISNUMBER($AN11),$AN11/($R11/(1+Paramètres!$B$5)),"") | AP11: =IF($A11="","",IF($Y11<>1,"INCOMPLET",IF(NOT(ISNUMBER($AM11)),"SANS RÉF. MARCHÉ",IF($AM11<=Paramètres!$B$12,"OK",IF(AND($AO11>=Paramètres!$B$15,$AN11>=Paramètres!$B$16),"À REVOIR","NON RENTABLE"))))) -> INCOMPLET | AQ11: =TRIM(IF(AND($Y11=1,ISNUMBER($N11)),IF($M11<$N11,"MOQ ",""),"")&IF(AND($Y11=1,ISNUMBER($O11)),IF($O11<$I11*$M11,"DISPO ",""),"")&IF($S11="O","FICTIF ","")&IF($Y11=1,IF(AND($K11="TTC",$W11<>"CH"),"TVA-ÉTRANGÈRE ",""),"")) | AR11: =IF($Y11=1,COUNTIFS($A$6:$A$205,$A11,$AK$6:$AK$205,"<"&$AK11,$Y$6:$Y$205,1)+1,"") | AS11: =IF(ISNUMBER($AR11),$A11&"|"&$AR11,"") | AT11: =IF($Y11=1,$AK11*$I11*$M11,"")
A12: REF-11 | B12: Coffret Dresseur d'Élite (ETB) Méga-Évolution – Équilibre Parfait – FR | C12: Asmodee France | G12: Méga-Évolution – Équilibre Parfait | H12: etb | S12: N | T12: =IF($C12="","",IFERROR(INDEX(Fournisseurs!$C$5:$C$24,MATCH($C12,Fournisseurs!$A$5:$A$24,0)),"")) -> 0 | U12: =IF($C12="","",IFERROR(INDEX(Fournisseurs!$D$5:$D$24,MATCH($C12,Fournisseurs!$A$5:$A$24,0)),"")) -> 0 | V12: =IF($C12="","",IFERROR(INDEX(Fournisseurs!$G$5:$G$24,MATCH($C12,Fournisseurs!$A$5:$A$24,0)),"")) -> 0 | W12: =IF($C12="","",IFERROR(INDEX(Fournisseurs!$H$5:$H$24,MATCH($C12,Fournisseurs!$A$5:$A$24,0)),"")) -> 0 | X12: =IF($C12="","",IFERROR(INDEX(Fournisseurs!$B$5:$B$24,MATCH($C12,Fournisseurs!$A$5:$A$24,0)),"")) -> 0 | Y12: =IF($A12="","",IF(AND($A12<>"",$C12<>"",ISNUMBER($I12),ISNUMBER($J12),ISNUMBER($M12)),IF(AND($I12>=1,$J12>0,OR($K12="HT",$K12="TTC"),$M12>=1,IFERROR(INDEX(Fournisseurs!$T$5:$T$24,MATCH($C12,Fournisseurs!$A$5:$A$24,0)),0)=1),1,0),0)) -> 0 | Z12: =IF($Y12=1,$J12*(1-N($L12)),"") | AA12: =IF($Y12=1,IF($K12="TTC",$Z12/(1+$V12),$Z12),"") | AB12: =IF($Y12=1,IF($K12="TTC",$Z12-$AA12,$AA12*$V12),"") | AC12: =IF($Y12=1,$AA12*$U12*$M12,"") | AD12: =IF($Y12=1,$AC12/SUMIFS($AC$6:$AC$205,$C$6:$C$205,$C12,$Y$6:$Y$205,1),"") | AE12: =IF($Y12=1,(INDEX(Fournisseurs!$J$5:$J$24,MATCH($C12,Fournisseurs!$A$5:$A$24,0))+INDEX(Fournisseurs!$K$5:$K$24,MATCH($C12,Fournisseurs!$A$5:$A$24,0)))*$U12*$AD12/($I12*$M12),"") | AF12: =IF($Y12=1,INDEX(Fournisseurs!$L$5:$L$24,MATCH($C12,Fournisseurs!$A$5:$A$24,0))*$AD12/($I12*$M12),"") | AG12: =IF($Y12=1,$AA12*$U12/$I12,"") | AH12: =IF($Y12=1,$AB12*$U12/$I12,"") | AI12: =IF($Y12=1,IF(AND(Paramètres!$B$4="EFFECTIVE",$W12="CH",$AB12>0),1,0),"") | AJ12: =IF($Y12=1,IF($X12<>"CH",($AG12+$AE12+$AF12)*Paramètres!$B$14,0),"") | AK12: =IF($Y12=1,$AG12+IF($AI12=1,0,$AH12)+$AE12+$AF12+IF(Paramètres!$B$4="NOT_REGISTERED",$AJ12,0),"") | AL12: =IF($Y12=1,($AK12+Paramètres!$B$7+Paramètres!$B$8+Paramètres!$B$9+Paramètres!$B$10)/((1-Paramètres!$B$11)/(1+Paramètres!$B$5)-Paramètres!$B$6),"") | AM12: =IF(AND($Y12=1,ISNUMBER($R12)),IF($R12>0,$AL12/$R12-1,""),"") | AN12: =IF(AND($Y12=1,ISNUMBER($R12)),IF($R12>0,$R12/(1+Paramètres!$B$5)-$AK12-($R12*Paramètres!$B$6+Paramètres!$B$7)-Paramètres!$B$8-Paramètres!$B$9-Paramètres!$B$10,""),"") | AO12: =IF(ISNUMBER($AN12),$AN12/($R12/(1+Paramètres!$B$5)),"") | AP12: =IF($A12="","",IF($Y12<>1,"INCOMPLET",IF(NOT(ISNUMBER($AM12)),"SANS RÉF. MARCHÉ",IF($AM12<=Paramètres!$B$12,"OK",IF(AND($AO12>=Paramètres!$B$15,$AN12>=Paramètres!$B$16),"À REVOIR","NON RENTABLE"))))) -> INCOMPLET | AQ12: =TRIM(IF(AND($Y12=1,ISNUMBER($N12)),IF($M12<$N12,"MOQ ",""),"")&IF(AND($Y12=1,ISNUMBER($O12)),IF($O12<$I12*$M12,"DISPO ",""),"")&IF($S12="O","FICTIF ","")&IF($Y12=1,IF(AND($K12="TTC",$W12<>"CH"),"TVA-ÉTRANGÈRE ",""),"")) | AR12: =IF($Y12=1,COUNTIFS($A$6:$A$205,$A12,$AK$6:$AK$205,"<"&$AK12,$Y$6:$Y$205,1)+1,"") | AS12: =IF(ISNUMBER($AR12),$A12&"|"&$AR12,"") | AT12: =IF($Y12=1,$AK12*$I12*$M12,"")
A13: REF-02 | B13: Bundle 30ᵉ Anniversaire – FR | C13: Asmodee France | G13: 30ᵉ Anniversaire | H13: bundle | S13: N | T13: =IF($C13="","",IFERROR(INDEX(Fournisseurs!$C$5:$C$24,MATCH($C13,Fournisseurs!$A$5:$A$24,0)),"")) -> 0 | U13: =IF($C13="","",IFERROR(INDEX(Fournisseurs!$D$5:$D$24,MATCH($C13,Fournisseurs!$A$5:$A$24,0)),"")) -> 0 | V13: =IF($C13="","",IFERROR(INDEX(Fournisseurs!$G$5:$G$24,MATCH($C13,Fournisseurs!$A$5:$A$24,0)),"")) -> 0 | W13: =IF($C13="","",IFERROR(INDEX(Fournisseurs!$H$5:$H$24,MATCH($C13,Fournisseurs!$A$5:$A$24,0)),"")) -> 0 | X13: =IF($C13="","",IFERROR(INDEX(Fournisseurs!$B$5:$B$24,MATCH($C13,Fournisseurs!$A$5:$A$24,0)),"")) -> 0 | Y13: =IF($A13="","",IF(AND($A13<>"",$C13<>"",ISNUMBER($I13),ISNUMBER($J13),ISNUMBER($M13)),IF(AND($I13>=1,$J13>0,OR($K13="HT",$K13="TTC"),$M13>=1,IFERROR(INDEX(Fournisseurs!$T$5:$T$24,MATCH($C13,Fournisseurs!$A$5:$A$24,0)),0)=1),1,0),0)) -> 0 | Z13: =IF($Y13=1,$J13*(1-N($L13)),"") | AA13: =IF($Y13=1,IF($K13="TTC",$Z13/(1+$V13),$Z13),"") | AB13: =IF($Y13=1,IF($K13="TTC",$Z13-$AA13,$AA13*$V13),"") | AC13: =IF($Y13=1,$AA13*$U13*$M13,"") | AD13: =IF($Y13=1,$AC13/SUMIFS($AC$6:$AC$205,$C$6:$C$205,$C13,$Y$6:$Y$205,1),"") | AE13: =IF($Y13=1,(INDEX(Fournisseurs!$J$5:$J$24,MATCH($C13,Fournisseurs!$A$5:$A$24,0))+INDEX(Fournisseurs!$K$5:$K$24,MATCH($C13,Fournisseurs!$A$5:$A$24,0)))*$U13*$AD13/($I13*$M13),"") | AF13: =IF($Y13=1,INDEX(Fournisseurs!$L$5:$L$24,MATCH($C13,Fournisseurs!$A$5:$A$24,0))*$AD13/($I13*$M13),"") | AG13: =IF($Y13=1,$AA13*$U13/$I13,"") | AH13: =IF($Y13=1,$AB13*$U13/$I13,"") | AI13: =IF($Y13=1,IF(AND(Paramètres!$B$4="EFFECTIVE",$W13="CH",$AB13>0),1,0),"") | AJ13: =IF($Y13=1,IF($X13<>"CH",($AG13+$AE13+$AF13)*Paramètres!$B$14,0),"") | AK13: =IF($Y13=1,$AG13+IF($AI13=1,0,$AH13)+$AE13+$AF13+IF(Paramètres!$B$4="NOT_REGISTERED",$AJ13,0),"") | AL13: =IF($Y13=1,($AK13+Paramètres!$B$7+Paramètres!$B$8+Paramètres!$B$9+Paramètres!$B$10)/((1-Paramètres!$B$11)/(1+Paramètres!$B$5)-Paramètres!$B$6),"") | AM13: =IF(AND($Y13=1,ISNUMBER($R13)),IF($R13>0,$AL13/$R13-1,""),"") | AN13: =IF(AND($Y13=1,ISNUMBER($R13)),IF($R13>0,$R13/(1+Paramètres!$B$5)-$AK13-($R13*Paramètres!$B$6+Paramètres!$B$7)-Paramètres!$B$8-Paramètres!$B$9-Paramètres!$B$10,""),"") | AO13: =IF(ISNUMBER($AN13),$AN13/($R13/(1+Paramètres!$B$5)),"") | AP13: =IF($A13="","",IF($Y13<>1,"INCOMPLET",IF(NOT(ISNUMBER($AM13)),"SANS RÉF. MARCHÉ",IF($AM13<=Paramètres!$B$12,"OK",IF(AND($AO13>=Paramètres!$B$15,$AN13>=Paramètres!$B$16),"À REVOIR","NON RENTABLE"))))) -> INCOMPLET | AQ13: =TRIM(IF(AND($Y13=1,ISNUMBER($N13)),IF($M13<$N13,"MOQ ",""),"")&IF(AND($Y13=1,ISNUMBER($O13)),IF($O13<$I13*$M13,"DISPO ",""),"")&IF($S13="O","FICTIF ","")&IF($Y13=1,IF(AND($K13="TTC",$W13<>"CH"),"TVA-ÉTRANGÈRE ",""),"")) | AR13: =IF($Y13=1,COUNTIFS($A$6:$A$205,$A13,$AK$6:$AK$205,"<"&$AK13,$Y$6:$Y$205,1)+1,"") | AS13: =IF(ISNUMBER($AR13),$A13&"|"&$AR13,"") | AT13: =IF($Y13=1,$AK13*$I13*$M13,"")
A14: REF-08 | B14: Tripack Méga-Évolution – Nuit Noire – FR | C14: Asmodee France | G14: Méga-Évolution – Nuit Noire | H14: tripack | S14: N | T14: =IF($C14="","",IFERROR(INDEX(Fournisseurs!$C$5:$C$24,MATCH($C14,Fournisseurs!$A$5:$A$24,0)),"")) -> 0 | U14: =IF($C14="","",IFERROR(INDEX(Fournisseurs!$D$5:$D$24,MATCH($C14,Fournisseurs!$A$5:$A$24,0)),"")) -> 0 | V14: =IF($C14="","",IFERROR(INDEX(Fournisseurs!$G$5:$G$24,MATCH($C14,Fournisseurs!$A$5:$A$24,0)),"")) -> 0 | W14: =IF($C14="","",IFERROR(INDEX(Fournisseurs!$H$5:$H$24,MATCH($C14,Fournisseurs!$A$5:$A$24,0)),"")) -> 0 | X14: =IF($C14="","",IFERROR(INDEX(Fournisseurs!$B$5:$B$24,MATCH($C14,Fournisseurs!$A$5:$A$24,0)),"")) -> 0 | Y14: =IF($A14="","",IF(AND($A14<>"",$C14<>"",ISNUMBER($I14),ISNUMBER($J14),ISNUMBER($M14)),IF(AND($I14>=1,$J14>0,OR($K14="HT",$K14="TTC"),$M14>=1,IFERROR(INDEX(Fournisseurs!$T$5:$T$24,MATCH($C14,Fournisseurs!$A$5:$A$24,0)),0)=1),1,0),0)) -> 0 | Z14: =IF($Y14=1,$J14*(1-N($L14)),"") | AA14: =IF($Y14=1,IF($K14="TTC",$Z14/(1+$V14),$Z14),"") | AB14: =IF($Y14=1,IF($K14="TTC",$Z14-$AA14,$AA14*$V14),"") | AC14: =IF($Y14=1,$AA14*$U14*$M14,"") | AD14: =IF($Y14=1,$AC14/SUMIFS($AC$6:$AC$205,$C$6:$C$205,$C14,$Y$6:$Y$205,1),"") | AE14: =IF($Y14=1,(INDEX(Fournisseurs!$J$5:$J$24,MATCH($C14,Fournisseurs!$A$5:$A$24,0))+INDEX(Fournisseurs!$K$5:$K$24,MATCH($C14,Fournisseurs!$A$5:$A$24,0)))*$U14*$AD14/($I14*$M14),"") | AF14: =IF($Y14=1,INDEX(Fournisseurs!$L$5:$L$24,MATCH($C14,Fournisseurs!$A$5:$A$24,0))*$AD14/($I14*$M14),"") | AG14: =IF($Y14=1,$AA14*$U14/$I14,"") | AH14: =IF($Y14=1,$AB14*$U14/$I14,"") | AI14: =IF($Y14=1,IF(AND(Paramètres!$B$4="EFFECTIVE",$W14="CH",$AB14>0),1,0),"") | AJ14: =IF($Y14=1,IF($X14<>"CH",($AG14+$AE14+$AF14)*Paramètres!$B$14,0),"") | AK14: =IF($Y14=1,$AG14+IF($AI14=1,0,$AH14)+$AE14+$AF14+IF(Paramètres!$B$4="NOT_REGISTERED",$AJ14,0),"") | AL14: =IF($Y14=1,($AK14+Paramètres!$B$7+Paramètres!$B$8+Paramètres!$B$9+Paramètres!$B$10)/((1-Paramètres!$B$11)/(1+Paramètres!$B$5)-Paramètres!$B$6),"") | AM14: =IF(AND($Y14=1,ISNUMBER($R14)),IF($R14>0,$AL14/$R14-1,""),"") | AN14: =IF(AND($Y14=1,ISNUMBER($R14)),IF($R14>0,$R14/(1+Paramètres!$B$5)-$AK14-($R14*Paramètres!$B$6+Paramètres!$B$7)-Paramètres!$B$8-Paramètres!$B$9-Paramètres!$B$10,""),"") | AO14: =IF(ISNUMBER($AN14),$AN14/($R14/(1+Paramètres!$B$5)),"") | AP14: =IF($A14="","",IF($Y14<>1,"INCOMPLET",IF(NOT(ISNUMBER($AM14)),"SANS RÉF. MARCHÉ",IF($AM14<=Paramètres!$B$12,"OK",IF(AND($AO14>=Paramètres!$B$15,$AN14>=Paramètres!$B$16),"À REVOIR","NON RENTABLE"))))) -> INCOMPLET | AQ14: =TRIM(IF(AND($Y14=1,ISNUMBER($N14)),IF($M14<$N14,"MOQ ",""),"")&IF(AND($Y14=1,ISNUMBER($O14)),IF($O14<$I14*$M14,"DISPO ",""),"")&IF($S14="O","FICTIF ","")&IF($Y14=1,IF(AND($K14="TTC",$W14<>"CH"),"TVA-ÉTRANGÈRE ",""),"")) | AR14: =IF($Y14=1,COUNTIFS($A$6:$A$205,$A14,$AK$6:$AK$205,"<"&$AK14,$Y$6:$Y$205,1)+1,"") | AS14: =IF(ISNUMBER($AR14),$A14&"|"&$AR14,"") | AT14: =IF($Y14=1,$AK14*$I14*$M14,"")
A15: REF-19 | B15: Tripack ou bundle Méga-Évolution – Chaos Ascendant – FR | C15: Asmodee France | G15: Méga-Évolution – Chaos Ascendant | H15: tripack | S15: N | T15: =IF($C15="","",IFERROR(INDEX(Fournisseurs!$C$5:$C$24,MATCH($C15,Fournisseurs!$A$5:$A$24,0)),"")) -> 0 | U15: =IF($C15="","",IFERROR(INDEX(Fournisseurs!$D$5:$D$24,MATCH($C15,Fournisseurs!$A$5:$A$24,0)),"")) -> 0 | V15: =IF($C15="","",IFERROR(INDEX(Fournisseurs!$G$5:$G$24,MATCH($C15,Fournisseurs!$A$5:$A$24,0)),"")) -> 0 | W15: =IF($C15="","",IFERROR(INDEX(Fournisseurs!$H$5:$H$24,MATCH($C15,Fournisseurs!$A$5:$A$24,0)),"")) -> 0 | X15: =IF($C15="","",IFERROR(INDEX(Fournisseurs!$B$5:$B$24,MATCH($C15,Fournisseurs!$A$5:$A$24,0)),"")) -> 0 | Y15: =IF($A15="","",IF(AND($A15<>"",$C15<>"",ISNUMBER($I15),ISNUMBER($J15),ISNUMBER($M15)),IF(AND($I15>=1,$J15>0,OR($K15="HT",$K15="TTC"),$M15>=1,IFERROR(INDEX(Fournisseurs!$T$5:$T$24,MATCH($C15,Fournisseurs!$A$5:$A$24,0)),0)=1),1,0),0)) -> 0 | Z15: =IF($Y15=1,$J15*(1-N($L15)),"") | AA15: =IF($Y15=1,IF($K15="TTC",$Z15/(1+$V15),$Z15),"") | AB15: =IF($Y15=1,IF($K15="TTC",$Z15-$AA15,$AA15*$V15),"") | AC15: =IF($Y15=1,$AA15*$U15*$M15,"") | AD15: =IF($Y15=1,$AC15/SUMIFS($AC$6:$AC$205,$C$6:$C$205,$C15,$Y$6:$Y$205,1),"") | AE15: =IF($Y15=1,(INDEX(Fournisseurs!$J$5:$J$24,MATCH($C15,Fournisseurs!$A$5:$A$24,0))+INDEX(Fournisseurs!$K$5:$K$24,MATCH($C15,Fournisseurs!$A$5:$A$24,0)))*$U15*$AD15/($I15*$M15),"") | AF15: =IF($Y15=1,INDEX(Fournisseurs!$L$5:$L$24,MATCH($C15,Fournisseurs!$A$5:$A$24,0))*$AD15/($I15*$M15),"") | AG15: =IF($Y15=1,$AA15*$U15/$I15,"") | AH15: =IF($Y15=1,$AB15*$U15/$I15,"") | AI15: =IF($Y15=1,IF(AND(Paramètres!$B$4="EFFECTIVE",$W15="CH",$AB15>0),1,0),"") | AJ15: =IF($Y15=1,IF($X15<>"CH",($AG15+$AE15+$AF15)*Paramètres!$B$14,0),"") | AK15: =IF($Y15=1,$AG15+IF($AI15=1,0,$AH15)+$AE15+$AF15+IF(Paramètres!$B$4="NOT_REGISTERED",$AJ15,0),"") | AL15: =IF($Y15=1,($AK15+Paramètres!$B$7+Paramètres!$B$8+Paramètres!$B$9+Paramètres!$B$10)/((1-Paramètres!$B$11)/(1+Paramètres!$B$5)-Paramètres!$B$6),"") | AM15: =IF(AND($Y15=1,ISNUMBER($R15)),IF($R15>0,$AL15/$R15-1,""),"") | AN15: =IF(AND($Y15=1,ISNUMBER($R15)),IF($R15>0,$R15/(1+Paramètres!$B$5)-$AK15-($R15*Paramètres!$B$6+Paramètres!$B$7)-Paramètres!$B$8-Paramètres!$B$9-Paramètres!$B$10,""),"") | AO15: =IF(ISNUMBER($AN15),$AN15/($R15/(1+Paramètres!$B$5)),"") | AP15: =IF($A15="","",IF($Y15<>1,"INCOMPLET",IF(NOT(ISNUMBER($AM15)),"SANS RÉF. MARCHÉ",IF($AM15<=Paramètres!$B$12,"OK",IF(AND($AO15>=Paramètres!$B$15,$AN15>=Paramètres!$B$16),"À REVOIR","NON RENTABLE"))))) -> INCOMPLET | AQ15: =TRIM(IF(AND($Y15=1,ISNUMBER($N15)),IF($M15<$N15,"MOQ ",""),"")&IF(AND($Y15=1,ISNUMBER($O15)),IF($O15<$I15*$M15,"DISPO ",""),"")&IF($S15="O","FICTIF ","")&IF($Y15=1,IF(AND($K15="TTC",$W15<>"CH"),"TVA-ÉTRANGÈRE ",""),"")) | AR15: =IF($Y15=1,COUNTIFS($A$6:$A$205,$A15,$AK$6:$AK$205,"<"&$AK15,$Y$6:$Y$205,1)+1,"") | AS15: =IF(ISNUMBER($AR15),$A15&"|"&$AR15,"") | AT15: =IF($Y15=1,$AK15*$I15*$M15,"")
A16: REF-04 | B16: Coffret 30ᵉ Anniversaire Nymphali-ex – FR | C16: Asmodee France | G16: 30ᵉ Anniversaire | H16: coffret | S16: N | T16: =IF($C16="","",IFERROR(INDEX(Fournisseurs!$C$5:$C$24,MATCH($C16,Fournisseurs!$A$5:$A$24,0)),"")) -> 0 | U16: =IF($C16="","",IFERROR(INDEX(Fournisseurs!$D$5:$D$24,MATCH($C16,Fournisseurs!$A$5:$A$24,0)),"")) -> 0 | V16: =IF($C16="","",IFERROR(INDEX(Fournisseurs!$G$5:$G$24,MATCH($C16,Fournisseurs!$A$5:$A$24,0)),"")) -> 0 | W16: =IF($C16="","",IFERROR(INDEX(Fournisseurs!$H$5:$H$24,MATCH($C16,Fournisseurs!$A$5:$A$24,0)),"")) -> 0 | X16: =IF($C16="","",IFERROR(INDEX(Fournisseurs!$B$5:$B$24,MATCH($C16,Fournisseurs!$A$5:$A$24,0)),"")) -> 0 | Y16: =IF($A16="","",IF(AND($A16<>"",$C16<>"",ISNUMBER($I16),ISNUMBER($J16),ISNUMBER($M16)),IF(AND($I16>=1,$J16>0,OR($K16="HT",$K16="TTC"),$M16>=1,IFERROR(INDEX(Fournisseurs!$T$5:$T$24,MATCH($C16,Fournisseurs!$A$5:$A$24,0)),0)=1),1,0),0)) -> 0 | Z16: =IF($Y16=1,$J16*(1-N($L16)),"") | AA16: =IF($Y16=1,IF($K16="TTC",$Z16/(1+$V16),$Z16),"") | AB16: =IF($Y16=1,IF($K16="TTC",$Z16-$AA16,$AA16*$V16),"") | AC16: =IF($Y16=1,$AA16*$U16*$M16,"") | AD16: =IF($Y16=1,$AC16/SUMIFS($AC$6:$AC$205,$C$6:$C$205,$C16,$Y$6:$Y$205,1),"") | AE16: =IF($Y16=1,(INDEX(Fournisseurs!$J$5:$J$24,MATCH($C16,Fournisseurs!$A$5:$A$24,0))+INDEX(Fournisseurs!$K$5:$K$24,MATCH($C16,Fournisseurs!$A$5:$A$24,0)))*$U16*$AD16/($I16*$M16),"") | AF16: =IF($Y16=1,INDEX(Fournisseurs!$L$5:$L$24,MATCH($C16,Fournisseurs!$A$5:$A$24,0))*$AD16/($I16*$M16),"") | AG16: =IF($Y16=1,$AA16*$U16/$I16,"") | AH16: =IF($Y16=1,$AB16*$U16/$I16,"") | AI16: =IF($Y16=1,IF(AND(Paramètres!$B$4="EFFECTIVE",$W16="CH",$AB16>0),1,0),"") | AJ16: =IF($Y16=1,IF($X16<>"CH",($AG16+$AE16+$AF16)*Paramètres!$B$14,0),"") | AK16: =IF($Y16=1,$AG16+IF($AI16=1,0,$AH16)+$AE16+$AF16+IF(Paramètres!$B$4="NOT_REGISTERED",$AJ16,0),"") | AL16: =IF($Y16=1,($AK16+Paramètres!$B$7+Paramètres!$B$8+Paramètres!$B$9+Paramètres!$B$10)/((1-Paramètres!$B$11)/(1+Paramètres!$B$5)-Paramètres!$B$6),"") | AM16: =IF(AND($Y16=1,ISNUMBER($R16)),IF($R16>0,$AL16/$R16-1,""),"") | AN16: =IF(AND($Y16=1,ISNUMBER($R16)),IF($R16>0,$R16/(1+Paramètres!$B$5)-$AK16-($R16*Paramètres!$B$6+Paramètres!$B$7)-Paramètres!$B$8-Paramètres!$B$9-Paramètres!$B$10,""),"") | AO16: =IF(ISNUMBER($AN16),$AN16/($R16/(1+Paramètres!$B$5)),"") | AP16: =IF($A16="","",IF($Y16<>1,"INCOMPLET",IF(NOT(ISNUMBER($AM16)),"SANS RÉF. MARCHÉ",IF($AM16<=Paramètres!$B$12,"OK",IF(AND($AO16>=Paramètres!$B$15,$AN16>=Paramètres!$B$16),"À REVOIR","NON RENTABLE"))))) -> INCOMPLET | AQ16: =TRIM(IF(AND($Y16=1,ISNUMBER($N16)),IF($M16<$N16,"MOQ ",""),"")&IF(AND($Y16=1,ISNUMBER($O16)),IF($O16<$I16*$M16,"DISPO ",""),"")&IF($S16="O","FICTIF ","")&IF($Y16=1,IF(AND($K16="TTC",$W16<>"CH"),"TVA-ÉTRANGÈRE ",""),"")) | AR16: =IF($Y16=1,COUNTIFS($A$6:$A$205,$A16,$AK$6:$AK$205,"<"&$AK16,$Y$6:$Y$205,1)+1,"") | AS16: =IF(ISNUMBER($AR16),$A16&"|"&$AR16,"") | AT16: =IF($Y16=1,$AK16*$I16*$M16,"")
A17: REF-20 | B17: Coffret ou collection – Équilibre Parfait ou Héros Transcendants – FR | C17: Asmodee France | G17: Méga-Évolution – Équilibre Parfait / Héros Transcendants | H17: coffret | S17: N | T17: =IF($C17="","",IFERROR(INDEX(Fournisseurs!$C$5:$C$24,MATCH($C17,Fournisseurs!$A$5:$A$24,0)),"")) -> 0 | U17: =IF($C17="","",IFERROR(INDEX(Fournisseurs!$D$5:$D$24,MATCH($C17,Fournisseurs!$A$5:$A$24,0)),"")) -> 0 | V17: =IF($C17="","",IFERROR(INDEX(Fournisseurs!$G$5:$G$24,MATCH($C17,Fournisseurs!$A$5:$A$24,0)),"")) -> 0 | W17: =IF($C17="","",IFERROR(INDEX(Fournisseurs!$H$5:$H$24,MATCH($C17,Fournisseurs!$A$5:$A$24,0)),"")) -> 0 | X17: =IF($C17="","",IFERROR(INDEX(Fournisseurs!$B$5:$B$24,MATCH($C17,Fournisseurs!$A$5:$A$24,0)),"")) -> 0 | Y17: =IF($A17="","",IF(AND($A17<>"",$C17<>"",ISNUMBER($I17),ISNUMBER($J17),ISNUMBER($M17)),IF(AND($I17>=1,$J17>0,OR($K17="HT",$K17="TTC"),$M17>=1,IFERROR(INDEX(Fournisseurs!$T$5:$T$24,MATCH($C17,Fournisseurs!$A$5:$A$24,0)),0)=1),1,0),0)) -> 0 | Z17: =IF($Y17=1,$J17*(1-N($L17)),"") | AA17: =IF($Y17=1,IF($K17="TTC",$Z17/(1+$V17),$Z17),"") | AB17: =IF($Y17=1,IF($K17="TTC",$Z17-$AA17,$AA17*$V17),"") | AC17: =IF($Y17=1,$AA17*$U17*$M17,"") | AD17: =IF($Y17=1,$AC17/SUMIFS($AC$6:$AC$205,$C$6:$C$205,$C17,$Y$6:$Y$205,1),"") | AE17: =IF($Y17=1,(INDEX(Fournisseurs!$J$5:$J$24,MATCH($C17,Fournisseurs!$A$5:$A$24,0))+INDEX(Fournisseurs!$K$5:$K$24,MATCH($C17,Fournisseurs!$A$5:$A$24,0)))*$U17*$AD17/($I17*$M17),"") | AF17: =IF($Y17=1,INDEX(Fournisseurs!$L$5:$L$24,MATCH($C17,Fournisseurs!$A$5:$A$24,0))*$AD17/($I17*$M17),"") | AG17: =IF($Y17=1,$AA17*$U17/$I17,"") | AH17: =IF($Y17=1,$AB17*$U17/$I17,"") | AI17: =IF($Y17=1,IF(AND(Paramètres!$B$4="EFFECTIVE",$W17="CH",$AB17>0),1,0),"") | AJ17: =IF($Y17=1,IF($X17<>"CH",($AG17+$AE17+$AF17)*Paramètres!$B$14,0),"") | AK17: =IF($Y17=1,$AG17+IF($AI17=1,0,$AH17)+$AE17+$AF17+IF(Paramètres!$B$4="NOT_REGISTERED",$AJ17,0),"") | AL17: =IF($Y17=1,($AK17+Paramètres!$B$7+Paramètres!$B$8+Paramètres!$B$9+Paramètres!$B$10)/((1-Paramètres!$B$11)/(1+Paramètres!$B$5)-Paramètres!$B$6),"") | AM17: =IF(AND($Y17=1,ISNUMBER($R17)),IF($R17>0,$AL17/$R17-1,""),"") | AN17: =IF(AND($Y17=1,ISNUMBER($R17)),IF($R17>0,$R17/(1+Paramètres!$B$5)-$AK17-($R17*Paramètres!$B$6+Paramètres!$B$7)-Paramètres!$B$8-Paramètres!$B$9-Paramètres!$B$10,""),"") | AO17: =IF(ISNUMBER($AN17),$AN17/($R17/(1+Paramètres!$B$5)),"") | AP17: =IF($A17="","",IF($Y17<>1,"INCOMPLET",IF(NOT(ISNUMBER($AM17)),"SANS RÉF. MARCHÉ",IF($AM17<=Paramètres!$B$12,"OK",IF(AND($AO17>=Paramètres!$B$15,$AN17>=Paramètres!$B$16),"À REVOIR","NON RENTABLE"))))) -> INCOMPLET | AQ17: =TRIM(IF(AND($Y17=1,ISNUMBER($N17)),IF($M17<$N17,"MOQ ",""),"")&IF(AND($Y17=1,ISNUMBER($O17)),IF($O17<$I17*$M17,"DISPO ",""),"")&IF($S17="O","FICTIF ","")&IF($Y17=1,IF(AND($K17="TTC",$W17<>"CH"),"TVA-ÉTRANGÈRE ",""),"")) | AR17: =IF($Y17=1,COUNTIFS($A$6:$A$205,$A17,$AK$6:$AK$205,"<"&$AK17,$Y$6:$Y$205,1)+1,"") | AS17: =IF(ISNUMBER($AR17),$A17&"|"&$AR17,"") | AT17: =IF($Y17=1,$AK17*$I17*$M17,"")
A18: REF-16 | B18: Protège-cartes format standard (paquet) | C18: Asmodee France | H18: accessoire | S18: N | T18: =IF($C18="","",IFERROR(INDEX(Fournisseurs!$C$5:$C$24,MATCH($C18,Fournisseurs!$A$5:$A$24,0)),"")) -> 0 | U18: =IF($C18="","",IFERROR(INDEX(Fournisseurs!$D$5:$D$24,MATCH($C18,Fournisseurs!$A$5:$A$24,0)),"")) -> 0 | V18: =IF($C18="","",IFERROR(INDEX(Fournisseurs!$G$5:$G$24,MATCH($C18,Fournisseurs!$A$5:$A$24,0)),"")) -> 0 | W18: =IF($C18="","",IFERROR(INDEX(Fournisseurs!$H$5:$H$24,MATCH($C18,Fournisseurs!$A$5:$A$24,0)),"")) -> 0 | X18: =IF($C18="","",IFERROR(INDEX(Fournisseurs!$B$5:$B$24,MATCH($C18,Fournisseurs!$A$5:$A$24,0)),"")) -> 0 | Y18: =IF($A18="","",IF(AND($A18<>"",$C18<>"",ISNUMBER($I18),ISNUMBER($J18),ISNUMBER($M18)),IF(AND($I18>=1,$J18>0,OR($K18="HT",$K18="TTC"),$M18>=1,IFERROR(INDEX(Fournisseurs!$T$5:$T$24,MATCH($C18,Fournisseurs!$A$5:$A$24,0)),0)=1),1,0),0)) -> 0 | Z18: =IF($Y18=1,$J18*(1-N($L18)),"") | AA18: =IF($Y18=1,IF($K18="TTC",$Z18/(1+$V18),$Z18),"") | AB18: =IF($Y18=1,IF($K18="TTC",$Z18-$AA18,$AA18*$V18),"") | AC18: =IF($Y18=1,$AA18*$U18*$M18,"") | AD18: =IF($Y18=1,$AC18/SUMIFS($AC$6:$AC$205,$C$6:$C$205,$C18,$Y$6:$Y$205,1),"") | AE18: =IF($Y18=1,(INDEX(Fournisseurs!$J$5:$J$24,MATCH($C18,Fournisseurs!$A$5:$A$24,0))+INDEX(Fournisseurs!$K$5:$K$24,MATCH($C18,Fournisseurs!$A$5:$A$24,0)))*$U18*$AD18/($I18*$M18),"") | AF18: =IF($Y18=1,INDEX(Fournisseurs!$L$5:$L$24,MATCH($C18,Fournisseurs!$A$5:$A$24,0))*$AD18/($I18*$M18),"") | AG18: =IF($Y18=1,$AA18*$U18/$I18,"") | AH18: =IF($Y18=1,$AB18*$U18/$I18,"") | AI18: =IF($Y18=1,IF(AND(Paramètres!$B$4="EFFECTIVE",$W18="CH",$AB18>0),1,0),"") | AJ18: =IF($Y18=1,IF($X18<>"CH",($AG18+$AE18+$AF18)*Paramètres!$B$14,0),"") | AK18: =IF($Y18=1,$AG18+IF($AI18=1,0,$AH18)+$AE18+$AF18+IF(Paramètres!$B$4="NOT_REGISTERED",$AJ18,0),"") | AL18: =IF($Y18=1,($AK18+Paramètres!$B$7+Paramètres!$B$8+Paramètres!$B$9+Paramètres!$B$10)/((1-Paramètres!$B$11)/(1+Paramètres!$B$5)-Paramètres!$B$6),"") | AM18: =IF(AND($Y18=1,ISNUMBER($R18)),IF($R18>0,$AL18/$R18-1,""),"") | AN18: =IF(AND($Y18=1,ISNUMBER($R18)),IF($R18>0,$R18/(1+Paramètres!$B$5)-$AK18-($R18*Paramètres!$B$6+Paramètres!$B$7)-Paramètres!$B$8-Paramètres!$B$9-Paramètres!$B$10,""),"") | AO18: =IF(ISNUMBER($AN18),$AN18/($R18/(1+Paramètres!$B$5)),"") | AP18: =IF($A18="","",IF($Y18<>1,"INCOMPLET",IF(NOT(ISNUMBER($AM18)),"SANS RÉF. MARCHÉ",IF($AM18<=Paramètres!$B$12,"OK",IF(AND($AO18>=Paramètres!$B$15,$AN18>=Paramètres!$B$16),"À REVOIR","NON RENTABLE"))))) -> INCOMPLET | AQ18: =TRIM(IF(AND($Y18=1,ISNUMBER($N18)),IF($M18<$N18,"MOQ ",""),"")&IF(AND($Y18=1,ISNUMBER($O18)),IF($O18<$I18*$M18,"DISPO ",""),"")&IF($S18="O","FICTIF ","")&IF($Y18=1,IF(AND($K18="TTC",$W18<>"CH"),"TVA-ÉTRANGÈRE ",""),"")) | AR18: =IF($Y18=1,COUNTIFS($A$6:$A$205,$A18,$AK$6:$AK$205,"<"&$AK18,$Y$6:$Y$205,1)+1,"") | AS18: =IF(ISNUMBER($AR18),$A18&"|"&$AR18,"") | AT18: =IF($Y18=1,$AK18*$I18*$M18,"")
A19: REF-17 | B19: Classeur 9 cases | C19: Asmodee France | H19: accessoire | S19: N | T19: =IF($C19="","",IFERROR(INDEX(Fournisseurs!$C$5:$C$24,MATCH($C19,Fournisseurs!$A$5:$A$24,0)),"")) -> 0 | U19: =IF($C19="","",IFERROR(INDEX(Fournisseurs!$D$5:$D$24,MATCH($C19,Fournisseurs!$A$5:$A$24,0)),"")) -> 0 | V19: =IF($C19="","",IFERROR(INDEX(Fournisseurs!$G$5:$G$24,MATCH($C19,Fournisseurs!$A$5:$A$24,0)),"")) -> 0 | W19: =IF($C19="","",IFERROR(INDEX(Fournisseurs!$H$5:$H$24,MATCH($C19,Fournisseurs!$A$5:$A$24,0)),"")) -> 0 | X19: =IF($C19="","",IFERROR(INDEX(Fournisseurs!$B$5:$B$24,MATCH($C19,Fournisseurs!$A$5:$A$24,0)),"")) -> 0 | Y19: =IF($A19="","",IF(AND($A19<>"",$C19<>"",ISNUMBER($I19),ISNUMBER($J19),ISNUMBER($M19)),IF(AND($I19>=1,$J19>0,OR($K19="HT",$K19="TTC"),$M19>=1,IFERROR(INDEX(Fournisseurs!$T$5:$T$24,MATCH($C19,Fournisseurs!$A$5:$A$24,0)),0)=1),1,0),0)) -> 0 | Z19: =IF($Y19=1,$J19*(1-N($L19)),"") | AA19: =IF($Y19=1,IF($K19="TTC",$Z19/(1+$V19),$Z19),"") | AB19: =IF($Y19=1,IF($K19="TTC",$Z19-$AA19,$AA19*$V19),"") | AC19: =IF($Y19=1,$AA19*$U19*$M19,"") | AD19: =IF($Y19=1,$AC19/SUMIFS($AC$6:$AC$205,$C$6:$C$205,$C19,$Y$6:$Y$205,1),"") | AE19: =IF($Y19=1,(INDEX(Fournisseurs!$J$5:$J$24,MATCH($C19,Fournisseurs!$A$5:$A$24,0))+INDEX(Fournisseurs!$K$5:$K$24,MATCH($C19,Fournisseurs!$A$5:$A$24,0)))*$U19*$AD19/($I19*$M19),"") | AF19: =IF($Y19=1,INDEX(Fournisseurs!$L$5:$L$24,MATCH($C19,Fournisseurs!$A$5:$A$24,0))*$AD19/($I19*$M19),"") | AG19: =IF($Y19=1,$AA19*$U19/$I19,"") | AH19: =IF($Y19=1,$AB19*$U19/$I19,"") | AI19: =IF($Y19=1,IF(AND(Paramètres!$B$4="EFFECTIVE",$W19="CH",$AB19>0),1,0),"") | AJ19: =IF($Y19=1,IF($X19<>"CH",($AG19+$AE19+$AF19)*Paramètres!$B$14,0),"") | AK19: =IF($Y19=1,$AG19+IF($AI19=1,0,$AH19)+$AE19+$AF19+IF(Paramètres!$B$4="NOT_REGISTERED",$AJ19,0),"") | AL19: =IF($Y19=1,($AK19+Paramètres!$B$7+Paramètres!$B$8+Paramètres!$B$9+Paramètres!$B$10)/((1-Paramètres!$B$11)/(1+Paramètres!$B$5)-Paramètres!$B$6),"") | AM19: =IF(AND($Y19=1,ISNUMBER($R19)),IF($R19>0,$AL19/$R19-1,""),"") | AN19: =IF(AND($Y19=1,ISNUMBER($R19)),IF($R19>0,$R19/(1+Paramètres!$B$5)-$AK19-($R19*Paramètres!$B$6+Paramètres!$B$7)-Paramètres!$B$8-Paramètres!$B$9-Paramètres!$B$10,""),"") | AO19: =IF(ISNUMBER($AN19),$AN19/($R19/(1+Paramètres!$B$5)),"") | AP19: =IF($A19="","",IF($Y19<>1,"INCOMPLET",IF(NOT(ISNUMBER($AM19)),"SANS RÉF. MARCHÉ",IF($AM19<=Paramètres!$B$12,"OK",IF(AND($AO19>=Paramètres!$B$15,$AN19>=Paramètres!$B$16),"À REVOIR","NON RENTABLE"))))) -> INCOMPLET | AQ19: =TRIM(IF(AND($Y19=1,ISNUMBER($N19)),IF($M19<$N19,"MOQ ",""),"")&IF(AND($Y19=1,ISNUMBER($O19)),IF($O19<$I19*$M19,"DISPO ",""),"")&IF($S19="O","FICTIF ","")&IF($Y19=1,IF(AND($K19="TTC",$W19<>"CH"),"TVA-ÉTRANGÈRE ",""),"")) | AR19: =IF($Y19=1,COUNTIFS($A$6:$A$205,$A19,$AK$6:$AK$205,"<"&$AK19,$Y$6:$Y$205,1)+1,"") | AS19: =IF(ISNUMBER($AR19),$A19&"|"&$AR19,"") | AT19: =IF($Y19=1,$AK19*$I19*$M19,"")
A20: REF-03 | B20: Mini-Tin 30ᵉ Anniversaire – FR | C20: Asmodee France | G20: 30ᵉ Anniversaire | H20: coffret | S20: N | T20: =IF($C20="","",IFERROR(INDEX(Fournisseurs!$C$5:$C$24,MATCH($C20,Fournisseurs!$A$5:$A$24,0)),"")) -> 0 | U20: =IF($C20="","",IFERROR(INDEX(Fournisseurs!$D$5:$D$24,MATCH($C20,Fournisseurs!$A$5:$A$24,0)),"")) -> 0 | V20: =IF($C20="","",IFERROR(INDEX(Fournisseurs!$G$5:$G$24,MATCH($C20,Fournisseurs!$A$5:$A$24,0)),"")) -> 0 | W20: =IF($C20="","",IFERROR(INDEX(Fournisseurs!$H$5:$H$24,MATCH($C20,Fournisseurs!$A$5:$A$24,0)),"")) -> 0 | X20: =IF($C20="","",IFERROR(INDEX(Fournisseurs!$B$5:$B$24,MATCH($C20,Fournisseurs!$A$5:$A$24,0)),"")) -> 0 | Y20: =IF($A20="","",IF(AND($A20<>"",$C20<>"",ISNUMBER($I20),ISNUMBER($J20),ISNUMBER($M20)),IF(AND($I20>=1,$J20>0,OR($K20="HT",$K20="TTC"),$M20>=1,IFERROR(INDEX(Fournisseurs!$T$5:$T$24,MATCH($C20,Fournisseurs!$A$5:$A$24,0)),0)=1),1,0),0)) -> 0 | Z20: =IF($Y20=1,$J20*(1-N($L20)),"") | AA20: =IF($Y20=1,IF($K20="TTC",$Z20/(1+$V20),$Z20),"") | AB20: =IF($Y20=1,IF($K20="TTC",$Z20-$AA20,$AA20*$V20),"") | AC20: =IF($Y20=1,$AA20*$U20*$M20,"") | AD20: =IF($Y20=1,$AC20/SUMIFS($AC$6:$AC$205,$C$6:$C$205,$C20,$Y$6:$Y$205,1),"") | AE20: =IF($Y20=1,(INDEX(Fournisseurs!$J$5:$J$24,MATCH($C20,Fournisseurs!$A$5:$A$24,0))+INDEX(Fournisseurs!$K$5:$K$24,MATCH($C20,Fournisseurs!$A$5:$A$24,0)))*$U20*$AD20/($I20*$M20),"") | AF20: =IF($Y20=1,INDEX(Fournisseurs!$L$5:$L$24,MATCH($C20,Fournisseurs!$A$5:$A$24,0))*$AD20/($I20*$M20),"") | AG20: =IF($Y20=1,$AA20*$U20/$I20,"") | AH20: =IF($Y20=1,$AB20*$U20/$I20,"") | AI20: =IF($Y20=1,IF(AND(Paramètres!$B$4="EFFECTIVE",$W20="CH",$AB20>0),1,0),"") | AJ20: =IF($Y20=1,IF($X20<>"CH",($AG20+$AE20+$AF20)*Paramètres!$B$14,0),"") | AK20: =IF($Y20=1,$AG20+IF($AI20=1,0,$AH20)+$AE20+$AF20+IF(Paramètres!$B$4="NOT_REGISTERED",$AJ20,0),"") | AL20: =IF($Y20=1,($AK20+Paramètres!$B$7+Paramètres!$B$8+Paramètres!$B$9+Paramètres!$B$10)/((1-Paramètres!$B$11)/(1+Paramètres!$B$5)-Paramètres!$B$6),"") | AM20: =IF(AND($Y20=1,ISNUMBER($R20)),IF($R20>0,$AL20/$R20-1,""),"") | AN20: =IF(AND($Y20=1,ISNUMBER($R20)),IF($R20>0,$R20/(1+Paramètres!$B$5)-$AK20-($R20*Paramètres!$B$6+Paramètres!$B$7)-Paramètres!$B$8-Paramètres!$B$9-Paramètres!$B$10,""),"") | AO20: =IF(ISNUMBER($AN20),$AN20/($R20/(1+Paramètres!$B$5)),"") | AP20: =IF($A20="","",IF($Y20<>1,"INCOMPLET",IF(NOT(ISNUMBER($AM20)),"SANS RÉF. MARCHÉ",IF($AM20<=Paramètres!$B$12,"OK",IF(AND($AO20>=Paramètres!$B$15,$AN20>=Paramètres!$B$16),"À REVOIR","NON RENTABLE"))))) -> INCOMPLET | AQ20: =TRIM(IF(AND($Y20=1,ISNUMBER($N20)),IF($M20<$N20,"MOQ ",""),"")&IF(AND($Y20=1,ISNUMBER($O20)),IF($O20<$I20*$M20,"DISPO ",""),"")&IF($S20="O","FICTIF ","")&IF($Y20=1,IF(AND($K20="TTC",$W20<>"CH"),"TVA-ÉTRANGÈRE ",""),"")) | AR20: =IF($Y20=1,COUNTIFS($A$6:$A$205,$A20,$AK$6:$AK$205,"<"&$AK20,$Y$6:$Y$205,1)+1,"") | AS20: =IF(ISNUMBER($AR20),$A20&"|"&$AR20,"") | AT20: =IF($Y20=1,$AK20*$I20*$M20,"")
A21: REF-05 | B21: Collection Classeur 30ᵉ Anniversaire – FR | C21: Asmodee France | G21: 30ᵉ Anniversaire | H21: coffret | S21: N | T21: =IF($C21="","",IFERROR(INDEX(Fournisseurs!$C$5:$C$24,MATCH($C21,Fournisseurs!$A$5:$A$24,0)),"")) -> 0 | U21: =IF($C21="","",IFERROR(INDEX(Fournisseurs!$D$5:$D$24,MATCH($C21,Fournisseurs!$A$5:$A$24,0)),"")) -> 0 | V21: =IF($C21="","",IFERROR(INDEX(Fournisseurs!$G$5:$G$24,MATCH($C21,Fournisseurs!$A$5:$A$24,0)),"")) -> 0 | W21: =IF($C21="","",IFERROR(INDEX(Fournisseurs!$H$5:$H$24,MATCH($C21,Fournisseurs!$A$5:$A$24,0)),"")) -> 0 | X21: =IF($C21="","",IFERROR(INDEX(Fournisseurs!$B$5:$B$24,MATCH($C21,Fournisseurs!$A$5:$A$24,0)),"")) -> 0 | Y21: =IF($A21="","",IF(AND($A21<>"",$C21<>"",ISNUMBER($I21),ISNUMBER($J21),ISNUMBER($M21)),IF(AND($I21>=1,$J21>0,OR($K21="HT",$K21="TTC"),$M21>=1,IFERROR(INDEX(Fournisseurs!$T$5:$T$24,MATCH($C21,Fournisseurs!$A$5:$A$24,0)),0)=1),1,0),0)) -> 0 | Z21: =IF($Y21=1,$J21*(1-N($L21)),"") | AA21: =IF($Y21=1,IF($K21="TTC",$Z21/(1+$V21),$Z21),"") | AB21: =IF($Y21=1,IF($K21="TTC",$Z21-$AA21,$AA21*$V21),"") | AC21: =IF($Y21=1,$AA21*$U21*$M21,"") | AD21: =IF($Y21=1,$AC21/SUMIFS($AC$6:$AC$205,$C$6:$C$205,$C21,$Y$6:$Y$205,1),"") | AE21: =IF($Y21=1,(INDEX(Fournisseurs!$J$5:$J$24,MATCH($C21,Fournisseurs!$A$5:$A$24,0))+INDEX(Fournisseurs!$K$5:$K$24,MATCH($C21,Fournisseurs!$A$5:$A$24,0)))*$U21*$AD21/($I21*$M21),"") | AF21: =IF($Y21=1,INDEX(Fournisseurs!$L$5:$L$24,MATCH($C21,Fournisseurs!$A$5:$A$24,0))*$AD21/($I21*$M21),"") | AG21: =IF($Y21=1,$AA21*$U21/$I21,"") | AH21: =IF($Y21=1,$AB21*$U21/$I21,"") | AI21: =IF($Y21=1,IF(AND(Paramètres!$B$4="EFFECTIVE",$W21="CH",$AB21>0),1,0),"") | AJ21: =IF($Y21=1,IF($X21<>"CH",($AG21+$AE21+$AF21)*Paramètres!$B$14,0),"") | AK21: =IF($Y21=1,$AG21+IF($AI21=1,0,$AH21)+$AE21+$AF21+IF(Paramètres!$B$4="NOT_REGISTERED",$AJ21,0),"") | AL21: =IF($Y21=1,($AK21+Paramètres!$B$7+Paramètres!$B$8+Paramètres!$B$9+Paramètres!$B$10)/((1-Paramètres!$B$11)/(1+Paramètres!$B$5)-Paramètres!$B$6),"") | AM21: =IF(AND($Y21=1,ISNUMBER($R21)),IF($R21>0,$AL21/$R21-1,""),"") | AN21: =IF(AND($Y21=1,ISNUMBER($R21)),IF($R21>0,$R21/(1+Paramètres!$B$5)-$AK21-($R21*Paramètres!$B$6+Paramètres!$B$7)-Paramètres!$B$8-Paramètres!$B$9-Paramètres!$B$10,""),"") | AO21: =IF(ISNUMBER($AN21),$AN21/($R21/(1+Paramètres!$B$5)),"") | AP21: =IF($A21="","",IF($Y21<>1,"INCOMPLET",IF(NOT(ISNUMBER($AM21)),"SANS RÉF. MARCHÉ",IF($AM21<=Paramètres!$B$12,"OK",IF(AND($AO21>=Paramètres!$B$15,$AN21>=Paramètres!$B$16),"À REVOIR","NON RENTABLE"))))) -> INCOMPLET | AQ21: =TRIM(IF(AND($Y21=1,ISNUMBER($N21)),IF($M21<$N21,"MOQ ",""),"")&IF(AND($Y21=1,ISNUMBER($O21)),IF($O21<$I21*$M21,"DISPO ",""),"")&IF($S21="O","FICTIF ","")&IF($Y21=1,IF(AND($K21="TTC",$W21<>"CH"),"TVA-ÉTRANGÈRE ",""),"")) | AR21: =IF($Y21=1,COUNTIFS($A$6:$A$205,$A21,$AK$6:$AK$205,"<"&$AK21,$Y$6:$Y$205,1)+1,"") | AS21: =IF(ISNUMBER($AR21),$A21&"|"&$AR21,"") | AT21: =IF($Y21=1,$AK21*$I21*$M21,"")
A22: REF-10 | B22: Coffret Dresseur d'Élite (ETB) Méga-Évolution – Chaos Ascendant – FR | C22: Asmodee France | G22: Méga-Évolution – Chaos Ascendant | H22: etb | S22: N | T22: =IF($C22="","",IFERROR(INDEX(Fournisseurs!$C$5:$C$24,MATCH($C22,Fournisseurs!$A$5:$A$24,0)),"")) -> 0 | U22: =IF($C22="","",IFERROR(INDEX(Fournisseurs!$D$5:$D$24,MATCH($C22,Fournisseurs!$A$5:$A$24,0)),"")) -> 0 | V22: =IF($C22="","",IFERROR(INDEX(Fournisseurs!$G$5:$G$24,MATCH($C22,Fournisseurs!$A$5:$A$24,0)),"")) -> 0 | W22: =IF($C22="","",IFERROR(INDEX(Fournisseurs!$H$5:$H$24,MATCH($C22,Fournisseurs!$A$5:$A$24,0)),"")) -> 0 | X22: =IF($C22="","",IFERROR(INDEX(Fournisseurs!$B$5:$B$24,MATCH($C22,Fournisseurs!$A$5:$A$24,0)),"")) -> 0 | Y22: =IF($A22="","",IF(AND($A22<>"",$C22<>"",ISNUMBER($I22),ISNUMBER($J22),ISNUMBER($M22)),IF(AND($I22>=1,$J22>0,OR($K22="HT",$K22="TTC"),$M22>=1,IFERROR(INDEX(Fournisseurs!$T$5:$T$24,MATCH($C22,Fournisseurs!$A$5:$A$24,0)),0)=1),1,0),0)) -> 0 | Z22: =IF($Y22=1,$J22*(1-N($L22)),"") | AA22: =IF($Y22=1,IF($K22="TTC",$Z22/(1+$V22),$Z22),"") | AB22: =IF($Y22=1,IF($K22="TTC",$Z22-$AA22,$AA22*$V22),"") | AC22: =IF($Y22=1,$AA22*$U22*$M22,"") | AD22: =IF($Y22=1,$AC22/SUMIFS($AC$6:$AC$205,$C$6:$C$205,$C22,$Y$6:$Y$205,1),"") | AE22: =IF($Y22=1,(INDEX(Fournisseurs!$J$5:$J$24,MATCH($C22,Fournisseurs!$A$5:$A$24,0))+INDEX(Fournisseurs!$K$5:$K$24,MATCH($C22,Fournisseurs!$A$5:$A$24,0)))*$U22*$AD22/($I22*$M22),"") | AF22: =IF($Y22=1,INDEX(Fournisseurs!$L$5:$L$24,MATCH($C22,Fournisseurs!$A$5:$A$24,0))*$AD22/($I22*$M22),"") | AG22: =IF($Y22=1,$AA22*$U22/$I22,"") | AH22: =IF($Y22=1,$AB22*$U22/$I22,"") | AI22: =IF($Y22=1,IF(AND(Paramètres!$B$4="EFFECTIVE",$W22="CH",$AB22>0),1,0),"") | AJ22: =IF($Y22=1,IF($X22<>"CH",($AG22+$AE22+$AF22)*Paramètres!$B$14,0),"") | AK22: =IF($Y22=1,$AG22+IF($AI22=1,0,$AH22)+$AE22+$AF22+IF(Paramètres!$B$4="NOT_REGISTERED",$AJ22,0),"") | AL22: =IF($Y22=1,($AK22+Paramètres!$B$7+Paramètres!$B$8+Paramètres!$B$9+Paramètres!$B$10)/((1-Paramètres!$B$11)/(1+Paramètres!$B$5)-Paramètres!$B$6),"") | AM22: =IF(AND($Y22=1,ISNUMBER($R22)),IF($R22>0,$AL22/$R22-1,""),"") | AN22: =IF(AND($Y22=1,ISNUMBER($R22)),IF($R22>0,$R22/(1+Paramètres!$B$5)-$AK22-($R22*Paramètres!$B$6+Paramètres!$B$7)-Paramètres!$B$8-Paramètres!$B$9-Paramètres!$B$10,""),"") | AO22: =IF(ISNUMBER($AN22),$AN22/($R22/(1+Paramètres!$B$5)),"") | AP22: =IF($A22="","",IF($Y22<>1,"INCOMPLET",IF(NOT(ISNUMBER($AM22)),"SANS RÉF. MARCHÉ",IF($AM22<=Paramètres!$B$12,"OK",IF(AND($AO22>=Paramètres!$B$15,$AN22>=Paramètres!$B$16),"À REVOIR","NON RENTABLE"))))) -> INCOMPLET | AQ22: =TRIM(IF(AND($Y22=1,ISNUMBER($N22)),IF($M22<$N22,"MOQ ",""),"")&IF(AND($Y22=1,ISNUMBER($O22)),IF($O22<$I22*$M22,"DISPO ",""),"")&IF($S22="O","FICTIF ","")&IF($Y22=1,IF(AND($K22="TTC",$W22<>"CH"),"TVA-ÉTRANGÈRE ",""),"")) | AR22: =IF($Y22=1,COUNTIFS($A$6:$A$205,$A22,$AK$6:$AK$205,"<"&$AK22,$Y$6:$Y$205,1)+1,"") | AS22: =IF(ISNUMBER($AR22),$A22&"|"&$AR22,"") | AT22: =IF($Y22=1,$AK22*$I22*$M22,"")
A23: REF-12 | B23: Coffret Dresseur d'Élite (ETB) Méga-Évolution – Héros Transcendants – FR | C23: Asmodee France | G23: Méga-Évolution – Héros Transcendants | H23: etb | S23: N | T23: =IF($C23="","",IFERROR(INDEX(Fournisseurs!$C$5:$C$24,MATCH($C23,Fournisseurs!$A$5:$A$24,0)),"")) -> 0 | U23: =IF($C23="","",IFERROR(INDEX(Fournisseurs!$D$5:$D$24,MATCH($C23,Fournisseurs!$A$5:$A$24,0)),"")) -> 0 | V23: =IF($C23="","",IFERROR(INDEX(Fournisseurs!$G$5:$G$24,MATCH($C23,Fournisseurs!$A$5:$A$24,0)),"")) -> 0 | W23: =IF($C23="","",IFERROR(INDEX(Fournisseurs!$H$5:$H$24,MATCH($C23,Fournisseurs!$A$5:$A$24,0)),"")) -> 0 | X23: =IF($C23="","",IFERROR(INDEX(Fournisseurs!$B$5:$B$24,MATCH($C23,Fournisseurs!$A$5:$A$24,0)),"")) -> 0 | Y23: =IF($A23="","",IF(AND($A23<>"",$C23<>"",ISNUMBER($I23),ISNUMBER($J23),ISNUMBER($M23)),IF(AND($I23>=1,$J23>0,OR($K23="HT",$K23="TTC"),$M23>=1,IFERROR(INDEX(Fournisseurs!$T$5:$T$24,MATCH($C23,Fournisseurs!$A$5:$A$24,0)),0)=1),1,0),0)) -> 0 | Z23: =IF($Y23=1,$J23*(1-N($L23)),"") | AA23: =IF($Y23=1,IF($K23="TTC",$Z23/(1+$V23),$Z23),"") | AB23: =IF($Y23=1,IF($K23="TTC",$Z23-$AA23,$AA23*$V23),"") | AC23: =IF($Y23=1,$AA23*$U23*$M23,"") | AD23: =IF($Y23=1,$AC23/SUMIFS($AC$6:$AC$205,$C$6:$C$205,$C23,$Y$6:$Y$205,1),"") | AE23: =IF($Y23=1,(INDEX(Fournisseurs!$J$5:$J$24,MATCH($C23,Fournisseurs!$A$5:$A$24,0))+INDEX(Fournisseurs!$K$5:$K$24,MATCH($C23,Fournisseurs!$A$5:$A$24,0)))*$U23*$AD23/($I23*$M23),"") | AF23: =IF($Y23=1,INDEX(Fournisseurs!$L$5:$L$24,MATCH($C23,Fournisseurs!$A$5:$A$24,0))*$AD23/($I23*$M23),"") | AG23: =IF($Y23=1,$AA23*$U23/$I23,"") | AH23: =IF($Y23=1,$AB23*$U23/$I23,"") | AI23: =IF($Y23=1,IF(AND(Paramètres!$B$4="EFFECTIVE",$W23="CH",$AB23>0),1,0),"") | AJ23: =IF($Y23=1,IF($X23<>"CH",($AG23+$AE23+$AF23)*Paramètres!$B$14,0),"") | AK23: =IF($Y23=1,$AG23+IF($AI23=1,0,$AH23)+$AE23+$AF23+IF(Paramètres!$B$4="NOT_REGISTERED",$AJ23,0),"") | AL23: =IF($Y23=1,($AK23+Paramètres!$B$7+Paramètres!$B$8+Paramètres!$B$9+Paramètres!$B$10)/((1-Paramètres!$B$11)/(1+Paramètres!$B$5)-Paramètres!$B$6),"") | AM23: =IF(AND($Y23=1,ISNUMBER($R23)),IF($R23>0,$AL23/$R23-1,""),"") | AN23: =IF(AND($Y23=1,ISNUMBER($R23)),IF($R23>0,$R23/(1+Paramètres!$B$5)-$AK23-($R23*Paramètres!$B$6+Paramètres!$B$7)-Paramètres!$B$8-Paramètres!$B$9-Paramètres!$B$10,""),"") | AO23: =IF(ISNUMBER($AN23),$AN23/($R23/(1+Paramètres!$B$5)),"") | AP23: =IF($A23="","",IF($Y23<>1,"INCOMPLET",IF(NOT(ISNUMBER($AM23)),"SANS RÉF. MARCHÉ",IF($AM23<=Paramètres!$B$12,"OK",IF(AND($AO23>=Paramètres!$B$15,$AN23>=Paramètres!$B$16),"À REVOIR","NON RENTABLE"))))) -> INCOMPLET | AQ23: =TRIM(IF(AND($Y23=1,ISNUMBER($N23)),IF($M23<$N23,"MOQ ",""),"")&IF(AND($Y23=1,ISNUMBER($O23)),IF($O23<$I23*$M23,"DISPO ",""),"")&IF($S23="O","FICTIF ","")&IF($Y23=1,IF(AND($K23="TTC",$W23<>"CH"),"TVA-ÉTRANGÈRE ",""),"")) | AR23: =IF($Y23=1,COUNTIFS($A$6:$A$205,$A23,$AK$6:$AK$205,"<"&$AK23,$Y$6:$Y$205,1)+1,"") | AS23: =IF(ISNUMBER($AR23),$A23&"|"&$AR23,"") | AT23: =IF($Y23=1,$AK23*$I23*$M23,"")
A24: REF-13 | B24: Display 36 boosters Méga-Évolution – Règne Delta (ME06) – FR | C24: Asmodee France | G24: Méga-Évolution – Règne Delta | H24: display | S24: N | T24: =IF($C24="","",IFERROR(INDEX(Fournisseurs!$C$5:$C$24,MATCH($C24,Fournisseurs!$A$5:$A$24,0)),"")) -> 0 | U24: =IF($C24="","",IFERROR(INDEX(Fournisseurs!$D$5:$D$24,MATCH($C24,Fournisseurs!$A$5:$A$24,0)),"")) -> 0 | V24: =IF($C24="","",IFERROR(INDEX(Fournisseurs!$G$5:$G$24,MATCH($C24,Fournisseurs!$A$5:$A$24,0)),"")) -> 0 | W24: =IF($C24="","",IFERROR(INDEX(Fournisseurs!$H$5:$H$24,MATCH($C24,Fournisseurs!$A$5:$A$24,0)),"")) -> 0 | X24: =IF($C24="","",IFERROR(INDEX(Fournisseurs!$B$5:$B$24,MATCH($C24,Fournisseurs!$A$5:$A$24,0)),"")) -> 0 | Y24: =IF($A24="","",IF(AND($A24<>"",$C24<>"",ISNUMBER($I24),ISNUMBER($J24),ISNUMBER($M24)),IF(AND($I24>=1,$J24>0,OR($K24="HT",$K24="TTC"),$M24>=1,IFERROR(INDEX(Fournisseurs!$T$5:$T$24,MATCH($C24,Fournisseurs!$A$5:$A$24,0)),0)=1),1,0),0)) -> 0 | Z24: =IF($Y24=1,$J24*(1-N($L24)),"") | AA24: =IF($Y24=1,IF($K24="TTC",$Z24/(1+$V24),$Z24),"") | AB24: =IF($Y24=1,IF($K24="TTC",$Z24-$AA24,$AA24*$V24),"") | AC24: =IF($Y24=1,$AA24*$U24*$M24,"") | AD24: =IF($Y24=1,$AC24/SUMIFS($AC$6:$AC$205,$C$6:$C$205,$C24,$Y$6:$Y$205,1),"") | AE24: =IF($Y24=1,(INDEX(Fournisseurs!$J$5:$J$24,MATCH($C24,Fournisseurs!$A$5:$A$24,0))+INDEX(Fournisseurs!$K$5:$K$24,MATCH($C24,Fournisseurs!$A$5:$A$24,0)))*$U24*$AD24/($I24*$M24),"") | AF24: =IF($Y24=1,INDEX(Fournisseurs!$L$5:$L$24,MATCH($C24,Fournisseurs!$A$5:$A$24,0))*$AD24/($I24*$M24),"") | AG24: =IF($Y24=1,$AA24*$U24/$I24,"") | AH24: =IF($Y24=1,$AB24*$U24/$I24,"") | AI24: =IF($Y24=1,IF(AND(Paramètres!$B$4="EFFECTIVE",$W24="CH",$AB24>0),1,0),"") | AJ24: =IF($Y24=1,IF($X24<>"CH",($AG24+$AE24+$AF24)*Paramètres!$B$14,0),"") | AK24: =IF($Y24=1,$AG24+IF($AI24=1,0,$AH24)+$AE24+$AF24+IF(Paramètres!$B$4="NOT_REGISTERED",$AJ24,0),"") | AL24: =IF($Y24=1,($AK24+Paramètres!$B$7+Paramètres!$B$8+Paramètres!$B$9+Paramètres!$B$10)/((1-Paramètres!$B$11)/(1+Paramètres!$B$5)-Paramètres!$B$6),"") | AM24: =IF(AND($Y24=1,ISNUMBER($R24)),IF($R24>0,$AL24/$R24-1,""),"") | AN24: =IF(AND($Y24=1,ISNUMBER($R24)),IF($R24>0,$R24/(1+Paramètres!$B$5)-$AK24-($R24*Paramètres!$B$6+Paramètres!$B$7)-Paramètres!$B$8-Paramètres!$B$9-Paramètres!$B$10,""),"") | AO24: =IF(ISNUMBER($AN24),$AN24/($R24/(1+Paramètres!$B$5)),"") | AP24: =IF($A24="","",IF($Y24<>1,"INCOMPLET",IF(NOT(ISNUMBER($AM24)),"SANS RÉF. MARCHÉ",IF($AM24<=Paramètres!$B$12,"OK",IF(AND($AO24>=Paramètres!$B$15,$AN24>=Paramètres!$B$16),"À REVOIR","NON RENTABLE"))))) -> INCOMPLET | AQ24: =TRIM(IF(AND($Y24=1,ISNUMBER($N24)),IF($M24<$N24,"MOQ ",""),"")&IF(AND($Y24=1,ISNUMBER($O24)),IF($O24<$I24*$M24,"DISPO ",""),"")&IF($S24="O","FICTIF ","")&IF($Y24=1,IF(AND($K24="TTC",$W24<>"CH"),"TVA-ÉTRANGÈRE ",""),"")) | AR24: =IF($Y24=1,COUNTIFS($A$6:$A$205,$A24,$AK$6:$AK$205,"<"&$AK24,$Y$6:$Y$205,1)+1,"") | AS24: =IF(ISNUMBER($AR24),$A24&"|"&$AR24,"") | AT24: =IF($Y24=1,$AK24*$I24*$M24,"")
A25: REF-14 | B25: Coffret Dresseur d'Élite (ETB) Méga-Évolution – Règne Delta – FR | C25: Asmodee France | G25: Méga-Évolution – Règne Delta | H25: etb | S25: N | T25: =IF($C25="","",IFERROR(INDEX(Fournisseurs!$C$5:$C$24,MATCH($C25,Fournisseurs!$A$5:$A$24,0)),"")) -> 0 | U25: =IF($C25="","",IFERROR(INDEX(Fournisseurs!$D$5:$D$24,MATCH($C25,Fournisseurs!$A$5:$A$24,0)),"")) -> 0 | V25: =IF($C25="","",IFERROR(INDEX(Fournisseurs!$G$5:$G$24,MATCH($C25,Fournisseurs!$A$5:$A$24,0)),"")) -> 0 | W25: =IF($C25="","",IFERROR(INDEX(Fournisseurs!$H$5:$H$24,MATCH($C25,Fournisseurs!$A$5:$A$24,0)),"")) -> 0 | X25: =IF($C25="","",IFERROR(INDEX(Fournisseurs!$B$5:$B$24,MATCH($C25,Fournisseurs!$A$5:$A$24,0)),"")) -> 0 | Y25: =IF($A25="","",IF(AND($A25<>"",$C25<>"",ISNUMBER($I25),ISNUMBER($J25),ISNUMBER($M25)),IF(AND($I25>=1,$J25>0,OR($K25="HT",$K25="TTC"),$M25>=1,IFERROR(INDEX(Fournisseurs!$T$5:$T$24,MATCH($C25,Fournisseurs!$A$5:$A$24,0)),0)=1),1,0),0)) -> 0 | Z25: =IF($Y25=1,$J25*(1-N($L25)),"") | AA25: =IF($Y25=1,IF($K25="TTC",$Z25/(1+$V25),$Z25),"") | AB25: =IF($Y25=1,IF($K25="TTC",$Z25-$AA25,$AA25*$V25),"") | AC25: =IF($Y25=1,$AA25*$U25*$M25,"") | AD25: =IF($Y25=1,$AC25/SUMIFS($AC$6:$AC$205,$C$6:$C$205,$C25,$Y$6:$Y$205,1),"") | AE25: =IF($Y25=1,(INDEX(Fournisseurs!$J$5:$J$24,MATCH($C25,Fournisseurs!$A$5:$A$24,0))+INDEX(Fournisseurs!$K$5:$K$24,MATCH($C25,Fournisseurs!$A$5:$A$24,0)))*$U25*$AD25/($I25*$M25),"") | AF25: =IF($Y25=1,INDEX(Fournisseurs!$L$5:$L$24,MATCH($C25,Fournisseurs!$A$5:$A$24,0))*$AD25/($I25*$M25),"") | AG25: =IF($Y25=1,$AA25*$U25/$I25,"") | AH25: =IF($Y25=1,$AB25*$U25/$I25,"") | AI25: =IF($Y25=1,IF(AND(Paramètres!$B$4="EFFECTIVE",$W25="CH",$AB25>0),1,0),"") | AJ25: =IF($Y25=1,IF($X25<>"CH",($AG25+$AE25+$AF25)*Paramètres!$B$14,0),"") | AK25: =IF($Y25=1,$AG25+IF($AI25=1,0,$AH25)+$AE25+$AF25+IF(Paramètres!$B$4="NOT_REGISTERED",$AJ25,0),"") | AL25: =IF($Y25=1,($AK25+Paramètres!$B$7+Paramètres!$B$8+Paramètres!$B$9+Paramètres!$B$10)/((1-Paramètres!$B$11)/(1+Paramètres!$B$5)-Paramètres!$B$6),"") | AM25: =IF(AND($Y25=1,ISNUMBER($R25)),IF($R25>0,$AL25/$R25-1,""),"") | AN25: =IF(AND($Y25=1,ISNUMBER($R25)),IF($R25>0,$R25/(1+Paramètres!$B$5)-$AK25-($R25*Paramètres!$B$6+Paramètres!$B$7)-Paramètres!$B$8-Paramètres!$B$9-Paramètres!$B$10,""),"") | AO25: =IF(ISNUMBER($AN25),$AN25/($R25/(1+Paramètres!$B$5)),"") | AP25: =IF($A25="","",IF($Y25<>1,"INCOMPLET",IF(NOT(ISNUMBER($AM25)),"SANS RÉF. MARCHÉ",IF($AM25<=Paramètres!$B$12,"OK",IF(AND($AO25>=Paramètres!$B$15,$AN25>=Paramètres!$B$16),"À REVOIR","NON RENTABLE"))))) -> INCOMPLET | AQ25: =TRIM(IF(AND($Y25=1,ISNUMBER($N25)),IF($M25<$N25,"MOQ ",""),"")&IF(AND($Y25=1,ISNUMBER($O25)),IF($O25<$I25*$M25,"DISPO ",""),"")&IF($S25="O","FICTIF ","")&IF($Y25=1,IF(AND($K25="TTC",$W25<>"CH"),"TVA-ÉTRANGÈRE ",""),"")) | AR25: =IF($Y25=1,COUNTIFS($A$6:$A$205,$A25,$AK$6:$AK$205,"<"&$AK25,$Y$6:$Y$205,1)+1,"") | AS25: =IF(ISNUMBER($AR25),$A25&"|"&$AR25,"") | AT25: =IF($Y25=1,$AK25*$I25*$M25,"")
A26: REF-15 | B26: Tripack Méga-Évolution – Règne Delta – FR | C26: Asmodee France | G26: Méga-Évolution – Règne Delta | H26: tripack | S26: N | T26: =IF($C26="","",IFERROR(INDEX(Fournisseurs!$C$5:$C$24,MATCH($C26,Fournisseurs!$A$5:$A$24,0)),"")) -> 0 | U26: =IF($C26="","",IFERROR(INDEX(Fournisseurs!$D$5:$D$24,MATCH($C26,Fournisseurs!$A$5:$A$24,0)),"")) -> 0 | V26: =IF($C26="","",IFERROR(INDEX(Fournisseurs!$G$5:$G$24,MATCH($C26,Fournisseurs!$A$5:$A$24,0)),"")) -> 0 | W26: =IF($C26="","",IFERROR(INDEX(Fournisseurs!$H$5:$H$24,MATCH($C26,Fournisseurs!$A$5:$A$24,0)),"")) -> 0 | X26: =IF($C26="","",IFERROR(INDEX(Fournisseurs!$B$5:$B$24,MATCH($C26,Fournisseurs!$A$5:$A$24,0)),"")) -> 0 | Y26: =IF($A26="","",IF(AND($A26<>"",$C26<>"",ISNUMBER($I26),ISNUMBER($J26),ISNUMBER($M26)),IF(AND($I26>=1,$J26>0,OR($K26="HT",$K26="TTC"),$M26>=1,IFERROR(INDEX(Fournisseurs!$T$5:$T$24,MATCH($C26,Fournisseurs!$A$5:$A$24,0)),0)=1),1,0),0)) -> 0 | Z26: =IF($Y26=1,$J26*(1-N($L26)),"") | AA26: =IF($Y26=1,IF($K26="TTC",$Z26/(1+$V26),$Z26),"") | AB26: =IF($Y26=1,IF($K26="TTC",$Z26-$AA26,$AA26*$V26),"") | AC26: =IF($Y26=1,$AA26*$U26*$M26,"") | AD26: =IF($Y26=1,$AC26/SUMIFS($AC$6:$AC$205,$C$6:$C$205,$C26,$Y$6:$Y$205,1),"") | AE26: =IF($Y26=1,(INDEX(Fournisseurs!$J$5:$J$24,MATCH($C26,Fournisseurs!$A$5:$A$24,0))+INDEX(Fournisseurs!$K$5:$K$24,MATCH($C26,Fournisseurs!$A$5:$A$24,0)))*$U26*$AD26/($I26*$M26),"") | AF26: =IF($Y26=1,INDEX(Fournisseurs!$L$5:$L$24,MATCH($C26,Fournisseurs!$A$5:$A$24,0))*$AD26/($I26*$M26),"") | AG26: =IF($Y26=1,$AA26*$U26/$I26,"") | AH26: =IF($Y26=1,$AB26*$U26/$I26,"") | AI26: =IF($Y26=1,IF(AND(Paramètres!$B$4="EFFECTIVE",$W26="CH",$AB26>0),1,0),"") | AJ26: =IF($Y26=1,IF($X26<>"CH",($AG26+$AE26+$AF26)*Paramètres!$B$14,0),"") | AK26: =IF($Y26=1,$AG26+IF($AI26=1,0,$AH26)+$AE26+$AF26+IF(Paramètres!$B$4="NOT_REGISTERED",$AJ26,0),"") | AL26: =IF($Y26=1,($AK26+Paramètres!$B$7+Paramètres!$B$8+Paramètres!$B$9+Paramètres!$B$10)/((1-Paramètres!$B$11)/(1+Paramètres!$B$5)-Paramètres!$B$6),"") | AM26: =IF(AND($Y26=1,ISNUMBER($R26)),IF($R26>0,$AL26/$R26-1,""),"") | AN26: =IF(AND($Y26=1,ISNUMBER($R26)),IF($R26>0,$R26/(1+Paramètres!$B$5)-$AK26-($R26*Paramètres!$B$6+Paramètres!$B$7)-Paramètres!$B$8-Paramètres!$B$9-Paramètres!$B$10,""),"") | AO26: =IF(ISNUMBER($AN26),$AN26/($R26/(1+Paramètres!$B$5)),"") | AP26: =IF($A26="","",IF($Y26<>1,"INCOMPLET",IF(NOT(ISNUMBER($AM26)),"SANS RÉF. MARCHÉ",IF($AM26<=Paramètres!$B$12,"OK",IF(AND($AO26>=Paramètres!$B$15,$AN26>=Paramètres!$B$16),"À REVOIR","NON RENTABLE"))))) -> INCOMPLET | AQ26: =TRIM(IF(AND($Y26=1,ISNUMBER($N26)),IF($M26<$N26,"MOQ ",""),"")&IF(AND($Y26=1,ISNUMBER($O26)),IF($O26<$I26*$M26,"DISPO ",""),"")&IF($S26="O","FICTIF ","")&IF($Y26=1,IF(AND($K26="TTC",$W26<>"CH"),"TVA-ÉTRANGÈRE ",""),"")) | AR26: =IF($Y26=1,COUNTIFS($A$6:$A$205,$A26,$AK$6:$AK$205,"<"&$AK26,$Y$6:$Y$205,1)+1,"") | AS26: =IF(ISNUMBER($AR26),$A26&"|"&$AR26,"") | AT26: =IF($Y26=1,$AK26*$I26*$M26,"")
A27: REF-18 | B27: Boîte de rangement de deck (deck box) | C27: Asmodee France | H27: accessoire | S27: N | T27: =IF($C27="","",IFERROR(INDEX(Fournisseurs!$C$5:$C$24,MATCH($C27,Fournisseurs!$A$5:$A$24,0)),"")) -> 0 | U27: =IF($C27="","",IFERROR(INDEX(Fournisseurs!$D$5:$D$24,MATCH($C27,Fournisseurs!$A$5:$A$24,0)),"")) -> 0 | V27: =IF($C27="","",IFERROR(INDEX(Fournisseurs!$G$5:$G$24,MATCH($C27,Fournisseurs!$A$5:$A$24,0)),"")) -> 0 | W27: =IF($C27="","",IFERROR(INDEX(Fournisseurs!$H$5:$H$24,MATCH($C27,Fournisseurs!$A$5:$A$24,0)),"")) -> 0 | X27: =IF($C27="","",IFERROR(INDEX(Fournisseurs!$B$5:$B$24,MATCH($C27,Fournisseurs!$A$5:$A$24,0)),"")) -> 0 | Y27: =IF($A27="","",IF(AND($A27<>"",$C27<>"",ISNUMBER($I27),ISNUMBER($J27),ISNUMBER($M27)),IF(AND($I27>=1,$J27>0,OR($K27="HT",$K27="TTC"),$M27>=1,IFERROR(INDEX(Fournisseurs!$T$5:$T$24,MATCH($C27,Fournisseurs!$A$5:$A$24,0)),0)=1),1,0),0)) -> 0 | Z27: =IF($Y27=1,$J27*(1-N($L27)),"") | AA27: =IF($Y27=1,IF($K27="TTC",$Z27/(1+$V27),$Z27),"") | AB27: =IF($Y27=1,IF($K27="TTC",$Z27-$AA27,$AA27*$V27),"") | AC27: =IF($Y27=1,$AA27*$U27*$M27,"") | AD27: =IF($Y27=1,$AC27/SUMIFS($AC$6:$AC$205,$C$6:$C$205,$C27,$Y$6:$Y$205,1),"") | AE27: =IF($Y27=1,(INDEX(Fournisseurs!$J$5:$J$24,MATCH($C27,Fournisseurs!$A$5:$A$24,0))+INDEX(Fournisseurs!$K$5:$K$24,MATCH($C27,Fournisseurs!$A$5:$A$24,0)))*$U27*$AD27/($I27*$M27),"") | AF27: =IF($Y27=1,INDEX(Fournisseurs!$L$5:$L$24,MATCH($C27,Fournisseurs!$A$5:$A$24,0))*$AD27/($I27*$M27),"") | AG27: =IF($Y27=1,$AA27*$U27/$I27,"") | AH27: =IF($Y27=1,$AB27*$U27/$I27,"") | AI27: =IF($Y27=1,IF(AND(Paramètres!$B$4="EFFECTIVE",$W27="CH",$AB27>0),1,0),"") | AJ27: =IF($Y27=1,IF($X27<>"CH",($AG27+$AE27+$AF27)*Paramètres!$B$14,0),"") | AK27: =IF($Y27=1,$AG27+IF($AI27=1,0,$AH27)+$AE27+$AF27+IF(Paramètres!$B$4="NOT_REGISTERED",$AJ27,0),"") | AL27: =IF($Y27=1,($AK27+Paramètres!$B$7+Paramètres!$B$8+Paramètres!$B$9+Paramètres!$B$10)/((1-Paramètres!$B$11)/(1+Paramètres!$B$5)-Paramètres!$B$6),"") | AM27: =IF(AND($Y27=1,ISNUMBER($R27)),IF($R27>0,$AL27/$R27-1,""),"") | AN27: =IF(AND($Y27=1,ISNUMBER($R27)),IF($R27>0,$R27/(1+Paramètres!$B$5)-$AK27-($R27*Paramètres!$B$6+Paramètres!$B$7)-Paramètres!$B$8-Paramètres!$B$9-Paramètres!$B$10,""),"") | AO27: =IF(ISNUMBER($AN27),$AN27/($R27/(1+Paramètres!$B$5)),"") | AP27: =IF($A27="","",IF($Y27<>1,"INCOMPLET",IF(NOT(ISNUMBER($AM27)),"SANS RÉF. MARCHÉ",IF($AM27<=Paramètres!$B$12,"OK",IF(AND($AO27>=Paramètres!$B$15,$AN27>=Paramètres!$B$16),"À REVOIR","NON RENTABLE"))))) -> INCOMPLET | AQ27: =TRIM(IF(AND($Y27=1,ISNUMBER($N27)),IF($M27<$N27,"MOQ ",""),"")&IF(AND($Y27=1,ISNUMBER($O27)),IF($O27<$I27*$M27,"DISPO ",""),"")&IF($S27="O","FICTIF ","")&IF($Y27=1,IF(AND($K27="TTC",$W27<>"CH"),"TVA-ÉTRANGÈRE ",""),"")) | AR27: =IF($Y27=1,COUNTIFS($A$6:$A$205,$A27,$AK$6:$AK$205,"<"&$AK27,$Y$6:$Y$205,1)+1,"") | AS27: =IF(ISNUMBER($AR27),$A27&"|"&$AR27,"") | AT27: =IF($Y27=1,$AK27*$I27*$M27,"")
A28: REF-06 | B28: Display 36 boosters Méga-Évolution – Nuit Noire (ME05) – FR | C28: Matoo et Miao | G28: Méga-Évolution – Nuit Noire | H28: display | S28: N | T28: =IF($C28="","",IFERROR(INDEX(Fournisseurs!$C$5:$C$24,MATCH($C28,Fournisseurs!$A$5:$A$24,0)),"")) -> 0 | U28: =IF($C28="","",IFERROR(INDEX(Fournisseurs!$D$5:$D$24,MATCH($C28,Fournisseurs!$A$5:$A$24,0)),"")) -> 0 | V28: =IF($C28="","",IFERROR(INDEX(Fournisseurs!$G$5:$G$24,MATCH($C28,Fournisseurs!$A$5:$A$24,0)),"")) -> 0 | W28: =IF($C28="","",IFERROR(INDEX(Fournisseurs!$H$5:$H$24,MATCH($C28,Fournisseurs!$A$5:$A$24,0)),"")) -> 0 | X28: =IF($C28="","",IFERROR(INDEX(Fournisseurs!$B$5:$B$24,MATCH($C28,Fournisseurs!$A$5:$A$24,0)),"")) -> 0 | Y28: =IF($A28="","",IF(AND($A28<>"",$C28<>"",ISNUMBER($I28),ISNUMBER($J28),ISNUMBER($M28)),IF(AND($I28>=1,$J28>0,OR($K28="HT",$K28="TTC"),$M28>=1,IFERROR(INDEX(Fournisseurs!$T$5:$T$24,MATCH($C28,Fournisseurs!$A$5:$A$24,0)),0)=1),1,0),0)) -> 0 | Z28: =IF($Y28=1,$J28*(1-N($L28)),"") | AA28: =IF($Y28=1,IF($K28="TTC",$Z28/(1+$V28),$Z28),"") | AB28: =IF($Y28=1,IF($K28="TTC",$Z28-$AA28,$AA28*$V28),"") | AC28: =IF($Y28=1,$AA28*$U28*$M28,"") | AD28: =IF($Y28=1,$AC28/SUMIFS($AC$6:$AC$205,$C$6:$C$205,$C28,$Y$6:$Y$205,1),"") | AE28: =IF($Y28=1,(INDEX(Fournisseurs!$J$5:$J$24,MATCH($C28,Fournisseurs!$A$5:$A$24,0))+INDEX(Fournisseurs!$K$5:$K$24,MATCH($C28,Fournisseurs!$A$5:$A$24,0)))*$U28*$AD28/($I28*$M28),"") | AF28: =IF($Y28=1,INDEX(Fournisseurs!$L$5:$L$24,MATCH($C28,Fournisseurs!$A$5:$A$24,0))*$AD28/($I28*$M28),"") | AG28: =IF($Y28=1,$AA28*$U28/$I28,"") | AH28: =IF($Y28=1,$AB28*$U28/$I28,"") | AI28: =IF($Y28=1,IF(AND(Paramètres!$B$4="EFFECTIVE",$W28="CH",$AB28>0),1,0),"") | AJ28: =IF($Y28=1,IF($X28<>"CH",($AG28+$AE28+$AF28)*Paramètres!$B$14,0),"") | AK28: =IF($Y28=1,$AG28+IF($AI28=1,0,$AH28)+$AE28+$AF28+IF(Paramètres!$B$4="NOT_REGISTERED",$AJ28,0),"") | AL28: =IF($Y28=1,($AK28+Paramètres!$B$7+Paramètres!$B$8+Paramètres!$B$9+Paramètres!$B$10)/((1-Paramètres!$B$11)/(1+Paramètres!$B$5)-Paramètres!$B$6),"") | AM28: =IF(AND($Y28=1,ISNUMBER($R28)),IF($R28>0,$AL28/$R28-1,""),"") | AN28: =IF(AND($Y28=1,ISNUMBER($R28)),IF($R28>0,$R28/(1+Paramètres!$B$5)-$AK28-($R28*Paramètres!$B$6+Paramètres!$B$7)-Paramètres!$B$8-Paramètres!$B$9-Paramètres!$B$10,""),"") | AO28: =IF(ISNUMBER($AN28),$AN28/($R28/(1+Paramètres!$B$5)),"") | AP28: =IF($A28="","",IF($Y28<>1,"INCOMPLET",IF(NOT(ISNUMBER($AM28)),"SANS RÉF. MARCHÉ",IF($AM28<=Paramètres!$B$12,"OK",IF(AND($AO28>=Paramètres!$B$15,$AN28>=Paramètres!$B$16),"À REVOIR","NON RENTABLE"))))) -> INCOMPLET | AQ28: =TRIM(IF(AND($Y28=1,ISNUMBER($N28)),IF($M28<$N28,"MOQ ",""),"")&IF(AND($Y28=1,ISNUMBER($O28)),IF($O28<$I28*$M28,"DISPO ",""),"")&IF($S28="O","FICTIF ","")&IF($Y28=1,IF(AND($K28="TTC",$W28<>"CH"),"TVA-ÉTRANGÈRE ",""),"")) | AR28: =IF($Y28=1,COUNTIFS($A$6:$A$205,$A28,$AK$6:$AK$205,"<"&$AK28,$Y$6:$Y$205,1)+1,"") | AS28: =IF(ISNUMBER($AR28),$A28&"|"&$AR28,"") | AT28: =IF($Y28=1,$AK28*$I28*$M28,"")
A29: REF-09 | B29: Display 36 boosters Méga-Évolution – Chaos Ascendant – FR | C29: Matoo et Miao | G29: Méga-Évolution – Chaos Ascendant | H29: display | S29: N | T29: =IF($C29="","",IFERROR(INDEX(Fournisseurs!$C$5:$C$24,MATCH($C29,Fournisseurs!$A$5:$A$24,0)),"")) -> 0 | U29: =IF($C29="","",IFERROR(INDEX(Fournisseurs!$D$5:$D$24,MATCH($C29,Fournisseurs!$A$5:$A$24,0)),"")) -> 0 | V29: =IF($C29="","",IFERROR(INDEX(Fournisseurs!$G$5:$G$24,MATCH($C29,Fournisseurs!$A$5:$A$24,0)),"")) -> 0 | W29: =IF($C29="","",IFERROR(INDEX(Fournisseurs!$H$5:$H$24,MATCH($C29,Fournisseurs!$A$5:$A$24,0)),"")) -> 0 | X29: =IF($C29="","",IFERROR(INDEX(Fournisseurs!$B$5:$B$24,MATCH($C29,Fournisseurs!$A$5:$A$24,0)),"")) -> 0 | Y29: =IF($A29="","",IF(AND($A29<>"",$C29<>"",ISNUMBER($I29),ISNUMBER($J29),ISNUMBER($M29)),IF(AND($I29>=1,$J29>0,OR($K29="HT",$K29="TTC"),$M29>=1,IFERROR(INDEX(Fournisseurs!$T$5:$T$24,MATCH($C29,Fournisseurs!$A$5:$A$24,0)),0)=1),1,0),0)) -> 0 | Z29: =IF($Y29=1,$J29*(1-N($L29)),"") | AA29: =IF($Y29=1,IF($K29="TTC",$Z29/(1+$V29),$Z29),"") | AB29: =IF($Y29=1,IF($K29="TTC",$Z29-$AA29,$AA29*$V29),"") | AC29: =IF($Y29=1,$AA29*$U29*$M29,"") | AD29: =IF($Y29=1,$AC29/SUMIFS($AC$6:$AC$205,$C$6:$C$205,$C29,$Y$6:$Y$205,1),"") | AE29: =IF($Y29=1,(INDEX(Fournisseurs!$J$5:$J$24,MATCH($C29,Fournisseurs!$A$5:$A$24,0))+INDEX(Fournisseurs!$K$5:$K$24,MATCH($C29,Fournisseurs!$A$5:$A$24,0)))*$U29*$AD29/($I29*$M29),"") | AF29: =IF($Y29=1,INDEX(Fournisseurs!$L$5:$L$24,MATCH($C29,Fournisseurs!$A$5:$A$24,0))*$AD29/($I29*$M29),"") | AG29: =IF($Y29=1,$AA29*$U29/$I29,"") | AH29: =IF($Y29=1,$AB29*$U29/$I29,"") | AI29: =IF($Y29=1,IF(AND(Paramètres!$B$4="EFFECTIVE",$W29="CH",$AB29>0),1,0),"") | AJ29: =IF($Y29=1,IF($X29<>"CH",($AG29+$AE29+$AF29)*Paramètres!$B$14,0),"") | AK29: =IF($Y29=1,$AG29+IF($AI29=1,0,$AH29)+$AE29+$AF29+IF(Paramètres!$B$4="NOT_REGISTERED",$AJ29,0),"") | AL29: =IF($Y29=1,($AK29+Paramètres!$B$7+Paramètres!$B$8+Paramètres!$B$9+Paramètres!$B$10)/((1-Paramètres!$B$11)/(1+Paramètres!$B$5)-Paramètres!$B$6),"") | AM29: =IF(AND($Y29=1,ISNUMBER($R29)),IF($R29>0,$AL29/$R29-1,""),"") | AN29: =IF(AND($Y29=1,ISNUMBER($R29)),IF($R29>0,$R29/(1+Paramètres!$B$5)-$AK29-($R29*Paramètres!$B$6+Paramètres!$B$7)-Paramètres!$B$8-Paramètres!$B$9-Paramètres!$B$10,""),"") | AO29: =IF(ISNUMBER($AN29),$AN29/($R29/(1+Paramètres!$B$5)),"") | AP29: =IF($A29="","",IF($Y29<>1,"INCOMPLET",IF(NOT(ISNUMBER($AM29)),"SANS RÉF. MARCHÉ",IF($AM29<=Paramètres!$B$12,"OK",IF(AND($AO29>=Paramètres!$B$15,$AN29>=Paramètres!$B$16),"À REVOIR","NON RENTABLE"))))) -> INCOMPLET | AQ29: =TRIM(IF(AND($Y29=1,ISNUMBER($N29)),IF($M29<$N29,"MOQ ",""),"")&IF(AND($Y29=1,ISNUMBER($O29)),IF($O29<$I29*$M29,"DISPO ",""),"")&IF($S29="O","FICTIF ","")&IF($Y29=1,IF(AND($K29="TTC",$W29<>"CH"),"TVA-ÉTRANGÈRE ",""),"")) | AR29: =IF($Y29=1,COUNTIFS($A$6:$A$205,$A29,$AK$6:$AK$205,"<"&$AK29,$Y$6:$Y$205,1)+1,"") | AS29: =IF(ISNUMBER($AR29),$A29&"|"&$AR29,"") | AT29: =IF($Y29=1,$AK29*$I29*$M29,"")
A30: REF-01 | B30: Coffret Dresseur d'Élite (ETB) 30ᵉ Anniversaire – FR | C30: Matoo et Miao | G30: 30ᵉ Anniversaire | H30: etb | S30: N | T30: =IF($C30="","",IFERROR(INDEX(Fournisseurs!$C$5:$C$24,MATCH($C30,Fournisseurs!$A$5:$A$24,0)),"")) -> 0 | U30: =IF($C30="","",IFERROR(INDEX(Fournisseurs!$D$5:$D$24,MATCH($C30,Fournisseurs!$A$5:$A$24,0)),"")) -> 0 | V30: =IF($C30="","",IFERROR(INDEX(Fournisseurs!$G$5:$G$24,MATCH($C30,Fournisseurs!$A$5:$A$24,0)),"")) -> 0 | W30: =IF($C30="","",IFERROR(INDEX(Fournisseurs!$H$5:$H$24,MATCH($C30,Fournisseurs!$A$5:$A$24,0)),"")) -> 0 | X30: =IF($C30="","",IFERROR(INDEX(Fournisseurs!$B$5:$B$24,MATCH($C30,Fournisseurs!$A$5:$A$24,0)),"")) -> 0 | Y30: =IF($A30="","",IF(AND($A30<>"",$C30<>"",ISNUMBER($I30),ISNUMBER($J30),ISNUMBER($M30)),IF(AND($I30>=1,$J30>0,OR($K30="HT",$K30="TTC"),$M30>=1,IFERROR(INDEX(Fournisseurs!$T$5:$T$24,MATCH($C30,Fournisseurs!$A$5:$A$24,0)),0)=1),1,0),0)) -> 0 | Z30: =IF($Y30=1,$J30*(1-N($L30)),"") | AA30: =IF($Y30=1,IF($K30="TTC",$Z30/(1+$V30),$Z30),"") | AB30: =IF($Y30=1,IF($K30="TTC",$Z30-$AA30,$AA30*$V30),"") | AC30: =IF($Y30=1,$AA30*$U30*$M30,"") | AD30: =IF($Y30=1,$AC30/SUMIFS($AC$6:$AC$205,$C$6:$C$205,$C30,$Y$6:$Y$205,1),"") | AE30: =IF($Y30=1,(INDEX(Fournisseurs!$J$5:$J$24,MATCH($C30,Fournisseurs!$A$5:$A$24,0))+INDEX(Fournisseurs!$K$5:$K$24,MATCH($C30,Fournisseurs!$A$5:$A$24,0)))*$U30*$AD30/($I30*$M30),"") | AF30: =IF($Y30=1,INDEX(Fournisseurs!$L$5:$L$24,MATCH($C30,Fournisseurs!$A$5:$A$24,0))*$AD30/($I30*$M30),"") | AG30: =IF($Y30=1,$AA30*$U30/$I30,"") | AH30: =IF($Y30=1,$AB30*$U30/$I30,"") | AI30: =IF($Y30=1,IF(AND(Paramètres!$B$4="EFFECTIVE",$W30="CH",$AB30>0),1,0),"") | AJ30: =IF($Y30=1,IF($X30<>"CH",($AG30+$AE30+$AF30)*Paramètres!$B$14,0),"") | AK30: =IF($Y30=1,$AG30+IF($AI30=1,0,$AH30)+$AE30+$AF30+IF(Paramètres!$B$4="NOT_REGISTERED",$AJ30,0),"") | AL30: =IF($Y30=1,($AK30+Paramètres!$B$7+Paramètres!$B$8+Paramètres!$B$9+Paramètres!$B$10)/((1-Paramètres!$B$11)/(1+Paramètres!$B$5)-Paramètres!$B$6),"") | AM30: =IF(AND($Y30=1,ISNUMBER($R30)),IF($R30>0,$AL30/$R30-1,""),"") | AN30: =IF(AND($Y30=1,ISNUMBER($R30)),IF($R30>0,$R30/(1+Paramètres!$B$5)-$AK30-($R30*Paramètres!$B$6+Paramètres!$B$7)-Paramètres!$B$8-Paramètres!$B$9-Paramètres!$B$10,""),"") | AO30: =IF(ISNUMBER($AN30),$AN30/($R30/(1+Paramètres!$B$5)),"") | AP30: =IF($A30="","",IF($Y30<>1,"INCOMPLET",IF(NOT(ISNUMBER($AM30)),"SANS RÉF. MARCHÉ",IF($AM30<=Paramètres!$B$12,"OK",IF(AND($AO30>=Paramètres!$B$15,$AN30>=Paramètres!$B$16),"À REVOIR","NON RENTABLE"))))) -> INCOMPLET | AQ30: =TRIM(IF(AND($Y30=1,ISNUMBER($N30)),IF($M30<$N30,"MOQ ",""),"")&IF(AND($Y30=1,ISNUMBER($O30)),IF($O30<$I30*$M30,"DISPO ",""),"")&IF($S30="O","FICTIF ","")&IF($Y30=1,IF(AND($K30="TTC",$W30<>"CH"),"TVA-ÉTRANGÈRE ",""),"")) | AR30: =IF($Y30=1,COUNTIFS($A$6:$A$205,$A30,$AK$6:$AK$205,"<"&$AK30,$Y$6:$Y$205,1)+1,"") | AS30: =IF(ISNUMBER($AR30),$A30&"|"&$AR30,"") | AT30: =IF($Y30=1,$AK30*$I30*$M30,"")
A31: REF-07 | B31: Coffret Dresseur d'Élite (ETB) Méga-Évolution – Nuit Noire – FR | C31: Matoo et Miao | G31: Méga-Évolution – Nuit Noire | H31: etb | S31: N | T31: =IF($C31="","",IFERROR(INDEX(Fournisseurs!$C$5:$C$24,MATCH($C31,Fournisseurs!$A$5:$A$24,0)),"")) -> 0 | U31: =IF($C31="","",IFERROR(INDEX(Fournisseurs!$D$5:$D$24,MATCH($C31,Fournisseurs!$A$5:$A$24,0)),"")) -> 0 | V31: =IF($C31="","",IFERROR(INDEX(Fournisseurs!$G$5:$G$24,MATCH($C31,Fournisseurs!$A$5:$A$24,0)),"")) -> 0 | W31: =IF($C31="","",IFERROR(INDEX(Fournisseurs!$H$5:$H$24,MATCH($C31,Fournisseurs!$A$5:$A$24,0)),"")) -> 0 | X31: =IF($C31="","",IFERROR(INDEX(Fournisseurs!$B$5:$B$24,MATCH($C31,Fournisseurs!$A$5:$A$24,0)),"")) -> 0 | Y31: =IF($A31="","",IF(AND($A31<>"",$C31<>"",ISNUMBER($I31),ISNUMBER($J31),ISNUMBER($M31)),IF(AND($I31>=1,$J31>0,OR($K31="HT",$K31="TTC"),$M31>=1,IFERROR(INDEX(Fournisseurs!$T$5:$T$24,MATCH($C31,Fournisseurs!$A$5:$A$24,0)),0)=1),1,0),0)) -> 0 | Z31: =IF($Y31=1,$J31*(1-N($L31)),"") | AA31: =IF($Y31=1,IF($K31="TTC",$Z31/(1+$V31),$Z31),"") | AB31: =IF($Y31=1,IF($K31="TTC",$Z31-$AA31,$AA31*$V31),"") | AC31: =IF($Y31=1,$AA31*$U31*$M31,"") | AD31: =IF($Y31=1,$AC31/SUMIFS($AC$6:$AC$205,$C$6:$C$205,$C31,$Y$6:$Y$205,1),"") | AE31: =IF($Y31=1,(INDEX(Fournisseurs!$J$5:$J$24,MATCH($C31,Fournisseurs!$A$5:$A$24,0))+INDEX(Fournisseurs!$K$5:$K$24,MATCH($C31,Fournisseurs!$A$5:$A$24,0)))*$U31*$AD31/($I31*$M31),"") | AF31: =IF($Y31=1,INDEX(Fournisseurs!$L$5:$L$24,MATCH($C31,Fournisseurs!$A$5:$A$24,0))*$AD31/($I31*$M31),"") | AG31: =IF($Y31=1,$AA31*$U31/$I31,"") | AH31: =IF($Y31=1,$AB31*$U31/$I31,"") | AI31: =IF($Y31=1,IF(AND(Paramètres!$B$4="EFFECTIVE",$W31="CH",$AB31>0),1,0),"") | AJ31: =IF($Y31=1,IF($X31<>"CH",($AG31+$AE31+$AF31)*Paramètres!$B$14,0),"") | AK31: =IF($Y31=1,$AG31+IF($AI31=1,0,$AH31)+$AE31+$AF31+IF(Paramètres!$B$4="NOT_REGISTERED",$AJ31,0),"") | AL31: =IF($Y31=1,($AK31+Paramètres!$B$7+Paramètres!$B$8+Paramètres!$B$9+Paramètres!$B$10)/((1-Paramètres!$B$11)/(1+Paramètres!$B$5)-Paramètres!$B$6),"") | AM31: =IF(AND($Y31=1,ISNUMBER($R31)),IF($R31>0,$AL31/$R31-1,""),"") | AN31: =IF(AND($Y31=1,ISNUMBER($R31)),IF($R31>0,$R31/(1+Paramètres!$B$5)-$AK31-($R31*Paramètres!$B$6+Paramètres!$B$7)-Paramètres!$B$8-Paramètres!$B$9-Paramètres!$B$10,""),"") | AO31: =IF(ISNUMBER($AN31),$AN31/($R31/(1+Paramètres!$B$5)),"") | AP31: =IF($A31="","",IF($Y31<>1,"INCOMPLET",IF(NOT(ISNUMBER($AM31)),"SANS RÉF. MARCHÉ",IF($AM31<=Paramètres!$B$12,"OK",IF(AND($AO31>=Paramètres!$B$15,$AN31>=Paramètres!$B$16),"À REVOIR","NON RENTABLE"))))) -> INCOMPLET | AQ31: =TRIM(IF(AND($Y31=1,ISNUMBER($N31)),IF($M31<$N31,"MOQ ",""),"")&IF(AND($Y31=1,ISNUMBER($O31)),IF($O31<$I31*$M31,"DISPO ",""),"")&IF($S31="O","FICTIF ","")&IF($Y31=1,IF(AND($K31="TTC",$W31<>"CH"),"TVA-ÉTRANGÈRE ",""),"")) | AR31: =IF($Y31=1,COUNTIFS($A$6:$A$205,$A31,$AK$6:$AK$205,"<"&$AK31,$Y$6:$Y$205,1)+1,"") | AS31: =IF(ISNUMBER($AR31),$A31&"|"&$AR31,"") | AT31: =IF($Y31=1,$AK31*$I31*$M31,"")
A32: REF-11 | B32: Coffret Dresseur d'Élite (ETB) Méga-Évolution – Équilibre Parfait – FR | C32: Matoo et Miao | G32: Méga-Évolution – Équilibre Parfait | H32: etb | S32: N | T32: =IF($C32="","",IFERROR(INDEX(Fournisseurs!$C$5:$C$24,MATCH($C32,Fournisseurs!$A$5:$A$24,0)),"")) -> 0 | U32: =IF($C32="","",IFERROR(INDEX(Fournisseurs!$D$5:$D$24,MATCH($C32,Fournisseurs!$A$5:$A$24,0)),"")) -> 0 | V32: =IF($C32="","",IFERROR(INDEX(Fournisseurs!$G$5:$G$24,MATCH($C32,Fournisseurs!$A$5:$A$24,0)),"")) -> 0 | W32: =IF($C32="","",IFERROR(INDEX(Fournisseurs!$H$5:$H$24,MATCH($C32,Fournisseurs!$A$5:$A$24,0)),"")) -> 0 | X32: =IF($C32="","",IFERROR(INDEX(Fournisseurs!$B$5:$B$24,MATCH($C32,Fournisseurs!$A$5:$A$24,0)),"")) -> 0 | Y32: =IF($A32="","",IF(AND($A32<>"",$C32<>"",ISNUMBER($I32),ISNUMBER($J32),ISNUMBER($M32)),IF(AND($I32>=1,$J32>0,OR($K32="HT",$K32="TTC"),$M32>=1,IFERROR(INDEX(Fournisseurs!$T$5:$T$24,MATCH($C32,Fournisseurs!$A$5:$A$24,0)),0)=1),1,0),0)) -> 0 | Z32: =IF($Y32=1,$J32*(1-N($L32)),"") | AA32: =IF($Y32=1,IF($K32="TTC",$Z32/(1+$V32),$Z32),"") | AB32: =IF($Y32=1,IF($K32="TTC",$Z32-$AA32,$AA32*$V32),"") | AC32: =IF($Y32=1,$AA32*$U32*$M32,"") | AD32: =IF($Y32=1,$AC32/SUMIFS($AC$6:$AC$205,$C$6:$C$205,$C32,$Y$6:$Y$205,1),"") | AE32: =IF($Y32=1,(INDEX(Fournisseurs!$J$5:$J$24,MATCH($C32,Fournisseurs!$A$5:$A$24,0))+INDEX(Fournisseurs!$K$5:$K$24,MATCH($C32,Fournisseurs!$A$5:$A$24,0)))*$U32*$AD32/($I32*$M32),"") | AF32: =IF($Y32=1,INDEX(Fournisseurs!$L$5:$L$24,MATCH($C32,Fournisseurs!$A$5:$A$24,0))*$AD32/($I32*$M32),"") | AG32: =IF($Y32=1,$AA32*$U32/$I32,"") | AH32: =IF($Y32=1,$AB32*$U32/$I32,"") | AI32: =IF($Y32=1,IF(AND(Paramètres!$B$4="EFFECTIVE",$W32="CH",$AB32>0),1,0),"") | AJ32: =IF($Y32=1,IF($X32<>"CH",($AG32+$AE32+$AF32)*Paramètres!$B$14,0),"") | AK32: =IF($Y32=1,$AG32+IF($AI32=1,0,$AH32)+$AE32+$AF32+IF(Paramètres!$B$4="NOT_REGISTERED",$AJ32,0),"") | AL32: =IF($Y32=1,($AK32+Paramètres!$B$7+Paramètres!$B$8+Paramètres!$B$9+Paramètres!$B$10)/((1-Paramètres!$B$11)/(1+Paramètres!$B$5)-Paramètres!$B$6),"") | AM32: =IF(AND($Y32=1,ISNUMBER($R32)),IF($R32>0,$AL32/$R32-1,""),"") | AN32: =IF(AND($Y32=1,ISNUMBER($R32)),IF($R32>0,$R32/(1+Paramètres!$B$5)-$AK32-($R32*Paramètres!$B$6+Paramètres!$B$7)-Paramètres!$B$8-Paramètres!$B$9-Paramètres!$B$10,""),"") | AO32: =IF(ISNUMBER($AN32),$AN32/($R32/(1+Paramètres!$B$5)),"") | AP32: =IF($A32="","",IF($Y32<>1,"INCOMPLET",IF(NOT(ISNUMBER($AM32)),"SANS RÉF. MARCHÉ",IF($AM32<=Paramètres!$B$12,"OK",IF(AND($AO32>=Paramètres!$B$15,$AN32>=Paramètres!$B$16),"À REVOIR","NON RENTABLE"))))) -> INCOMPLET | AQ32: =TRIM(IF(AND($Y32=1,ISNUMBER($N32)),IF($M32<$N32,"MOQ ",""),"")&IF(AND($Y32=1,ISNUMBER($O32)),IF($O32<$I32*$M32,"DISPO ",""),"")&IF($S32="O","FICTIF ","")&IF($Y32=1,IF(AND($K32="TTC",$W32<>"CH"),"TVA-ÉTRANGÈRE ",""),"")) | AR32: =IF($Y32=1,COUNTIFS($A$6:$A$205,$A32,$AK$6:$AK$205,"<"&$AK32,$Y$6:$Y$205,1)+1,"") | AS32: =IF(ISNUMBER($AR32),$A32&"|"&$AR32,"") | AT32: =IF($Y32=1,$AK32*$I32*$M32,"")
A33: REF-02 | B33: Bundle 30ᵉ Anniversaire – FR | C33: Matoo et Miao | G33: 30ᵉ Anniversaire | H33: bundle | S33: N | T33: =IF($C33="","",IFERROR(INDEX(Fournisseurs!$C$5:$C$24,MATCH($C33,Fournisseurs!$A$5:$A$24,0)),"")) -> 0 | U33: =IF($C33="","",IFERROR(INDEX(Fournisseurs!$D$5:$D$24,MATCH($C33,Fournisseurs!$A$5:$A$24,0)),"")) -> 0 | V33: =IF($C33="","",IFERROR(INDEX(Fournisseurs!$G$5:$G$24,MATCH($C33,Fournisseurs!$A$5:$A$24,0)),"")) -> 0 | W33: =IF($C33="","",IFERROR(INDEX(Fournisseurs!$H$5:$H$24,MATCH($C33,Fournisseurs!$A$5:$A$24,0)),"")) -> 0 | X33: =IF($C33="","",IFERROR(INDEX(Fournisseurs!$B$5:$B$24,MATCH($C33,Fournisseurs!$A$5:$A$24,0)),"")) -> 0 | Y33: =IF($A33="","",IF(AND($A33<>"",$C33<>"",ISNUMBER($I33),ISNUMBER($J33),ISNUMBER($M33)),IF(AND($I33>=1,$J33>0,OR($K33="HT",$K33="TTC"),$M33>=1,IFERROR(INDEX(Fournisseurs!$T$5:$T$24,MATCH($C33,Fournisseurs!$A$5:$A$24,0)),0)=1),1,0),0)) -> 0 | Z33: =IF($Y33=1,$J33*(1-N($L33)),"") | AA33: =IF($Y33=1,IF($K33="TTC",$Z33/(1+$V33),$Z33),"") | AB33: =IF($Y33=1,IF($K33="TTC",$Z33-$AA33,$AA33*$V33),"") | AC33: =IF($Y33=1,$AA33*$U33*$M33,"") | AD33: =IF($Y33=1,$AC33/SUMIFS($AC$6:$AC$205,$C$6:$C$205,$C33,$Y$6:$Y$205,1),"") | AE33: =IF($Y33=1,(INDEX(Fournisseurs!$J$5:$J$24,MATCH($C33,Fournisseurs!$A$5:$A$24,0))+INDEX(Fournisseurs!$K$5:$K$24,MATCH($C33,Fournisseurs!$A$5:$A$24,0)))*$U33*$AD33/($I33*$M33),"") | AF33: =IF($Y33=1,INDEX(Fournisseurs!$L$5:$L$24,MATCH($C33,Fournisseurs!$A$5:$A$24,0))*$AD33/($I33*$M33),"") | AG33: =IF($Y33=1,$AA33*$U33/$I33,"") | AH33: =IF($Y33=1,$AB33*$U33/$I33,"") | AI33: =IF($Y33=1,IF(AND(Paramètres!$B$4="EFFECTIVE",$W33="CH",$AB33>0),1,0),"") | AJ33: =IF($Y33=1,IF($X33<>"CH",($AG33+$AE33+$AF33)*Paramètres!$B$14,0),"") | AK33: =IF($Y33=1,$AG33+IF($AI33=1,0,$AH33)+$AE33+$AF33+IF(Paramètres!$B$4="NOT_REGISTERED",$AJ33,0),"") | AL33: =IF($Y33=1,($AK33+Paramètres!$B$7+Paramètres!$B$8+Paramètres!$B$9+Paramètres!$B$10)/((1-Paramètres!$B$11)/(1+Paramètres!$B$5)-Paramètres!$B$6),"") | AM33: =IF(AND($Y33=1,ISNUMBER($R33)),IF($R33>0,$AL33/$R33-1,""),"") | AN33: =IF(AND($Y33=1,ISNUMBER($R33)),IF($R33>0,$R33/(1+Paramètres!$B$5)-$AK33-($R33*Paramètres!$B$6+Paramètres!$B$7)-Paramètres!$B$8-Paramètres!$B$9-Paramètres!$B$10,""),"") | AO33: =IF(ISNUMBER($AN33),$AN33/($R33/(1+Paramètres!$B$5)),"") | AP33: =IF($A33="","",IF($Y33<>1,"INCOMPLET",IF(NOT(ISNUMBER($AM33)),"SANS RÉF. MARCHÉ",IF($AM33<=Paramètres!$B$12,"OK",IF(AND($AO33>=Paramètres!$B$15,$AN33>=Paramètres!$B$16),"À REVOIR","NON RENTABLE"))))) -> INCOMPLET | AQ33: =TRIM(IF(AND($Y33=1,ISNUMBER($N33)),IF($M33<$N33,"MOQ ",""),"")&IF(AND($Y33=1,ISNUMBER($O33)),IF($O33<$I33*$M33,"DISPO ",""),"")&IF($S33="O","FICTIF ","")&IF($Y33=1,IF(AND($K33="TTC",$W33<>"CH"),"TVA-ÉTRANGÈRE ",""),"")) | AR33: =IF($Y33=1,COUNTIFS($A$6:$A$205,$A33,$AK$6:$AK$205,"<"&$AK33,$Y$6:$Y$205,1)+1,"") | AS33: =IF(ISNUMBER($AR33),$A33&"|"&$AR33,"") | AT33: =IF($Y33=1,$AK33*$I33*$M33,"")
A34: REF-08 | B34: Tripack Méga-Évolution – Nuit Noire – FR | C34: Matoo et Miao | G34: Méga-Évolution – Nuit Noire | H34: tripack | S34: N | T34: =IF($C34="","",IFERROR(INDEX(Fournisseurs!$C$5:$C$24,MATCH($C34,Fournisseurs!$A$5:$A$24,0)),"")) -> 0 | U34: =IF($C34="","",IFERROR(INDEX(Fournisseurs!$D$5:$D$24,MATCH($C34,Fournisseurs!$A$5:$A$24,0)),"")) -> 0 | V34: =IF($C34="","",IFERROR(INDEX(Fournisseurs!$G$5:$G$24,MATCH($C34,Fournisseurs!$A$5:$A$24,0)),"")) -> 0 | W34: =IF($C34="","",IFERROR(INDEX(Fournisseurs!$H$5:$H$24,MATCH($C34,Fournisseurs!$A$5:$A$24,0)),"")) -> 0 | X34: =IF($C34="","",IFERROR(INDEX(Fournisseurs!$B$5:$B$24,MATCH($C34,Fournisseurs!$A$5:$A$24,0)),"")) -> 0 | Y34: =IF($A34="","",IF(AND($A34<>"",$C34<>"",ISNUMBER($I34),ISNUMBER($J34),ISNUMBER($M34)),IF(AND($I34>=1,$J34>0,OR($K34="HT",$K34="TTC"),$M34>=1,IFERROR(INDEX(Fournisseurs!$T$5:$T$24,MATCH($C34,Fournisseurs!$A$5:$A$24,0)),0)=1),1,0),0)) -> 0 | Z34: =IF($Y34=1,$J34*(1-N($L34)),"") | AA34: =IF($Y34=1,IF($K34="TTC",$Z34/(1+$V34),$Z34),"") | AB34: =IF($Y34=1,IF($K34="TTC",$Z34-$AA34,$AA34*$V34),"") | AC34: =IF($Y34=1,$AA34*$U34*$M34,"") | AD34: =IF($Y34=1,$AC34/SUMIFS($AC$6:$AC$205,$C$6:$C$205,$C34,$Y$6:$Y$205,1),"") | AE34: =IF($Y34=1,(INDEX(Fournisseurs!$J$5:$J$24,MATCH($C34,Fournisseurs!$A$5:$A$24,0))+INDEX(Fournisseurs!$K$5:$K$24,MATCH($C34,Fournisseurs!$A$5:$A$24,0)))*$U34*$AD34/($I34*$M34),"") | AF34: =IF($Y34=1,INDEX(Fournisseurs!$L$5:$L$24,MATCH($C34,Fournisseurs!$A$5:$A$24,0))*$AD34/($I34*$M34),"") | AG34: =IF($Y34=1,$AA34*$U34/$I34,"") | AH34: =IF($Y34=1,$AB34*$U34/$I34,"") | AI34: =IF($Y34=1,IF(AND(Paramètres!$B$4="EFFECTIVE",$W34="CH",$AB34>0),1,0),"") | AJ34: =IF($Y34=1,IF($X34<>"CH",($AG34+$AE34+$AF34)*Paramètres!$B$14,0),"") | AK34: =IF($Y34=1,$AG34+IF($AI34=1,0,$AH34)+$AE34+$AF34+IF(Paramètres!$B$4="NOT_REGISTERED",$AJ34,0),"") | AL34: =IF($Y34=1,($AK34+Paramètres!$B$7+Paramètres!$B$8+Paramètres!$B$9+Paramètres!$B$10)/((1-Paramètres!$B$11)/(1+Paramètres!$B$5)-Paramètres!$B$6),"") | AM34: =IF(AND($Y34=1,ISNUMBER($R34)),IF($R34>0,$AL34/$R34-1,""),"") | AN34: =IF(AND($Y34=1,ISNUMBER($R34)),IF($R34>0,$R34/(1+Paramètres!$B$5)-$AK34-($R34*Paramètres!$B$6+Paramètres!$B$7)-Paramètres!$B$8-Paramètres!$B$9-Paramètres!$B$10,""),"") | AO34: =IF(ISNUMBER($AN34),$AN34/($R34/(1+Paramètres!$B$5)),"") | AP34: =IF($A34="","",IF($Y34<>1,"INCOMPLET",IF(NOT(ISNUMBER($AM34)),"SANS RÉF. MARCHÉ",IF($AM34<=Paramètres!$B$12,"OK",IF(AND($AO34>=Paramètres!$B$15,$AN34>=Paramètres!$B$16),"À REVOIR","NON RENTABLE"))))) -> INCOMPLET | AQ34: =TRIM(IF(AND($Y34=1,ISNUMBER($N34)),IF($M34<$N34,"MOQ ",""),"")&IF(AND($Y34=1,ISNUMBER($O34)),IF($O34<$I34*$M34,"DISPO ",""),"")&IF($S34="O","FICTIF ","")&IF($Y34=1,IF(AND($K34="TTC",$W34<>"CH"),"TVA-ÉTRANGÈRE ",""),"")) | AR34: =IF($Y34=1,COUNTIFS($A$6:$A$205,$A34,$AK$6:$AK$205,"<"&$AK34,$Y$6:$Y$205,1)+1,"") | AS34: =IF(ISNUMBER($AR34),$A34&"|"&$AR34,"") | AT34: =IF($Y34=1,$AK34*$I34*$M34,"")
A35: REF-19 | B35: Tripack ou bundle Méga-Évolution – Chaos Ascendant – FR | C35: Matoo et Miao | G35: Méga-Évolution – Chaos Ascendant | H35: tripack | S35: N | T35: =IF($C35="","",IFERROR(INDEX(Fournisseurs!$C$5:$C$24,MATCH($C35,Fournisseurs!$A$5:$A$24,0)),"")) -> 0 | U35: =IF($C35="","",IFERROR(INDEX(Fournisseurs!$D$5:$D$24,MATCH($C35,Fournisseurs!$A$5:$A$24,0)),"")) -> 0 | V35: =IF($C35="","",IFERROR(INDEX(Fournisseurs!$G$5:$G$24,MATCH($C35,Fournisseurs!$A$5:$A$24,0)),"")) -> 0 | W35: =IF($C35="","",IFERROR(INDEX(Fournisseurs!$H$5:$H$24,MATCH($C35,Fournisseurs!$A$5:$A$24,0)),"")) -> 0 | X35: =IF($C35="","",IFERROR(INDEX(Fournisseurs!$B$5:$B$24,MATCH($C35,Fournisseurs!$A$5:$A$24,0)),"")) -> 0 | Y35: =IF($A35="","",IF(AND($A35<>"",$C35<>"",ISNUMBER($I35),ISNUMBER($J35),ISNUMBER($M35)),IF(AND($I35>=1,$J35>0,OR($K35="HT",$K35="TTC"),$M35>=1,IFERROR(INDEX(Fournisseurs!$T$5:$T$24,MATCH($C35,Fournisseurs!$A$5:$A$24,0)),0)=1),1,0),0)) -> 0 | Z35: =IF($Y35=1,$J35*(1-N($L35)),"") | AA35: =IF($Y35=1,IF($K35="TTC",$Z35/(1+$V35),$Z35),"") | AB35: =IF($Y35=1,IF($K35="TTC",$Z35-$AA35,$AA35*$V35),"") | AC35: =IF($Y35=1,$AA35*$U35*$M35,"") | AD35: =IF($Y35=1,$AC35/SUMIFS($AC$6:$AC$205,$C$6:$C$205,$C35,$Y$6:$Y$205,1),"") | AE35: =IF($Y35=1,(INDEX(Fournisseurs!$J$5:$J$24,MATCH($C35,Fournisseurs!$A$5:$A$24,0))+INDEX(Fournisseurs!$K$5:$K$24,MATCH($C35,Fournisseurs!$A$5:$A$24,0)))*$U35*$AD35/($I35*$M35),"") | AF35: =IF($Y35=1,INDEX(Fournisseurs!$L$5:$L$24,MATCH($C35,Fournisseurs!$A$5:$A$24,0))*$AD35/($I35*$M35),"") | AG35: =IF($Y35=1,$AA35*$U35/$I35,"") | AH35: =IF($Y35=1,$AB35*$U35/$I35,"") | AI35: =IF($Y35=1,IF(AND(Paramètres!$B$4="EFFECTIVE",$W35="CH",$AB35>0),1,0),"") | AJ35: =IF($Y35=1,IF($X35<>"CH",($AG35+$AE35+$AF35)*Paramètres!$B$14,0),"") | AK35: =IF($Y35=1,$AG35+IF($AI35=1,0,$AH35)+$AE35+$AF35+IF(Paramètres!$B$4="NOT_REGISTERED",$AJ35,0),"") | AL35: =IF($Y35=1,($AK35+Paramètres!$B$7+Paramètres!$B$8+Paramètres!$B$9+Paramètres!$B$10)/((1-Paramètres!$B$11)/(1+Paramètres!$B$5)-Paramètres!$B$6),"") | AM35: =IF(AND($Y35=1,ISNUMBER($R35)),IF($R35>0,$AL35/$R35-1,""),"") | AN35: =IF(AND($Y35=1,ISNUMBER($R35)),IF($R35>0,$R35/(1+Paramètres!$B$5)-$AK35-($R35*Paramètres!$B$6+Paramètres!$B$7)-Paramètres!$B$8-Paramètres!$B$9-Paramètres!$B$10,""),"") | AO35: =IF(ISNUMBER($AN35),$AN35/($R35/(1+Paramètres!$B$5)),"") | AP35: =IF($A35="","",IF($Y35<>1,"INCOMPLET",IF(NOT(ISNUMBER($AM35)),"SANS RÉF. MARCHÉ",IF($AM35<=Paramètres!$B$12,"OK",IF(AND($AO35>=Paramètres!$B$15,$AN35>=Paramètres!$B$16),"À REVOIR","NON RENTABLE"))))) -> INCOMPLET | AQ35: =TRIM(IF(AND($Y35=1,ISNUMBER($N35)),IF($M35<$N35,"MOQ ",""),"")&IF(AND($Y35=1,ISNUMBER($O35)),IF($O35<$I35*$M35,"DISPO ",""),"")&IF($S35="O","FICTIF ","")&IF($Y35=1,IF(AND($K35="TTC",$W35<>"CH"),"TVA-ÉTRANGÈRE ",""),"")) | AR35: =IF($Y35=1,COUNTIFS($A$6:$A$205,$A35,$AK$6:$AK$205,"<"&$AK35,$Y$6:$Y$205,1)+1,"") | AS35: =IF(ISNUMBER($AR35),$A35&"|"&$AR35,"") | AT35: =IF($Y35=1,$AK35*$I35*$M35,"")
A36: REF-04 | B36: Coffret 30ᵉ Anniversaire Nymphali-ex – FR | C36: Matoo et Miao | G36: 30ᵉ Anniversaire | H36: coffret | S36: N | T36: =IF($C36="","",IFERROR(INDEX(Fournisseurs!$C$5:$C$24,MATCH($C36,Fournisseurs!$A$5:$A$24,0)),"")) -> 0 | U36: =IF($C36="","",IFERROR(INDEX(Fournisseurs!$D$5:$D$24,MATCH($C36,Fournisseurs!$A$5:$A$24,0)),"")) -> 0 | V36: =IF($C36="","",IFERROR(INDEX(Fournisseurs!$G$5:$G$24,MATCH($C36,Fournisseurs!$A$5:$A$24,0)),"")) -> 0 | W36: =IF($C36="","",IFERROR(INDEX(Fournisseurs!$H$5:$H$24,MATCH($C36,Fournisseurs!$A$5:$A$24,0)),"")) -> 0 | X36: =IF($C36="","",IFERROR(INDEX(Fournisseurs!$B$5:$B$24,MATCH($C36,Fournisseurs!$A$5:$A$24,0)),"")) -> 0 | Y36: =IF($A36="","",IF(AND($A36<>"",$C36<>"",ISNUMBER($I36),ISNUMBER($J36),ISNUMBER($M36)),IF(AND($I36>=1,$J36>0,OR($K36="HT",$K36="TTC"),$M36>=1,IFERROR(INDEX(Fournisseurs!$T$5:$T$24,MATCH($C36,Fournisseurs!$A$5:$A$24,0)),0)=1),1,0),0)) -> 0 | Z36: =IF($Y36=1,$J36*(1-N($L36)),"") | AA36: =IF($Y36=1,IF($K36="TTC",$Z36/(1+$V36),$Z36),"") | AB36: =IF($Y36=1,IF($K36="TTC",$Z36-$AA36,$AA36*$V36),"") | AC36: =IF($Y36=1,$AA36*$U36*$M36,"") | AD36: =IF($Y36=1,$AC36/SUMIFS($AC$6:$AC$205,$C$6:$C$205,$C36,$Y$6:$Y$205,1),"") | AE36: =IF($Y36=1,(INDEX(Fournisseurs!$J$5:$J$24,MATCH($C36,Fournisseurs!$A$5:$A$24,0))+INDEX(Fournisseurs!$K$5:$K$24,MATCH($C36,Fournisseurs!$A$5:$A$24,0)))*$U36*$AD36/($I36*$M36),"") | AF36: =IF($Y36=1,INDEX(Fournisseurs!$L$5:$L$24,MATCH($C36,Fournisseurs!$A$5:$A$24,0))*$AD36/($I36*$M36),"") | AG36: =IF($Y36=1,$AA36*$U36/$I36,"") | AH36: =IF($Y36=1,$AB36*$U36/$I36,"") | AI36: =IF($Y36=1,IF(AND(Paramètres!$B$4="EFFECTIVE",$W36="CH",$AB36>0),1,0),"") | AJ36: =IF($Y36=1,IF($X36<>"CH",($AG36+$AE36+$AF36)*Paramètres!$B$14,0),"") | AK36: =IF($Y36=1,$AG36+IF($AI36=1,0,$AH36)+$AE36+$AF36+IF(Paramètres!$B$4="NOT_REGISTERED",$AJ36,0),"") | AL36: =IF($Y36=1,($AK36+Paramètres!$B$7+Paramètres!$B$8+Paramètres!$B$9+Paramètres!$B$10)/((1-Paramètres!$B$11)/(1+Paramètres!$B$5)-Paramètres!$B$6),"") | AM36: =IF(AND($Y36=1,ISNUMBER($R36)),IF($R36>0,$AL36/$R36-1,""),"") | AN36: =IF(AND($Y36=1,ISNUMBER($R36)),IF($R36>0,$R36/(1+Paramètres!$B$5)-$AK36-($R36*Paramètres!$B$6+Paramètres!$B$7)-Paramètres!$B$8-Paramètres!$B$9-Paramètres!$B$10,""),"") | AO36: =IF(ISNUMBER($AN36),$AN36/($R36/(1+Paramètres!$B$5)),"") | AP36: =IF($A36="","",IF($Y36<>1,"INCOMPLET",IF(NOT(ISNUMBER($AM36)),"SANS RÉF. MARCHÉ",IF($AM36<=Paramètres!$B$12,"OK",IF(AND($AO36>=Paramètres!$B$15,$AN36>=Paramètres!$B$16),"À REVOIR","NON RENTABLE"))))) -> INCOMPLET | AQ36: =TRIM(IF(AND($Y36=1,ISNUMBER($N36)),IF($M36<$N36,"MOQ ",""),"")&IF(AND($Y36=1,ISNUMBER($O36)),IF($O36<$I36*$M36,"DISPO ",""),"")&IF($S36="O","FICTIF ","")&IF($Y36=1,IF(AND($K36="TTC",$W36<>"CH"),"TVA-ÉTRANGÈRE ",""),"")) | AR36: =IF($Y36=1,COUNTIFS($A$6:$A$205,$A36,$AK$6:$AK$205,"<"&$AK36,$Y$6:$Y$205,1)+1,"") | AS36: =IF(ISNUMBER($AR36),$A36&"|"&$AR36,"") | AT36: =IF($Y36=1,$AK36*$I36*$M36,"")
A37: REF-20 | B37: Coffret ou collection – Équilibre Parfait ou Héros Transcendants – FR | C37: Matoo et Miao | G37: Méga-Évolution – Équilibre Parfait / Héros Transcendants | H37: coffret | S37: N | T37: =IF($C37="","",IFERROR(INDEX(Fournisseurs!$C$5:$C$24,MATCH($C37,Fournisseurs!$A$5:$A$24,0)),"")) -> 0 | U37: =IF($C37="","",IFERROR(INDEX(Fournisseurs!$D$5:$D$24,MATCH($C37,Fournisseurs!$A$5:$A$24,0)),"")) -> 0 | V37: =IF($C37="","",IFERROR(INDEX(Fournisseurs!$G$5:$G$24,MATCH($C37,Fournisseurs!$A$5:$A$24,0)),"")) -> 0 | W37: =IF($C37="","",IFERROR(INDEX(Fournisseurs!$H$5:$H$24,MATCH($C37,Fournisseurs!$A$5:$A$24,0)),"")) -> 0 | X37: =IF($C37="","",IFERROR(INDEX(Fournisseurs!$B$5:$B$24,MATCH($C37,Fournisseurs!$A$5:$A$24,0)),"")) -> 0 | Y37: =IF($A37="","",IF(AND($A37<>"",$C37<>"",ISNUMBER($I37),ISNUMBER($J37),ISNUMBER($M37)),IF(AND($I37>=1,$J37>0,OR($K37="HT",$K37="TTC"),$M37>=1,IFERROR(INDEX(Fournisseurs!$T$5:$T$24,MATCH($C37,Fournisseurs!$A$5:$A$24,0)),0)=1),1,0),0)) -> 0 | Z37: =IF($Y37=1,$J37*(1-N($L37)),"") | AA37: =IF($Y37=1,IF($K37="TTC",$Z37/(1+$V37),$Z37),"") | AB37: =IF($Y37=1,IF($K37="TTC",$Z37-$AA37,$AA37*$V37),"") | AC37: =IF($Y37=1,$AA37*$U37*$M37,"") | AD37: =IF($Y37=1,$AC37/SUMIFS($AC$6:$AC$205,$C$6:$C$205,$C37,$Y$6:$Y$205,1),"") | AE37: =IF($Y37=1,(INDEX(Fournisseurs!$J$5:$J$24,MATCH($C37,Fournisseurs!$A$5:$A$24,0))+INDEX(Fournisseurs!$K$5:$K$24,MATCH($C37,Fournisseurs!$A$5:$A$24,0)))*$U37*$AD37/($I37*$M37),"") | AF37: =IF($Y37=1,INDEX(Fournisseurs!$L$5:$L$24,MATCH($C37,Fournisseurs!$A$5:$A$24,0))*$AD37/($I37*$M37),"") | AG37: =IF($Y37=1,$AA37*$U37/$I37,"") | AH37: =IF($Y37=1,$AB37*$U37/$I37,"") | AI37: =IF($Y37=1,IF(AND(Paramètres!$B$4="EFFECTIVE",$W37="CH",$AB37>0),1,0),"") | AJ37: =IF($Y37=1,IF($X37<>"CH",($AG37+$AE37+$AF37)*Paramètres!$B$14,0),"") | AK37: =IF($Y37=1,$AG37+IF($AI37=1,0,$AH37)+$AE37+$AF37+IF(Paramètres!$B$4="NOT_REGISTERED",$AJ37,0),"") | AL37: =IF($Y37=1,($AK37+Paramètres!$B$7+Paramètres!$B$8+Paramètres!$B$9+Paramètres!$B$10)/((1-Paramètres!$B$11)/(1+Paramètres!$B$5)-Paramètres!$B$6),"") | AM37: =IF(AND($Y37=1,ISNUMBER($R37)),IF($R37>0,$AL37/$R37-1,""),"") | AN37: =IF(AND($Y37=1,ISNUMBER($R37)),IF($R37>0,$R37/(1+Paramètres!$B$5)-$AK37-($R37*Paramètres!$B$6+Paramètres!$B$7)-Paramètres!$B$8-Paramètres!$B$9-Paramètres!$B$10,""),"") | AO37: =IF(ISNUMBER($AN37),$AN37/($R37/(1+Paramètres!$B$5)),"") | AP37: =IF($A37="","",IF($Y37<>1,"INCOMPLET",IF(NOT(ISNUMBER($AM37)),"SANS RÉF. MARCHÉ",IF($AM37<=Paramètres!$B$12,"OK",IF(AND($AO37>=Paramètres!$B$15,$AN37>=Paramètres!$B$16),"À REVOIR","NON RENTABLE"))))) -> INCOMPLET | AQ37: =TRIM(IF(AND($Y37=1,ISNUMBER($N37)),IF($M37<$N37,"MOQ ",""),"")&IF(AND($Y37=1,ISNUMBER($O37)),IF($O37<$I37*$M37,"DISPO ",""),"")&IF($S37="O","FICTIF ","")&IF($Y37=1,IF(AND($K37="TTC",$W37<>"CH"),"TVA-ÉTRANGÈRE ",""),"")) | AR37: =IF($Y37=1,COUNTIFS($A$6:$A$205,$A37,$AK$6:$AK$205,"<"&$AK37,$Y$6:$Y$205,1)+1,"") | AS37: =IF(ISNUMBER($AR37),$A37&"|"&$AR37,"") | AT37: =IF($Y37=1,$AK37*$I37*$M37,"")
A38: REF-16 | B38: Protège-cartes format standard (paquet) | C38: Matoo et Miao | H38: accessoire | S38: N | T38: =IF($C38="","",IFERROR(INDEX(Fournisseurs!$C$5:$C$24,MATCH($C38,Fournisseurs!$A$5:$A$24,0)),"")) -> 0 | U38: =IF($C38="","",IFERROR(INDEX(Fournisseurs!$D$5:$D$24,MATCH($C38,Fournisseurs!$A$5:$A$24,0)),"")) -> 0 | V38: =IF($C38="","",IFERROR(INDEX(Fournisseurs!$G$5:$G$24,MATCH($C38,Fournisseurs!$A$5:$A$24,0)),"")) -> 0 | W38: =IF($C38="","",IFERROR(INDEX(Fournisseurs!$H$5:$H$24,MATCH($C38,Fournisseurs!$A$5:$A$24,0)),"")) -> 0 | X38: =IF($C38="","",IFERROR(INDEX(Fournisseurs!$B$5:$B$24,MATCH($C38,Fournisseurs!$A$5:$A$24,0)),"")) -> 0 | Y38: =IF($A38="","",IF(AND($A38<>"",$C38<>"",ISNUMBER($I38),ISNUMBER($J38),ISNUMBER($M38)),IF(AND($I38>=1,$J38>0,OR($K38="HT",$K38="TTC"),$M38>=1,IFERROR(INDEX(Fournisseurs!$T$5:$T$24,MATCH($C38,Fournisseurs!$A$5:$A$24,0)),0)=1),1,0),0)) -> 0 | Z38: =IF($Y38=1,$J38*(1-N($L38)),"") | AA38: =IF($Y38=1,IF($K38="TTC",$Z38/(1+$V38),$Z38),"") | AB38: =IF($Y38=1,IF($K38="TTC",$Z38-$AA38,$AA38*$V38),"") | AC38: =IF($Y38=1,$AA38*$U38*$M38,"") | AD38: =IF($Y38=1,$AC38/SUMIFS($AC$6:$AC$205,$C$6:$C$205,$C38,$Y$6:$Y$205,1),"") | AE38: =IF($Y38=1,(INDEX(Fournisseurs!$J$5:$J$24,MATCH($C38,Fournisseurs!$A$5:$A$24,0))+INDEX(Fournisseurs!$K$5:$K$24,MATCH($C38,Fournisseurs!$A$5:$A$24,0)))*$U38*$AD38/($I38*$M38),"") | AF38: =IF($Y38=1,INDEX(Fournisseurs!$L$5:$L$24,MATCH($C38,Fournisseurs!$A$5:$A$24,0))*$AD38/($I38*$M38),"") | AG38: =IF($Y38=1,$AA38*$U38/$I38,"") | AH38: =IF($Y38=1,$AB38*$U38/$I38,"") | AI38: =IF($Y38=1,IF(AND(Paramètres!$B$4="EFFECTIVE",$W38="CH",$AB38>0),1,0),"") | AJ38: =IF($Y38=1,IF($X38<>"CH",($AG38+$AE38+$AF38)*Paramètres!$B$14,0),"") | AK38: =IF($Y38=1,$AG38+IF($AI38=1,0,$AH38)+$AE38+$AF38+IF(Paramètres!$B$4="NOT_REGISTERED",$AJ38,0),"") | AL38: =IF($Y38=1,($AK38+Paramètres!$B$7+Paramètres!$B$8+Paramètres!$B$9+Paramètres!$B$10)/((1-Paramètres!$B$11)/(1+Paramètres!$B$5)-Paramètres!$B$6),"") | AM38: =IF(AND($Y38=1,ISNUMBER($R38)),IF($R38>0,$AL38/$R38-1,""),"") | AN38: =IF(AND($Y38=1,ISNUMBER($R38)),IF($R38>0,$R38/(1+Paramètres!$B$5)-$AK38-($R38*Paramètres!$B$6+Paramètres!$B$7)-Paramètres!$B$8-Paramètres!$B$9-Paramètres!$B$10,""),"") | AO38: =IF(ISNUMBER($AN38),$AN38/($R38/(1+Paramètres!$B$5)),"") | AP38: =IF($A38="","",IF($Y38<>1,"INCOMPLET",IF(NOT(ISNUMBER($AM38)),"SANS RÉF. MARCHÉ",IF($AM38<=Paramètres!$B$12,"OK",IF(AND($AO38>=Paramètres!$B$15,$AN38>=Paramètres!$B$16),"À REVOIR","NON RENTABLE"))))) -> INCOMPLET | AQ38: =TRIM(IF(AND($Y38=1,ISNUMBER($N38)),IF($M38<$N38,"MOQ ",""),"")&IF(AND($Y38=1,ISNUMBER($O38)),IF($O38<$I38*$M38,"DISPO ",""),"")&IF($S38="O","FICTIF ","")&IF($Y38=1,IF(AND($K38="TTC",$W38<>"CH"),"TVA-ÉTRANGÈRE ",""),"")) | AR38: =IF($Y38=1,COUNTIFS($A$6:$A$205,$A38,$AK$6:$AK$205,"<"&$AK38,$Y$6:$Y$205,1)+1,"") | AS38: =IF(ISNUMBER($AR38),$A38&"|"&$AR38,"") | AT38: =IF($Y38=1,$AK38*$I38*$M38,"")
A39: REF-17 | B39: Classeur 9 cases | C39: Matoo et Miao | H39: accessoire | S39: N | T39: =IF($C39="","",IFERROR(INDEX(Fournisseurs!$C$5:$C$24,MATCH($C39,Fournisseurs!$A$5:$A$24,0)),"")) -> 0 | U39: =IF($C39="","",IFERROR(INDEX(Fournisseurs!$D$5:$D$24,MATCH($C39,Fournisseurs!$A$5:$A$24,0)),"")) -> 0 | V39: =IF($C39="","",IFERROR(INDEX(Fournisseurs!$G$5:$G$24,MATCH($C39,Fournisseurs!$A$5:$A$24,0)),"")) -> 0 | W39: =IF($C39="","",IFERROR(INDEX(Fournisseurs!$H$5:$H$24,MATCH($C39,Fournisseurs!$A$5:$A$24,0)),"")) -> 0 | X39: =IF($C39="","",IFERROR(INDEX(Fournisseurs!$B$5:$B$24,MATCH($C39,Fournisseurs!$A$5:$A$24,0)),"")) -> 0 | Y39: =IF($A39="","",IF(AND($A39<>"",$C39<>"",ISNUMBER($I39),ISNUMBER($J39),ISNUMBER($M39)),IF(AND($I39>=1,$J39>0,OR($K39="HT",$K39="TTC"),$M39>=1,IFERROR(INDEX(Fournisseurs!$T$5:$T$24,MATCH($C39,Fournisseurs!$A$5:$A$24,0)),0)=1),1,0),0)) -> 0 | Z39: =IF($Y39=1,$J39*(1-N($L39)),"") | AA39: =IF($Y39=1,IF($K39="TTC",$Z39/(1+$V39),$Z39),"") | AB39: =IF($Y39=1,IF($K39="TTC",$Z39-$AA39,$AA39*$V39),"") | AC39: =IF($Y39=1,$AA39*$U39*$M39,"") | AD39: =IF($Y39=1,$AC39/SUMIFS($AC$6:$AC$205,$C$6:$C$205,$C39,$Y$6:$Y$205,1),"") | AE39: =IF($Y39=1,(INDEX(Fournisseurs!$J$5:$J$24,MATCH($C39,Fournisseurs!$A$5:$A$24,0))+INDEX(Fournisseurs!$K$5:$K$24,MATCH($C39,Fournisseurs!$A$5:$A$24,0)))*$U39*$AD39/($I39*$M39),"") | AF39: =IF($Y39=1,INDEX(Fournisseurs!$L$5:$L$24,MATCH($C39,Fournisseurs!$A$5:$A$24,0))*$AD39/($I39*$M39),"") | AG39: =IF($Y39=1,$AA39*$U39/$I39,"") | AH39: =IF($Y39=1,$AB39*$U39/$I39,"") | AI39: =IF($Y39=1,IF(AND(Paramètres!$B$4="EFFECTIVE",$W39="CH",$AB39>0),1,0),"") | AJ39: =IF($Y39=1,IF($X39<>"CH",($AG39+$AE39+$AF39)*Paramètres!$B$14,0),"") | AK39: =IF($Y39=1,$AG39+IF($AI39=1,0,$AH39)+$AE39+$AF39+IF(Paramètres!$B$4="NOT_REGISTERED",$AJ39,0),"") | AL39: =IF($Y39=1,($AK39+Paramètres!$B$7+Paramètres!$B$8+Paramètres!$B$9+Paramètres!$B$10)/((1-Paramètres!$B$11)/(1+Paramètres!$B$5)-Paramètres!$B$6),"") | AM39: =IF(AND($Y39=1,ISNUMBER($R39)),IF($R39>0,$AL39/$R39-1,""),"") | AN39: =IF(AND($Y39=1,ISNUMBER($R39)),IF($R39>0,$R39/(1+Paramètres!$B$5)-$AK39-($R39*Paramètres!$B$6+Paramètres!$B$7)-Paramètres!$B$8-Paramètres!$B$9-Paramètres!$B$10,""),"") | AO39: =IF(ISNUMBER($AN39),$AN39/($R39/(1+Paramètres!$B$5)),"") | AP39: =IF($A39="","",IF($Y39<>1,"INCOMPLET",IF(NOT(ISNUMBER($AM39)),"SANS RÉF. MARCHÉ",IF($AM39<=Paramètres!$B$12,"OK",IF(AND($AO39>=Paramètres!$B$15,$AN39>=Paramètres!$B$16),"À REVOIR","NON RENTABLE"))))) -> INCOMPLET | AQ39: =TRIM(IF(AND($Y39=1,ISNUMBER($N39)),IF($M39<$N39,"MOQ ",""),"")&IF(AND($Y39=1,ISNUMBER($O39)),IF($O39<$I39*$M39,"DISPO ",""),"")&IF($S39="O","FICTIF ","")&IF($Y39=1,IF(AND($K39="TTC",$W39<>"CH"),"TVA-ÉTRANGÈRE ",""),"")) | AR39: =IF($Y39=1,COUNTIFS($A$6:$A$205,$A39,$AK$6:$AK$205,"<"&$AK39,$Y$6:$Y$205,1)+1,"") | AS39: =IF(ISNUMBER($AR39),$A39&"|"&$AR39,"") | AT39: =IF($Y39=1,$AK39*$I39*$M39,"")
A40: REF-03 | B40: Mini-Tin 30ᵉ Anniversaire – FR | C40: Matoo et Miao | G40: 30ᵉ Anniversaire | H40: coffret | S40: N | T40: =IF($C40="","",IFERROR(INDEX(Fournisseurs!$C$5:$C$24,MATCH($C40,Fournisseurs!$A$5:$A$24,0)),"")) -> 0 | U40: =IF($C40="","",IFERROR(INDEX(Fournisseurs!$D$5:$D$24,MATCH($C40,Fournisseurs!$A$5:$A$24,0)),"")) -> 0 | V40: =IF($C40="","",IFERROR(INDEX(Fournisseurs!$G$5:$G$24,MATCH($C40,Fournisseurs!$A$5:$A$24,0)),"")) -> 0 | W40: =IF($C40="","",IFERROR(INDEX(Fournisseurs!$H$5:$H$24,MATCH($C40,Fournisseurs!$A$5:$A$24,0)),"")) -> 0 | X40: =IF($C40="","",IFERROR(INDEX(Fournisseurs!$B$5:$B$24,MATCH($C40,Fournisseurs!$A$5:$A$24,0)),"")) -> 0 | Y40: =IF($A40="","",IF(AND($A40<>"",$C40<>"",ISNUMBER($I40),ISNUMBER($J40),ISNUMBER($M40)),IF(AND($I40>=1,$J40>0,OR($K40="HT",$K40="TTC"),$M40>=1,IFERROR(INDEX(Fournisseurs!$T$5:$T$24,MATCH($C40,Fournisseurs!$A$5:$A$24,0)),0)=1),1,0),0)) -> 0 | Z40: =IF($Y40=1,$J40*(1-N($L40)),"") | AA40: =IF($Y40=1,IF($K40="TTC",$Z40/(1+$V40),$Z40),"") | AB40: =IF($Y40=1,IF($K40="TTC",$Z40-$AA40,$AA40*$V40),"") | AC40: =IF($Y40=1,$AA40*$U40*$M40,"") | AD40: =IF($Y40=1,$AC40/SUMIFS($AC$6:$AC$205,$C$6:$C$205,$C40,$Y$6:$Y$205,1),"") | AE40: =IF($Y40=1,(INDEX(Fournisseurs!$J$5:$J$24,MATCH($C40,Fournisseurs!$A$5:$A$24,0))+INDEX(Fournisseurs!$K$5:$K$24,MATCH($C40,Fournisseurs!$A$5:$A$24,0)))*$U40*$AD40/($I40*$M40),"") | AF40: =IF($Y40=1,INDEX(Fournisseurs!$L$5:$L$24,MATCH($C40,Fournisseurs!$A$5:$A$24,0))*$AD40/($I40*$M40),"") | AG40: =IF($Y40=1,$AA40*$U40/$I40,"") | AH40: =IF($Y40=1,$AB40*$U40/$I40,"") | AI40: =IF($Y40=1,IF(AND(Paramètres!$B$4="EFFECTIVE",$W40="CH",$AB40>0),1,0),"") | AJ40: =IF($Y40=1,IF($X40<>"CH",($AG40+$AE40+$AF40)*Paramètres!$B$14,0),"") | AK40: =IF($Y40=1,$AG40+IF($AI40=1,0,$AH40)+$AE40+$AF40+IF(Paramètres!$B$4="NOT_REGISTERED",$AJ40,0),"") | AL40: =IF($Y40=1,($AK40+Paramètres!$B$7+Paramètres!$B$8+Paramètres!$B$9+Paramètres!$B$10)/((1-Paramètres!$B$11)/(1+Paramètres!$B$5)-Paramètres!$B$6),"") | AM40: =IF(AND($Y40=1,ISNUMBER($R40)),IF($R40>0,$AL40/$R40-1,""),"") | AN40: =IF(AND($Y40=1,ISNUMBER($R40)),IF($R40>0,$R40/(1+Paramètres!$B$5)-$AK40-($R40*Paramètres!$B$6+Paramètres!$B$7)-Paramètres!$B$8-Paramètres!$B$9-Paramètres!$B$10,""),"") | AO40: =IF(ISNUMBER($AN40),$AN40/($R40/(1+Paramètres!$B$5)),"") | AP40: =IF($A40="","",IF($Y40<>1,"INCOMPLET",IF(NOT(ISNUMBER($AM40)),"SANS RÉF. MARCHÉ",IF($AM40<=Paramètres!$B$12,"OK",IF(AND($AO40>=Paramètres!$B$15,$AN40>=Paramètres!$B$16),"À REVOIR","NON RENTABLE"))))) -> INCOMPLET | AQ40: =TRIM(IF(AND($Y40=1,ISNUMBER($N40)),IF($M40<$N40,"MOQ ",""),"")&IF(AND($Y40=1,ISNUMBER($O40)),IF($O40<$I40*$M40,"DISPO ",""),"")&IF($S40="O","FICTIF ","")&IF($Y40=1,IF(AND($K40="TTC",$W40<>"CH"),"TVA-ÉTRANGÈRE ",""),"")) | AR40: =IF($Y40=1,COUNTIFS($A$6:$A$205,$A40,$AK$6:$AK$205,"<"&$AK40,$Y$6:$Y$205,1)+1,"") | AS40: =IF(ISNUMBER($AR40),$A40&"|"&$AR40,"") | AT40: =IF($Y40=1,$AK40*$I40*$M40,"")
A41: REF-05 | B41: Collection Classeur 30ᵉ Anniversaire – FR | C41: Matoo et Miao | G41: 30ᵉ Anniversaire | H41: coffret | S41: N | T41: =IF($C41="","",IFERROR(INDEX(Fournisseurs!$C$5:$C$24,MATCH($C41,Fournisseurs!$A$5:$A$24,0)),"")) -> 0 | U41: =IF($C41="","",IFERROR(INDEX(Fournisseurs!$D$5:$D$24,MATCH($C41,Fournisseurs!$A$5:$A$24,0)),"")) -> 0 | V41: =IF($C41="","",IFERROR(INDEX(Fournisseurs!$G$5:$G$24,MATCH($C41,Fournisseurs!$A$5:$A$24,0)),"")) -> 0 | W41: =IF($C41="","",IFERROR(INDEX(Fournisseurs!$H$5:$H$24,MATCH($C41,Fournisseurs!$A$5:$A$24,0)),"")) -> 0 | X41: =IF($C41="","",IFERROR(INDEX(Fournisseurs!$B$5:$B$24,MATCH($C41,Fournisseurs!$A$5:$A$24,0)),"")) -> 0 | Y41: =IF($A41="","",IF(AND($A41<>"",$C41<>"",ISNUMBER($I41),ISNUMBER($J41),ISNUMBER($M41)),IF(AND($I41>=1,$J41>0,OR($K41="HT",$K41="TTC"),$M41>=1,IFERROR(INDEX(Fournisseurs!$T$5:$T$24,MATCH($C41,Fournisseurs!$A$5:$A$24,0)),0)=1),1,0),0)) -> 0 | Z41: =IF($Y41=1,$J41*(1-N($L41)),"") | AA41: =IF($Y41=1,IF($K41="TTC",$Z41/(1+$V41),$Z41),"") | AB41: =IF($Y41=1,IF($K41="TTC",$Z41-$AA41,$AA41*$V41),"") | AC41: =IF($Y41=1,$AA41*$U41*$M41,"") | AD41: =IF($Y41=1,$AC41/SUMIFS($AC$6:$AC$205,$C$6:$C$205,$C41,$Y$6:$Y$205,1),"") | AE41: =IF($Y41=1,(INDEX(Fournisseurs!$J$5:$J$24,MATCH($C41,Fournisseurs!$A$5:$A$24,0))+INDEX(Fournisseurs!$K$5:$K$24,MATCH($C41,Fournisseurs!$A$5:$A$24,0)))*$U41*$AD41/($I41*$M41),"") | AF41: =IF($Y41=1,INDEX(Fournisseurs!$L$5:$L$24,MATCH($C41,Fournisseurs!$A$5:$A$24,0))*$AD41/($I41*$M41),"") | AG41: =IF($Y41=1,$AA41*$U41/$I41,"") | AH41: =IF($Y41=1,$AB41*$U41/$I41,"") | AI41: =IF($Y41=1,IF(AND(Paramètres!$B$4="EFFECTIVE",$W41="CH",$AB41>0),1,0),"") | AJ41: =IF($Y41=1,IF($X41<>"CH",($AG41+$AE41+$AF41)*Paramètres!$B$14,0),"") | AK41: =IF($Y41=1,$AG41+IF($AI41=1,0,$AH41)+$AE41+$AF41+IF(Paramètres!$B$4="NOT_REGISTERED",$AJ41,0),"") | AL41: =IF($Y41=1,($AK41+Paramètres!$B$7+Paramètres!$B$8+Paramètres!$B$9+Paramètres!$B$10)/((1-Paramètres!$B$11)/(1+Paramètres!$B$5)-Paramètres!$B$6),"") | AM41: =IF(AND($Y41=1,ISNUMBER($R41)),IF($R41>0,$AL41/$R41-1,""),"") | AN41: =IF(AND($Y41=1,ISNUMBER($R41)),IF($R41>0,$R41/(1+Paramètres!$B$5)-$AK41-($R41*Paramètres!$B$6+Paramètres!$B$7)-Paramètres!$B$8-Paramètres!$B$9-Paramètres!$B$10,""),"") | AO41: =IF(ISNUMBER($AN41),$AN41/($R41/(1+Paramètres!$B$5)),"") | AP41: =IF($A41="","",IF($Y41<>1,"INCOMPLET",IF(NOT(ISNUMBER($AM41)),"SANS RÉF. MARCHÉ",IF($AM41<=Paramètres!$B$12,"OK",IF(AND($AO41>=Paramètres!$B$15,$AN41>=Paramètres!$B$16),"À REVOIR","NON RENTABLE"))))) -> INCOMPLET | AQ41: =TRIM(IF(AND($Y41=1,ISNUMBER($N41)),IF($M41<$N41,"MOQ ",""),"")&IF(AND($Y41=1,ISNUMBER($O41)),IF($O41<$I41*$M41,"DISPO ",""),"")&IF($S41="O","FICTIF ","")&IF($Y41=1,IF(AND($K41="TTC",$W41<>"CH"),"TVA-ÉTRANGÈRE ",""),"")) | AR41: =IF($Y41=1,COUNTIFS($A$6:$A$205,$A41,$AK$6:$AK$205,"<"&$AK41,$Y$6:$Y$205,1)+1,"") | AS41: =IF(ISNUMBER($AR41),$A41&"|"&$AR41,"") | AT41: =IF($Y41=1,$AK41*$I41*$M41,"")
A42: REF-10 | B42: Coffret Dresseur d'Élite (ETB) Méga-Évolution – Chaos Ascendant – FR | C42: Matoo et Miao | G42: Méga-Évolution – Chaos Ascendant | H42: etb | S42: N | T42: =IF($C42="","",IFERROR(INDEX(Fournisseurs!$C$5:$C$24,MATCH($C42,Fournisseurs!$A$5:$A$24,0)),"")) -> 0 | U42: =IF($C42="","",IFERROR(INDEX(Fournisseurs!$D$5:$D$24,MATCH($C42,Fournisseurs!$A$5:$A$24,0)),"")) -> 0 | V42: =IF($C42="","",IFERROR(INDEX(Fournisseurs!$G$5:$G$24,MATCH($C42,Fournisseurs!$A$5:$A$24,0)),"")) -> 0 | W42: =IF($C42="","",IFERROR(INDEX(Fournisseurs!$H$5:$H$24,MATCH($C42,Fournisseurs!$A$5:$A$24,0)),"")) -> 0 | X42: =IF($C42="","",IFERROR(INDEX(Fournisseurs!$B$5:$B$24,MATCH($C42,Fournisseurs!$A$5:$A$24,0)),"")) -> 0 | Y42: =IF($A42="","",IF(AND($A42<>"",$C42<>"",ISNUMBER($I42),ISNUMBER($J42),ISNUMBER($M42)),IF(AND($I42>=1,$J42>0,OR($K42="HT",$K42="TTC"),$M42>=1,IFERROR(INDEX(Fournisseurs!$T$5:$T$24,MATCH($C42,Fournisseurs!$A$5:$A$24,0)),0)=1),1,0),0)) -> 0 | Z42: =IF($Y42=1,$J42*(1-N($L42)),"") | AA42: =IF($Y42=1,IF($K42="TTC",$Z42/(1+$V42),$Z42),"") | AB42: =IF($Y42=1,IF($K42="TTC",$Z42-$AA42,$AA42*$V42),"") | AC42: =IF($Y42=1,$AA42*$U42*$M42,"") | AD42: =IF($Y42=1,$AC42/SUMIFS($AC$6:$AC$205,$C$6:$C$205,$C42,$Y$6:$Y$205,1),"") | AE42: =IF($Y42=1,(INDEX(Fournisseurs!$J$5:$J$24,MATCH($C42,Fournisseurs!$A$5:$A$24,0))+INDEX(Fournisseurs!$K$5:$K$24,MATCH($C42,Fournisseurs!$A$5:$A$24,0)))*$U42*$AD42/($I42*$M42),"") | AF42: =IF($Y42=1,INDEX(Fournisseurs!$L$5:$L$24,MATCH($C42,Fournisseurs!$A$5:$A$24,0))*$AD42/($I42*$M42),"") | AG42: =IF($Y42=1,$AA42*$U42/$I42,"") | AH42: =IF($Y42=1,$AB42*$U42/$I42,"") | AI42: =IF($Y42=1,IF(AND(Paramètres!$B$4="EFFECTIVE",$W42="CH",$AB42>0),1,0),"") | AJ42: =IF($Y42=1,IF($X42<>"CH",($AG42+$AE42+$AF42)*Paramètres!$B$14,0),"") | AK42: =IF($Y42=1,$AG42+IF($AI42=1,0,$AH42)+$AE42+$AF42+IF(Paramètres!$B$4="NOT_REGISTERED",$AJ42,0),"") | AL42: =IF($Y42=1,($AK42+Paramètres!$B$7+Paramètres!$B$8+Paramètres!$B$9+Paramètres!$B$10)/((1-Paramètres!$B$11)/(1+Paramètres!$B$5)-Paramètres!$B$6),"") | AM42: =IF(AND($Y42=1,ISNUMBER($R42)),IF($R42>0,$AL42/$R42-1,""),"") | AN42: =IF(AND($Y42=1,ISNUMBER($R42)),IF($R42>0,$R42/(1+Paramètres!$B$5)-$AK42-($R42*Paramètres!$B$6+Paramètres!$B$7)-Paramètres!$B$8-Paramètres!$B$9-Paramètres!$B$10,""),"") | AO42: =IF(ISNUMBER($AN42),$AN42/($R42/(1+Paramètres!$B$5)),"") | AP42: =IF($A42="","",IF($Y42<>1,"INCOMPLET",IF(NOT(ISNUMBER($AM42)),"SANS RÉF. MARCHÉ",IF($AM42<=Paramètres!$B$12,"OK",IF(AND($AO42>=Paramètres!$B$15,$AN42>=Paramètres!$B$16),"À REVOIR","NON RENTABLE"))))) -> INCOMPLET | AQ42: =TRIM(IF(AND($Y42=1,ISNUMBER($N42)),IF($M42<$N42,"MOQ ",""),"")&IF(AND($Y42=1,ISNUMBER($O42)),IF($O42<$I42*$M42,"DISPO ",""),"")&IF($S42="O","FICTIF ","")&IF($Y42=1,IF(AND($K42="TTC",$W42<>"CH"),"TVA-ÉTRANGÈRE ",""),"")) | AR42: =IF($Y42=1,COUNTIFS($A$6:$A$205,$A42,$AK$6:$AK$205,"<"&$AK42,$Y$6:$Y$205,1)+1,"") | AS42: =IF(ISNUMBER($AR42),$A42&"|"&$AR42,"") | AT42: =IF($Y42=1,$AK42*$I42*$M42,"")
A43: REF-12 | B43: Coffret Dresseur d'Élite (ETB) Méga-Évolution – Héros Transcendants – FR | C43: Matoo et Miao | G43: Méga-Évolution – Héros Transcendants | H43: etb | S43: N | T43: =IF($C43="","",IFERROR(INDEX(Fournisseurs!$C$5:$C$24,MATCH($C43,Fournisseurs!$A$5:$A$24,0)),"")) -> 0 | U43: =IF($C43="","",IFERROR(INDEX(Fournisseurs!$D$5:$D$24,MATCH($C43,Fournisseurs!$A$5:$A$24,0)),"")) -> 0 | V43: =IF($C43="","",IFERROR(INDEX(Fournisseurs!$G$5:$G$24,MATCH($C43,Fournisseurs!$A$5:$A$24,0)),"")) -> 0 | W43: =IF($C43="","",IFERROR(INDEX(Fournisseurs!$H$5:$H$24,MATCH($C43,Fournisseurs!$A$5:$A$24,0)),"")) -> 0 | X43: =IF($C43="","",IFERROR(INDEX(Fournisseurs!$B$5:$B$24,MATCH($C43,Fournisseurs!$A$5:$A$24,0)),"")) -> 0 | Y43: =IF($A43="","",IF(AND($A43<>"",$C43<>"",ISNUMBER($I43),ISNUMBER($J43),ISNUMBER($M43)),IF(AND($I43>=1,$J43>0,OR($K43="HT",$K43="TTC"),$M43>=1,IFERROR(INDEX(Fournisseurs!$T$5:$T$24,MATCH($C43,Fournisseurs!$A$5:$A$24,0)),0)=1),1,0),0)) -> 0 | Z43: =IF($Y43=1,$J43*(1-N($L43)),"") | AA43: =IF($Y43=1,IF($K43="TTC",$Z43/(1+$V43),$Z43),"") | AB43: =IF($Y43=1,IF($K43="TTC",$Z43-$AA43,$AA43*$V43),"") | AC43: =IF($Y43=1,$AA43*$U43*$M43,"") | AD43: =IF($Y43=1,$AC43/SUMIFS($AC$6:$AC$205,$C$6:$C$205,$C43,$Y$6:$Y$205,1),"") | AE43: =IF($Y43=1,(INDEX(Fournisseurs!$J$5:$J$24,MATCH($C43,Fournisseurs!$A$5:$A$24,0))+INDEX(Fournisseurs!$K$5:$K$24,MATCH($C43,Fournisseurs!$A$5:$A$24,0)))*$U43*$AD43/($I43*$M43),"") | AF43: =IF($Y43=1,INDEX(Fournisseurs!$L$5:$L$24,MATCH($C43,Fournisseurs!$A$5:$A$24,0))*$AD43/($I43*$M43),"") | AG43: =IF($Y43=1,$AA43*$U43/$I43,"") | AH43: =IF($Y43=1,$AB43*$U43/$I43,"") | AI43: =IF($Y43=1,IF(AND(Paramètres!$B$4="EFFECTIVE",$W43="CH",$AB43>0),1,0),"") | AJ43: =IF($Y43=1,IF($X43<>"CH",($AG43+$AE43+$AF43)*Paramètres!$B$14,0),"") | AK43: =IF($Y43=1,$AG43+IF($AI43=1,0,$AH43)+$AE43+$AF43+IF(Paramètres!$B$4="NOT_REGISTERED",$AJ43,0),"") | AL43: =IF($Y43=1,($AK43+Paramètres!$B$7+Paramètres!$B$8+Paramètres!$B$9+Paramètres!$B$10)/((1-Paramètres!$B$11)/(1+Paramètres!$B$5)-Paramètres!$B$6),"") | AM43: =IF(AND($Y43=1,ISNUMBER($R43)),IF($R43>0,$AL43/$R43-1,""),"") | AN43: =IF(AND($Y43=1,ISNUMBER($R43)),IF($R43>0,$R43/(1+Paramètres!$B$5)-$AK43-($R43*Paramètres!$B$6+Paramètres!$B$7)-Paramètres!$B$8-Paramètres!$B$9-Paramètres!$B$10,""),"") | AO43: =IF(ISNUMBER($AN43),$AN43/($R43/(1+Paramètres!$B$5)),"") | AP43: =IF($A43="","",IF($Y43<>1,"INCOMPLET",IF(NOT(ISNUMBER($AM43)),"SANS RÉF. MARCHÉ",IF($AM43<=Paramètres!$B$12,"OK",IF(AND($AO43>=Paramètres!$B$15,$AN43>=Paramètres!$B$16),"À REVOIR","NON RENTABLE"))))) -> INCOMPLET | AQ43: =TRIM(IF(AND($Y43=1,ISNUMBER($N43)),IF($M43<$N43,"MOQ ",""),"")&IF(AND($Y43=1,ISNUMBER($O43)),IF($O43<$I43*$M43,"DISPO ",""),"")&IF($S43="O","FICTIF ","")&IF($Y43=1,IF(AND($K43="TTC",$W43<>"CH"),"TVA-ÉTRANGÈRE ",""),"")) | AR43: =IF($Y43=1,COUNTIFS($A$6:$A$205,$A43,$AK$6:$AK$205,"<"&$AK43,$Y$6:$Y$205,1)+1,"") | AS43: =IF(ISNUMBER($AR43),$A43&"|"&$AR43,"") | AT43: =IF($Y43=1,$AK43*$I43*$M43,"")
A44: REF-13 | B44: Display 36 boosters Méga-Évolution – Règne Delta (ME06) – FR | C44: Matoo et Miao | G44: Méga-Évolution – Règne Delta | H44: display | S44: N | T44: =IF($C44="","",IFERROR(INDEX(Fournisseurs!$C$5:$C$24,MATCH($C44,Fournisseurs!$A$5:$A$24,0)),"")) -> 0 | U44: =IF($C44="","",IFERROR(INDEX(Fournisseurs!$D$5:$D$24,MATCH($C44,Fournisseurs!$A$5:$A$24,0)),"")) -> 0 | V44: =IF($C44="","",IFERROR(INDEX(Fournisseurs!$G$5:$G$24,MATCH($C44,Fournisseurs!$A$5:$A$24,0)),"")) -> 0 | W44: =IF($C44="","",IFERROR(INDEX(Fournisseurs!$H$5:$H$24,MATCH($C44,Fournisseurs!$A$5:$A$24,0)),"")) -> 0 | X44: =IF($C44="","",IFERROR(INDEX(Fournisseurs!$B$5:$B$24,MATCH($C44,Fournisseurs!$A$5:$A$24,0)),"")) -> 0 | Y44: =IF($A44="","",IF(AND($A44<>"",$C44<>"",ISNUMBER($I44),ISNUMBER($J44),ISNUMBER($M44)),IF(AND($I44>=1,$J44>0,OR($K44="HT",$K44="TTC"),$M44>=1,IFERROR(INDEX(Fournisseurs!$T$5:$T$24,MATCH($C44,Fournisseurs!$A$5:$A$24,0)),0)=1),1,0),0)) -> 0 | Z44: =IF($Y44=1,$J44*(1-N($L44)),"") | AA44: =IF($Y44=1,IF($K44="TTC",$Z44/(1+$V44),$Z44),"") | AB44: =IF($Y44=1,IF($K44="TTC",$Z44-$AA44,$AA44*$V44),"") | AC44: =IF($Y44=1,$AA44*$U44*$M44,"") | AD44: =IF($Y44=1,$AC44/SUMIFS($AC$6:$AC$205,$C$6:$C$205,$C44,$Y$6:$Y$205,1),"") | AE44: =IF($Y44=1,(INDEX(Fournisseurs!$J$5:$J$24,MATCH($C44,Fournisseurs!$A$5:$A$24,0))+INDEX(Fournisseurs!$K$5:$K$24,MATCH($C44,Fournisseurs!$A$5:$A$24,0)))*$U44*$AD44/($I44*$M44),"") | AF44: =IF($Y44=1,INDEX(Fournisseurs!$L$5:$L$24,MATCH($C44,Fournisseurs!$A$5:$A$24,0))*$AD44/($I44*$M44),"") | AG44: =IF($Y44=1,$AA44*$U44/$I44,"") | AH44: =IF($Y44=1,$AB44*$U44/$I44,"") | AI44: =IF($Y44=1,IF(AND(Paramètres!$B$4="EFFECTIVE",$W44="CH",$AB44>0),1,0),"") | AJ44: =IF($Y44=1,IF($X44<>"CH",($AG44+$AE44+$AF44)*Paramètres!$B$14,0),"") | AK44: =IF($Y44=1,$AG44+IF($AI44=1,0,$AH44)+$AE44+$AF44+IF(Paramètres!$B$4="NOT_REGISTERED",$AJ44,0),"") | AL44: =IF($Y44=1,($AK44+Paramètres!$B$7+Paramètres!$B$8+Paramètres!$B$9+Paramètres!$B$10)/((1-Paramètres!$B$11)/(1+Paramètres!$B$5)-Paramètres!$B$6),"") | AM44: =IF(AND($Y44=1,ISNUMBER($R44)),IF($R44>0,$AL44/$R44-1,""),"") | AN44: =IF(AND($Y44=1,ISNUMBER($R44)),IF($R44>0,$R44/(1+Paramètres!$B$5)-$AK44-($R44*Paramètres!$B$6+Paramètres!$B$7)-Paramètres!$B$8-Paramètres!$B$9-Paramètres!$B$10,""),"") | AO44: =IF(ISNUMBER($AN44),$AN44/($R44/(1+Paramètres!$B$5)),"") | AP44: =IF($A44="","",IF($Y44<>1,"INCOMPLET",IF(NOT(ISNUMBER($AM44)),"SANS RÉF. MARCHÉ",IF($AM44<=Paramètres!$B$12,"OK",IF(AND($AO44>=Paramètres!$B$15,$AN44>=Paramètres!$B$16),"À REVOIR","NON RENTABLE"))))) -> INCOMPLET | AQ44: =TRIM(IF(AND($Y44=1,ISNUMBER($N44)),IF($M44<$N44,"MOQ ",""),"")&IF(AND($Y44=1,ISNUMBER($O44)),IF($O44<$I44*$M44,"DISPO ",""),"")&IF($S44="O","FICTIF ","")&IF($Y44=1,IF(AND($K44="TTC",$W44<>"CH"),"TVA-ÉTRANGÈRE ",""),"")) | AR44: =IF($Y44=1,COUNTIFS($A$6:$A$205,$A44,$AK$6:$AK$205,"<"&$AK44,$Y$6:$Y$205,1)+1,"") | AS44: =IF(ISNUMBER($AR44),$A44&"|"&$AR44,"") | AT44: =IF($Y44=1,$AK44*$I44*$M44,"")
A45: REF-14 | B45: Coffret Dresseur d'Élite (ETB) Méga-Évolution – Règne Delta – FR | C45: Matoo et Miao | G45: Méga-Évolution – Règne Delta | H45: etb | S45: N | T45: =IF($C45="","",IFERROR(INDEX(Fournisseurs!$C$5:$C$24,MATCH($C45,Fournisseurs!$A$5:$A$24,0)),"")) -> 0 | U45: =IF($C45="","",IFERROR(INDEX(Fournisseurs!$D$5:$D$24,MATCH($C45,Fournisseurs!$A$5:$A$24,0)),"")) -> 0 | V45: =IF($C45="","",IFERROR(INDEX(Fournisseurs!$G$5:$G$24,MATCH($C45,Fournisseurs!$A$5:$A$24,0)),"")) -> 0 | W45: =IF($C45="","",IFERROR(INDEX(Fournisseurs!$H$5:$H$24,MATCH($C45,Fournisseurs!$A$5:$A$24,0)),"")) -> 0 | X45: =IF($C45="","",IFERROR(INDEX(Fournisseurs!$B$5:$B$24,MATCH($C45,Fournisseurs!$A$5:$A$24,0)),"")) -> 0 | Y45: =IF($A45="","",IF(AND($A45<>"",$C45<>"",ISNUMBER($I45),ISNUMBER($J45),ISNUMBER($M45)),IF(AND($I45>=1,$J45>0,OR($K45="HT",$K45="TTC"),$M45>=1,IFERROR(INDEX(Fournisseurs!$T$5:$T$24,MATCH($C45,Fournisseurs!$A$5:$A$24,0)),0)=1),1,0),0)) -> 0 | Z45: =IF($Y45=1,$J45*(1-N($L45)),"") | AA45: =IF($Y45=1,IF($K45="TTC",$Z45/(1+$V45),$Z45),"") | AB45: =IF($Y45=1,IF($K45="TTC",$Z45-$AA45,$AA45*$V45),"") | AC45: =IF($Y45=1,$AA45*$U45*$M45,"") | AD45: =IF($Y45=1,$AC45/SUMIFS($AC$6:$AC$205,$C$6:$C$205,$C45,$Y$6:$Y$205,1),"") | AE45: =IF($Y45=1,(INDEX(Fournisseurs!$J$5:$J$24,MATCH($C45,Fournisseurs!$A$5:$A$24,0))+INDEX(Fournisseurs!$K$5:$K$24,MATCH($C45,Fournisseurs!$A$5:$A$24,0)))*$U45*$AD45/($I45*$M45),"") | AF45: =IF($Y45=1,INDEX(Fournisseurs!$L$5:$L$24,MATCH($C45,Fournisseurs!$A$5:$A$24,0))*$AD45/($I45*$M45),"") | AG45: =IF($Y45=1,$AA45*$U45/$I45,"") | AH45: =IF($Y45=1,$AB45*$U45/$I45,"") | AI45: =IF($Y45=1,IF(AND(Paramètres!$B$4="EFFECTIVE",$W45="CH",$AB45>0),1,0),"") | AJ45: =IF($Y45=1,IF($X45<>"CH",($AG45+$AE45+$AF45)*Paramètres!$B$14,0),"") | AK45: =IF($Y45=1,$AG45+IF($AI45=1,0,$AH45)+$AE45+$AF45+IF(Paramètres!$B$4="NOT_REGISTERED",$AJ45,0),"") | AL45: =IF($Y45=1,($AK45+Paramètres!$B$7+Paramètres!$B$8+Paramètres!$B$9+Paramètres!$B$10)/((1-Paramètres!$B$11)/(1+Paramètres!$B$5)-Paramètres!$B$6),"") | AM45: =IF(AND($Y45=1,ISNUMBER($R45)),IF($R45>0,$AL45/$R45-1,""),"") | AN45: =IF(AND($Y45=1,ISNUMBER($R45)),IF($R45>0,$R45/(1+Paramètres!$B$5)-$AK45-($R45*Paramètres!$B$6+Paramètres!$B$7)-Paramètres!$B$8-Paramètres!$B$9-Paramètres!$B$10,""),"") | AO45: =IF(ISNUMBER($AN45),$AN45/($R45/(1+Paramètres!$B$5)),"") | AP45: =IF($A45="","",IF($Y45<>1,"INCOMPLET",IF(NOT(ISNUMBER($AM45)),"SANS RÉF. MARCHÉ",IF($AM45<=Paramètres!$B$12,"OK",IF(AND($AO45>=Paramètres!$B$15,$AN45>=Paramètres!$B$16),"À REVOIR","NON RENTABLE"))))) -> INCOMPLET | AQ45: =TRIM(IF(AND($Y45=1,ISNUMBER($N45)),IF($M45<$N45,"MOQ ",""),"")&IF(AND($Y45=1,ISNUMBER($O45)),IF($O45<$I45*$M45,"DISPO ",""),"")&IF($S45="O","FICTIF ","")&IF($Y45=1,IF(AND($K45="TTC",$W45<>"CH"),"TVA-ÉTRANGÈRE ",""),"")) | AR45: =IF($Y45=1,COUNTIFS($A$6:$A$205,$A45,$AK$6:$AK$205,"<"&$AK45,$Y$6:$Y$205,1)+1,"") | AS45: =IF(ISNUMBER($AR45),$A45&"|"&$AR45,"") | AT45: =IF($Y45=1,$AK45*$I45*$M45,"")
A46: REF-15 | B46: Tripack Méga-Évolution – Règne Delta – FR | C46: Matoo et Miao | G46: Méga-Évolution – Règne Delta | H46: tripack | S46: N | T46: =IF($C46="","",IFERROR(INDEX(Fournisseurs!$C$5:$C$24,MATCH($C46,Fournisseurs!$A$5:$A$24,0)),"")) -> 0 | U46: =IF($C46="","",IFERROR(INDEX(Fournisseurs!$D$5:$D$24,MATCH($C46,Fournisseurs!$A$5:$A$24,0)),"")) -> 0 | V46: =IF($C46="","",IFERROR(INDEX(Fournisseurs!$G$5:$G$24,MATCH($C46,Fournisseurs!$A$5:$A$24,0)),"")) -> 0 | W46: =IF($C46="","",IFERROR(INDEX(Fournisseurs!$H$5:$H$24,MATCH($C46,Fournisseurs!$A$5:$A$24,0)),"")) -> 0 | X46: =IF($C46="","",IFERROR(INDEX(Fournisseurs!$B$5:$B$24,MATCH($C46,Fournisseurs!$A$5:$A$24,0)),"")) -> 0 | Y46: =IF($A46="","",IF(AND($A46<>"",$C46<>"",ISNUMBER($I46),ISNUMBER($J46),ISNUMBER($M46)),IF(AND($I46>=1,$J46>0,OR($K46="HT",$K46="TTC"),$M46>=1,IFERROR(INDEX(Fournisseurs!$T$5:$T$24,MATCH($C46,Fournisseurs!$A$5:$A$24,0)),0)=1),1,0),0)) -> 0 | Z46: =IF($Y46=1,$J46*(1-N($L46)),"") | AA46: =IF($Y46=1,IF($K46="TTC",$Z46/(1+$V46),$Z46),"") | AB46: =IF($Y46=1,IF($K46="TTC",$Z46-$AA46,$AA46*$V46),"") | AC46: =IF($Y46=1,$AA46*$U46*$M46,"") | AD46: =IF($Y46=1,$AC46/SUMIFS($AC$6:$AC$205,$C$6:$C$205,$C46,$Y$6:$Y$205,1),"") | AE46: =IF($Y46=1,(INDEX(Fournisseurs!$J$5:$J$24,MATCH($C46,Fournisseurs!$A$5:$A$24,0))+INDEX(Fournisseurs!$K$5:$K$24,MATCH($C46,Fournisseurs!$A$5:$A$24,0)))*$U46*$AD46/($I46*$M46),"") | AF46: =IF($Y46=1,INDEX(Fournisseurs!$L$5:$L$24,MATCH($C46,Fournisseurs!$A$5:$A$24,0))*$AD46/($I46*$M46),"") | AG46: =IF($Y46=1,$AA46*$U46/$I46,"") | AH46: =IF($Y46=1,$AB46*$U46/$I46,"") | AI46: =IF($Y46=1,IF(AND(Paramètres!$B$4="EFFECTIVE",$W46="CH",$AB46>0),1,0),"") | AJ46: =IF($Y46=1,IF($X46<>"CH",($AG46+$AE46+$AF46)*Paramètres!$B$14,0),"") | AK46: =IF($Y46=1,$AG46+IF($AI46=1,0,$AH46)+$AE46+$AF46+IF(Paramètres!$B$4="NOT_REGISTERED",$AJ46,0),"") | AL46: =IF($Y46=1,($AK46+Paramètres!$B$7+Paramètres!$B$8+Paramètres!$B$9+Paramètres!$B$10)/((1-Paramètres!$B$11)/(1+Paramètres!$B$5)-Paramètres!$B$6),"") | AM46: =IF(AND($Y46=1,ISNUMBER($R46)),IF($R46>0,$AL46/$R46-1,""),"") | AN46: =IF(AND($Y46=1,ISNUMBER($R46)),IF($R46>0,$R46/(1+Paramètres!$B$5)-$AK46-($R46*Paramètres!$B$6+Paramètres!$B$7)-Paramètres!$B$8-Paramètres!$B$9-Paramètres!$B$10,""),"") | AO46: =IF(ISNUMBER($AN46),$AN46/($R46/(1+Paramètres!$B$5)),"") | AP46: =IF($A46="","",IF($Y46<>1,"INCOMPLET",IF(NOT(ISNUMBER($AM46)),"SANS RÉF. MARCHÉ",IF($AM46<=Paramètres!$B$12,"OK",IF(AND($AO46>=Paramètres!$B$15,$AN46>=Paramètres!$B$16),"À REVOIR","NON RENTABLE"))))) -> INCOMPLET | AQ46: =TRIM(IF(AND($Y46=1,ISNUMBER($N46)),IF($M46<$N46,"MOQ ",""),"")&IF(AND($Y46=1,ISNUMBER($O46)),IF($O46<$I46*$M46,"DISPO ",""),"")&IF($S46="O","FICTIF ","")&IF($Y46=1,IF(AND($K46="TTC",$W46<>"CH"),"TVA-ÉTRANGÈRE ",""),"")) | AR46: =IF($Y46=1,COUNTIFS($A$6:$A$205,$A46,$AK$6:$AK$205,"<"&$AK46,$Y$6:$Y$205,1)+1,"") | AS46: =IF(ISNUMBER($AR46),$A46&"|"&$AR46,"") | AT46: =IF($Y46=1,$AK46*$I46*$M46,"")
A47: REF-18 | B47: Boîte de rangement de deck (deck box) | C47: Matoo et Miao | H47: accessoire | S47: N | T47: =IF($C47="","",IFERROR(INDEX(Fournisseurs!$C$5:$C$24,MATCH($C47,Fournisseurs!$A$5:$A$24,0)),"")) -> 0 | U47: =IF($C47="","",IFERROR(INDEX(Fournisseurs!$D$5:$D$24,MATCH($C47,Fournisseurs!$A$5:$A$24,0)),"")) -> 0 | V47: =IF($C47="","",IFERROR(INDEX(Fournisseurs!$G$5:$G$24,MATCH($C47,Fournisseurs!$A$5:$A$24,0)),"")) -> 0 | W47: =IF($C47="","",IFERROR(INDEX(Fournisseurs!$H$5:$H$24,MATCH($C47,Fournisseurs!$A$5:$A$24,0)),"")) -> 0 | X47: =IF($C47="","",IFERROR(INDEX(Fournisseurs!$B$5:$B$24,MATCH($C47,Fournisseurs!$A$5:$A$24,0)),"")) -> 0 | Y47: =IF($A47="","",IF(AND($A47<>"",$C47<>"",ISNUMBER($I47),ISNUMBER($J47),ISNUMBER($M47)),IF(AND($I47>=1,$J47>0,OR($K47="HT",$K47="TTC"),$M47>=1,IFERROR(INDEX(Fournisseurs!$T$5:$T$24,MATCH($C47,Fournisseurs!$A$5:$A$24,0)),0)=1),1,0),0)) -> 0 | Z47: =IF($Y47=1,$J47*(1-N($L47)),"") | AA47: =IF($Y47=1,IF($K47="TTC",$Z47/(1+$V47),$Z47),"") | AB47: =IF($Y47=1,IF($K47="TTC",$Z47-$AA47,$AA47*$V47),"") | AC47: =IF($Y47=1,$AA47*$U47*$M47,"") | AD47: =IF($Y47=1,$AC47/SUMIFS($AC$6:$AC$205,$C$6:$C$205,$C47,$Y$6:$Y$205,1),"") | AE47: =IF($Y47=1,(INDEX(Fournisseurs!$J$5:$J$24,MATCH($C47,Fournisseurs!$A$5:$A$24,0))+INDEX(Fournisseurs!$K$5:$K$24,MATCH($C47,Fournisseurs!$A$5:$A$24,0)))*$U47*$AD47/($I47*$M47),"") | AF47: =IF($Y47=1,INDEX(Fournisseurs!$L$5:$L$24,MATCH($C47,Fournisseurs!$A$5:$A$24,0))*$AD47/($I47*$M47),"") | AG47: =IF($Y47=1,$AA47*$U47/$I47,"") | AH47: =IF($Y47=1,$AB47*$U47/$I47,"") | AI47: =IF($Y47=1,IF(AND(Paramètres!$B$4="EFFECTIVE",$W47="CH",$AB47>0),1,0),"") | AJ47: =IF($Y47=1,IF($X47<>"CH",($AG47+$AE47+$AF47)*Paramètres!$B$14,0),"") | AK47: =IF($Y47=1,$AG47+IF($AI47=1,0,$AH47)+$AE47+$AF47+IF(Paramètres!$B$4="NOT_REGISTERED",$AJ47,0),"") | AL47: =IF($Y47=1,($AK47+Paramètres!$B$7+Paramètres!$B$8+Paramètres!$B$9+Paramètres!$B$10)/((1-Paramètres!$B$11)/(1+Paramètres!$B$5)-Paramètres!$B$6),"") | AM47: =IF(AND($Y47=1,ISNUMBER($R47)),IF($R47>0,$AL47/$R47-1,""),"") | AN47: =IF(AND($Y47=1,ISNUMBER($R47)),IF($R47>0,$R47/(1+Paramètres!$B$5)-$AK47-($R47*Paramètres!$B$6+Paramètres!$B$7)-Paramètres!$B$8-Paramètres!$B$9-Paramètres!$B$10,""),"") | AO47: =IF(ISNUMBER($AN47),$AN47/($R47/(1+Paramètres!$B$5)),"") | AP47: =IF($A47="","",IF($Y47<>1,"INCOMPLET",IF(NOT(ISNUMBER($AM47)),"SANS RÉF. MARCHÉ",IF($AM47<=Paramètres!$B$12,"OK",IF(AND($AO47>=Paramètres!$B$15,$AN47>=Paramètres!$B$16),"À REVOIR","NON RENTABLE"))))) -> INCOMPLET | AQ47: =TRIM(IF(AND($Y47=1,ISNUMBER($N47)),IF($M47<$N47,"MOQ ",""),"")&IF(AND($Y47=1,ISNUMBER($O47)),IF($O47<$I47*$M47,"DISPO ",""),"")&IF($S47="O","FICTIF ","")&IF($Y47=1,IF(AND($K47="TTC",$W47<>"CH"),"TVA-ÉTRANGÈRE ",""),"")) | AR47: =IF($Y47=1,COUNTIFS($A$6:$A$205,$A47,$AK$6:$AK$205,"<"&$AK47,$Y$6:$Y$205,1)+1,"") | AS47: =IF(ISNUMBER($AR47),$A47&"|"&$AR47,"") | AT47: =IF($Y47=1,$AK47*$I47*$M47,"")
A48: REF-06 | B48: Display 36 boosters Méga-Évolution – Nuit Noire (ME05) – FR | C48: TCG Distribution | G48: Méga-Évolution – Nuit Noire | H48: display | S48: N | T48: =IF($C48="","",IFERROR(INDEX(Fournisseurs!$C$5:$C$24,MATCH($C48,Fournisseurs!$A$5:$A$24,0)),"")) -> 0 | U48: =IF($C48="","",IFERROR(INDEX(Fournisseurs!$D$5:$D$24,MATCH($C48,Fournisseurs!$A$5:$A$24,0)),"")) -> 0 | V48: =IF($C48="","",IFERROR(INDEX(Fournisseurs!$G$5:$G$24,MATCH($C48,Fournisseurs!$A$5:$A$24,0)),"")) -> 0 | W48: =IF($C48="","",IFERROR(INDEX(Fournisseurs!$H$5:$H$24,MATCH($C48,Fournisseurs!$A$5:$A$24,0)),"")) -> 0 | X48: =IF($C48="","",IFERROR(INDEX(Fournisseurs!$B$5:$B$24,MATCH($C48,Fournisseurs!$A$5:$A$24,0)),"")) -> 0 | Y48: =IF($A48="","",IF(AND($A48<>"",$C48<>"",ISNUMBER($I48),ISNUMBER($J48),ISNUMBER($M48)),IF(AND($I48>=1,$J48>0,OR($K48="HT",$K48="TTC"),$M48>=1,IFERROR(INDEX(Fournisseurs!$T$5:$T$24,MATCH($C48,Fournisseurs!$A$5:$A$24,0)),0)=1),1,0),0)) -> 0 | Z48: =IF($Y48=1,$J48*(1-N($L48)),"") | AA48: =IF($Y48=1,IF($K48="TTC",$Z48/(1+$V48),$Z48),"") | AB48: =IF($Y48=1,IF($K48="TTC",$Z48-$AA48,$AA48*$V48),"") | AC48: =IF($Y48=1,$AA48*$U48*$M48,"") | AD48: =IF($Y48=1,$AC48/SUMIFS($AC$6:$AC$205,$C$6:$C$205,$C48,$Y$6:$Y$205,1),"") | AE48: =IF($Y48=1,(INDEX(Fournisseurs!$J$5:$J$24,MATCH($C48,Fournisseurs!$A$5:$A$24,0))+INDEX(Fournisseurs!$K$5:$K$24,MATCH($C48,Fournisseurs!$A$5:$A$24,0)))*$U48*$AD48/($I48*$M48),"") | AF48: =IF($Y48=1,INDEX(Fournisseurs!$L$5:$L$24,MATCH($C48,Fournisseurs!$A$5:$A$24,0))*$AD48/($I48*$M48),"") | AG48: =IF($Y48=1,$AA48*$U48/$I48,"") | AH48: =IF($Y48=1,$AB48*$U48/$I48,"") | AI48: =IF($Y48=1,IF(AND(Paramètres!$B$4="EFFECTIVE",$W48="CH",$AB48>0),1,0),"") | AJ48: =IF($Y48=1,IF($X48<>"CH",($AG48+$AE48+$AF48)*Paramètres!$B$14,0),"") | AK48: =IF($Y48=1,$AG48+IF($AI48=1,0,$AH48)+$AE48+$AF48+IF(Paramètres!$B$4="NOT_REGISTERED",$AJ48,0),"") | AL48: =IF($Y48=1,($AK48+Paramètres!$B$7+Paramètres!$B$8+Paramètres!$B$9+Paramètres!$B$10)/((1-Paramètres!$B$11)/(1+Paramètres!$B$5)-Paramètres!$B$6),"") | AM48: =IF(AND($Y48=1,ISNUMBER($R48)),IF($R48>0,$AL48/$R48-1,""),"") | AN48: =IF(AND($Y48=1,ISNUMBER($R48)),IF($R48>0,$R48/(1+Paramètres!$B$5)-$AK48-($R48*Paramètres!$B$6+Paramètres!$B$7)-Paramètres!$B$8-Paramètres!$B$9-Paramètres!$B$10,""),"") | AO48: =IF(ISNUMBER($AN48),$AN48/($R48/(1+Paramètres!$B$5)),"") | AP48: =IF($A48="","",IF($Y48<>1,"INCOMPLET",IF(NOT(ISNUMBER($AM48)),"SANS RÉF. MARCHÉ",IF($AM48<=Paramètres!$B$12,"OK",IF(AND($AO48>=Paramètres!$B$15,$AN48>=Paramètres!$B$16),"À REVOIR","NON RENTABLE"))))) -> INCOMPLET | AQ48: =TRIM(IF(AND($Y48=1,ISNUMBER($N48)),IF($M48<$N48,"MOQ ",""),"")&IF(AND($Y48=1,ISNUMBER($O48)),IF($O48<$I48*$M48,"DISPO ",""),"")&IF($S48="O","FICTIF ","")&IF($Y48=1,IF(AND($K48="TTC",$W48<>"CH"),"TVA-ÉTRANGÈRE ",""),"")) | AR48: =IF($Y48=1,COUNTIFS($A$6:$A$205,$A48,$AK$6:$AK$205,"<"&$AK48,$Y$6:$Y$205,1)+1,"") | AS48: =IF(ISNUMBER($AR48),$A48&"|"&$AR48,"") | AT48: =IF($Y48=1,$AK48*$I48*$M48,"")
A49: REF-09 | B49: Display 36 boosters Méga-Évolution – Chaos Ascendant – FR | C49: TCG Distribution | G49: Méga-Évolution – Chaos Ascendant | H49: display | S49: N | T49: =IF($C49="","",IFERROR(INDEX(Fournisseurs!$C$5:$C$24,MATCH($C49,Fournisseurs!$A$5:$A$24,0)),"")) -> 0 | U49: =IF($C49="","",IFERROR(INDEX(Fournisseurs!$D$5:$D$24,MATCH($C49,Fournisseurs!$A$5:$A$24,0)),"")) -> 0 | V49: =IF($C49="","",IFERROR(INDEX(Fournisseurs!$G$5:$G$24,MATCH($C49,Fournisseurs!$A$5:$A$24,0)),"")) -> 0 | W49: =IF($C49="","",IFERROR(INDEX(Fournisseurs!$H$5:$H$24,MATCH($C49,Fournisseurs!$A$5:$A$24,0)),"")) -> 0 | X49: =IF($C49="","",IFERROR(INDEX(Fournisseurs!$B$5:$B$24,MATCH($C49,Fournisseurs!$A$5:$A$24,0)),"")) -> 0 | Y49: =IF($A49="","",IF(AND($A49<>"",$C49<>"",ISNUMBER($I49),ISNUMBER($J49),ISNUMBER($M49)),IF(AND($I49>=1,$J49>0,OR($K49="HT",$K49="TTC"),$M49>=1,IFERROR(INDEX(Fournisseurs!$T$5:$T$24,MATCH($C49,Fournisseurs!$A$5:$A$24,0)),0)=1),1,0),0)) -> 0 | Z49: =IF($Y49=1,$J49*(1-N($L49)),"") | AA49: =IF($Y49=1,IF($K49="TTC",$Z49/(1+$V49),$Z49),"") | AB49: =IF($Y49=1,IF($K49="TTC",$Z49-$AA49,$AA49*$V49),"") | AC49: =IF($Y49=1,$AA49*$U49*$M49,"") | AD49: =IF($Y49=1,$AC49/SUMIFS($AC$6:$AC$205,$C$6:$C$205,$C49,$Y$6:$Y$205,1),"") | AE49: =IF($Y49=1,(INDEX(Fournisseurs!$J$5:$J$24,MATCH($C49,Fournisseurs!$A$5:$A$24,0))+INDEX(Fournisseurs!$K$5:$K$24,MATCH($C49,Fournisseurs!$A$5:$A$24,0)))*$U49*$AD49/($I49*$M49),"") | AF49: =IF($Y49=1,INDEX(Fournisseurs!$L$5:$L$24,MATCH($C49,Fournisseurs!$A$5:$A$24,0))*$AD49/($I49*$M49),"") | AG49: =IF($Y49=1,$AA49*$U49/$I49,"") | AH49: =IF($Y49=1,$AB49*$U49/$I49,"") | AI49: =IF($Y49=1,IF(AND(Paramètres!$B$4="EFFECTIVE",$W49="CH",$AB49>0),1,0),"") | AJ49: =IF($Y49=1,IF($X49<>"CH",($AG49+$AE49+$AF49)*Paramètres!$B$14,0),"") | AK49: =IF($Y49=1,$AG49+IF($AI49=1,0,$AH49)+$AE49+$AF49+IF(Paramètres!$B$4="NOT_REGISTERED",$AJ49,0),"") | AL49: =IF($Y49=1,($AK49+Paramètres!$B$7+Paramètres!$B$8+Paramètres!$B$9+Paramètres!$B$10)/((1-Paramètres!$B$11)/(1+Paramètres!$B$5)-Paramètres!$B$6),"") | AM49: =IF(AND($Y49=1,ISNUMBER($R49)),IF($R49>0,$AL49/$R49-1,""),"") | AN49: =IF(AND($Y49=1,ISNUMBER($R49)),IF($R49>0,$R49/(1+Paramètres!$B$5)-$AK49-($R49*Paramètres!$B$6+Paramètres!$B$7)-Paramètres!$B$8-Paramètres!$B$9-Paramètres!$B$10,""),"") | AO49: =IF(ISNUMBER($AN49),$AN49/($R49/(1+Paramètres!$B$5)),"") | AP49: =IF($A49="","",IF($Y49<>1,"INCOMPLET",IF(NOT(ISNUMBER($AM49)),"SANS RÉF. MARCHÉ",IF($AM49<=Paramètres!$B$12,"OK",IF(AND($AO49>=Paramètres!$B$15,$AN49>=Paramètres!$B$16),"À REVOIR","NON RENTABLE"))))) -> INCOMPLET | AQ49: =TRIM(IF(AND($Y49=1,ISNUMBER($N49)),IF($M49<$N49,"MOQ ",""),"")&IF(AND($Y49=1,ISNUMBER($O49)),IF($O49<$I49*$M49,"DISPO ",""),"")&IF($S49="O","FICTIF ","")&IF($Y49=1,IF(AND($K49="TTC",$W49<>"CH"),"TVA-ÉTRANGÈRE ",""),"")) | AR49: =IF($Y49=1,COUNTIFS($A$6:$A$205,$A49,$AK$6:$AK$205,"<"&$AK49,$Y$6:$Y$205,1)+1,"") | AS49: =IF(ISNUMBER($AR49),$A49&"|"&$AR49,"") | AT49: =IF($Y49=1,$AK49*$I49*$M49,"")
A50: REF-01 | B50: Coffret Dresseur d'Élite (ETB) 30ᵉ Anniversaire – FR | C50: TCG Distribution | G50: 30ᵉ Anniversaire | H50: etb | S50: N | T50: =IF($C50="","",IFERROR(INDEX(Fournisseurs!$C$5:$C$24,MATCH($C50,Fournisseurs!$A$5:$A$24,0)),"")) -> 0 | U50: =IF($C50="","",IFERROR(INDEX(Fournisseurs!$D$5:$D$24,MATCH($C50,Fournisseurs!$A$5:$A$24,0)),"")) -> 0 | V50: =IF($C50="","",IFERROR(INDEX(Fournisseurs!$G$5:$G$24,MATCH($C50,Fournisseurs!$A$5:$A$24,0)),"")) -> 0 | W50: =IF($C50="","",IFERROR(INDEX(Fournisseurs!$H$5:$H$24,MATCH($C50,Fournisseurs!$A$5:$A$24,0)),"")) -> 0 | X50: =IF($C50="","",IFERROR(INDEX(Fournisseurs!$B$5:$B$24,MATCH($C50,Fournisseurs!$A$5:$A$24,0)),"")) -> 0 | Y50: =IF($A50="","",IF(AND($A50<>"",$C50<>"",ISNUMBER($I50),ISNUMBER($J50),ISNUMBER($M50)),IF(AND($I50>=1,$J50>0,OR($K50="HT",$K50="TTC"),$M50>=1,IFERROR(INDEX(Fournisseurs!$T$5:$T$24,MATCH($C50,Fournisseurs!$A$5:$A$24,0)),0)=1),1,0),0)) -> 0 | Z50: =IF($Y50=1,$J50*(1-N($L50)),"") | AA50: =IF($Y50=1,IF($K50="TTC",$Z50/(1+$V50),$Z50),"") | AB50: =IF($Y50=1,IF($K50="TTC",$Z50-$AA50,$AA50*$V50),"") | AC50: =IF($Y50=1,$AA50*$U50*$M50,"") | AD50: =IF($Y50=1,$AC50/SUMIFS($AC$6:$AC$205,$C$6:$C$205,$C50,$Y$6:$Y$205,1),"") | AE50: =IF($Y50=1,(INDEX(Fournisseurs!$J$5:$J$24,MATCH($C50,Fournisseurs!$A$5:$A$24,0))+INDEX(Fournisseurs!$K$5:$K$24,MATCH($C50,Fournisseurs!$A$5:$A$24,0)))*$U50*$AD50/($I50*$M50),"") | AF50: =IF($Y50=1,INDEX(Fournisseurs!$L$5:$L$24,MATCH($C50,Fournisseurs!$A$5:$A$24,0))*$AD50/($I50*$M50),"") | AG50: =IF($Y50=1,$AA50*$U50/$I50,"") | AH50: =IF($Y50=1,$AB50*$U50/$I50,"") | AI50: =IF($Y50=1,IF(AND(Paramètres!$B$4="EFFECTIVE",$W50="CH",$AB50>0),1,0),"") | AJ50: =IF($Y50=1,IF($X50<>"CH",($AG50+$AE50+$AF50)*Paramètres!$B$14,0),"") | AK50: =IF($Y50=1,$AG50+IF($AI50=1,0,$AH50)+$AE50+$AF50+IF(Paramètres!$B$4="NOT_REGISTERED",$AJ50,0),"") | AL50: =IF($Y50=1,($AK50+Paramètres!$B$7+Paramètres!$B$8+Paramètres!$B$9+Paramètres!$B$10)/((1-Paramètres!$B$11)/(1+Paramètres!$B$5)-Paramètres!$B$6),"") | AM50: =IF(AND($Y50=1,ISNUMBER($R50)),IF($R50>0,$AL50/$R50-1,""),"") | AN50: =IF(AND($Y50=1,ISNUMBER($R50)),IF($R50>0,$R50/(1+Paramètres!$B$5)-$AK50-($R50*Paramètres!$B$6+Paramètres!$B$7)-Paramètres!$B$8-Paramètres!$B$9-Paramètres!$B$10,""),"") | AO50: =IF(ISNUMBER($AN50),$AN50/($R50/(1+Paramètres!$B$5)),"") | AP50: =IF($A50="","",IF($Y50<>1,"INCOMPLET",IF(NOT(ISNUMBER($AM50)),"SANS RÉF. MARCHÉ",IF($AM50<=Paramètres!$B$12,"OK",IF(AND($AO50>=Paramètres!$B$15,$AN50>=Paramètres!$B$16),"À REVOIR","NON RENTABLE"))))) -> INCOMPLET | AQ50: =TRIM(IF(AND($Y50=1,ISNUMBER($N50)),IF($M50<$N50,"MOQ ",""),"")&IF(AND($Y50=1,ISNUMBER($O50)),IF($O50<$I50*$M50,"DISPO ",""),"")&IF($S50="O","FICTIF ","")&IF($Y50=1,IF(AND($K50="TTC",$W50<>"CH"),"TVA-ÉTRANGÈRE ",""),"")) | AR50: =IF($Y50=1,COUNTIFS($A$6:$A$205,$A50,$AK$6:$AK$205,"<"&$AK50,$Y$6:$Y$205,1)+1,"") | AS50: =IF(ISNUMBER($AR50),$A50&"|"&$AR50,"") | AT50: =IF($Y50=1,$AK50*$I50*$M50,"")
A51: REF-07 | B51: Coffret Dresseur d'Élite (ETB) Méga-Évolution – Nuit Noire – FR | C51: TCG Distribution | G51: Méga-Évolution – Nuit Noire | H51: etb | S51: N | T51: =IF($C51="","",IFERROR(INDEX(Fournisseurs!$C$5:$C$24,MATCH($C51,Fournisseurs!$A$5:$A$24,0)),"")) -> 0 | U51: =IF($C51="","",IFERROR(INDEX(Fournisseurs!$D$5:$D$24,MATCH($C51,Fournisseurs!$A$5:$A$24,0)),"")) -> 0 | V51: =IF($C51="","",IFERROR(INDEX(Fournisseurs!$G$5:$G$24,MATCH($C51,Fournisseurs!$A$5:$A$24,0)),"")) -> 0 | W51: =IF($C51="","",IFERROR(INDEX(Fournisseurs!$H$5:$H$24,MATCH($C51,Fournisseurs!$A$5:$A$24,0)),"")) -> 0 | X51: =IF($C51="","",IFERROR(INDEX(Fournisseurs!$B$5:$B$24,MATCH($C51,Fournisseurs!$A$5:$A$24,0)),"")) -> 0 | Y51: =IF($A51="","",IF(AND($A51<>"",$C51<>"",ISNUMBER($I51),ISNUMBER($J51),ISNUMBER($M51)),IF(AND($I51>=1,$J51>0,OR($K51="HT",$K51="TTC"),$M51>=1,IFERROR(INDEX(Fournisseurs!$T$5:$T$24,MATCH($C51,Fournisseurs!$A$5:$A$24,0)),0)=1),1,0),0)) -> 0 | Z51: =IF($Y51=1,$J51*(1-N($L51)),"") | AA51: =IF($Y51=1,IF($K51="TTC",$Z51/(1+$V51),$Z51),"") | AB51: =IF($Y51=1,IF($K51="TTC",$Z51-$AA51,$AA51*$V51),"") | AC51: =IF($Y51=1,$AA51*$U51*$M51,"") | AD51: =IF($Y51=1,$AC51/SUMIFS($AC$6:$AC$205,$C$6:$C$205,$C51,$Y$6:$Y$205,1),"") | AE51: =IF($Y51=1,(INDEX(Fournisseurs!$J$5:$J$24,MATCH($C51,Fournisseurs!$A$5:$A$24,0))+INDEX(Fournisseurs!$K$5:$K$24,MATCH($C51,Fournisseurs!$A$5:$A$24,0)))*$U51*$AD51/($I51*$M51),"") | AF51: =IF($Y51=1,INDEX(Fournisseurs!$L$5:$L$24,MATCH($C51,Fournisseurs!$A$5:$A$24,0))*$AD51/($I51*$M51),"") | AG51: =IF($Y51=1,$AA51*$U51/$I51,"") | AH51: =IF($Y51=1,$AB51*$U51/$I51,"") | AI51: =IF($Y51=1,IF(AND(Paramètres!$B$4="EFFECTIVE",$W51="CH",$AB51>0),1,0),"") | AJ51: =IF($Y51=1,IF($X51<>"CH",($AG51+$AE51+$AF51)*Paramètres!$B$14,0),"") | AK51: =IF($Y51=1,$AG51+IF($AI51=1,0,$AH51)+$AE51+$AF51+IF(Paramètres!$B$4="NOT_REGISTERED",$AJ51,0),"") | AL51: =IF($Y51=1,($AK51+Paramètres!$B$7+Paramètres!$B$8+Paramètres!$B$9+Paramètres!$B$10)/((1-Paramètres!$B$11)/(1+Paramètres!$B$5)-Paramètres!$B$6),"") | AM51: =IF(AND($Y51=1,ISNUMBER($R51)),IF($R51>0,$AL51/$R51-1,""),"") | AN51: =IF(AND($Y51=1,ISNUMBER($R51)),IF($R51>0,$R51/(1+Paramètres!$B$5)-$AK51-($R51*Paramètres!$B$6+Paramètres!$B$7)-Paramètres!$B$8-Paramètres!$B$9-Paramètres!$B$10,""),"") | AO51: =IF(ISNUMBER($AN51),$AN51/($R51/(1+Paramètres!$B$5)),"") | AP51: =IF($A51="","",IF($Y51<>1,"INCOMPLET",IF(NOT(ISNUMBER($AM51)),"SANS RÉF. MARCHÉ",IF($AM51<=Paramètres!$B$12,"OK",IF(AND($AO51>=Paramètres!$B$15,$AN51>=Paramètres!$B$16),"À REVOIR","NON RENTABLE"))))) -> INCOMPLET | AQ51: =TRIM(IF(AND($Y51=1,ISNUMBER($N51)),IF($M51<$N51,"MOQ ",""),"")&IF(AND($Y51=1,ISNUMBER($O51)),IF($O51<$I51*$M51,"DISPO ",""),"")&IF($S51="O","FICTIF ","")&IF($Y51=1,IF(AND($K51="TTC",$W51<>"CH"),"TVA-ÉTRANGÈRE ",""),"")) | AR51: =IF($Y51=1,COUNTIFS($A$6:$A$205,$A51,$AK$6:$AK$205,"<"&$AK51,$Y$6:$Y$205,1)+1,"") | AS51: =IF(ISNUMBER($AR51),$A51&"|"&$AR51,"") | AT51: =IF($Y51=1,$AK51*$I51*$M51,"")
A52: REF-11 | B52: Coffret Dresseur d'Élite (ETB) Méga-Évolution – Équilibre Parfait – FR | C52: TCG Distribution | G52: Méga-Évolution – Équilibre Parfait | H52: etb | S52: N | T52: =IF($C52="","",IFERROR(INDEX(Fournisseurs!$C$5:$C$24,MATCH($C52,Fournisseurs!$A$5:$A$24,0)),"")) -> 0 | U52: =IF($C52="","",IFERROR(INDEX(Fournisseurs!$D$5:$D$24,MATCH($C52,Fournisseurs!$A$5:$A$24,0)),"")) -> 0 | V52: =IF($C52="","",IFERROR(INDEX(Fournisseurs!$G$5:$G$24,MATCH($C52,Fournisseurs!$A$5:$A$24,0)),"")) -> 0 | W52: =IF($C52="","",IFERROR(INDEX(Fournisseurs!$H$5:$H$24,MATCH($C52,Fournisseurs!$A$5:$A$24,0)),"")) -> 0 | X52: =IF($C52="","",IFERROR(INDEX(Fournisseurs!$B$5:$B$24,MATCH($C52,Fournisseurs!$A$5:$A$24,0)),"")) -> 0 | Y52: =IF($A52="","",IF(AND($A52<>"",$C52<>"",ISNUMBER($I52),ISNUMBER($J52),ISNUMBER($M52)),IF(AND($I52>=1,$J52>0,OR($K52="HT",$K52="TTC"),$M52>=1,IFERROR(INDEX(Fournisseurs!$T$5:$T$24,MATCH($C52,Fournisseurs!$A$5:$A$24,0)),0)=1),1,0),0)) -> 0 | Z52: =IF($Y52=1,$J52*(1-N($L52)),"") | AA52: =IF($Y52=1,IF($K52="TTC",$Z52/(1+$V52),$Z52),"") | AB52: =IF($Y52=1,IF($K52="TTC",$Z52-$AA52,$AA52*$V52),"") | AC52: =IF($Y52=1,$AA52*$U52*$M52,"") | AD52: =IF($Y52=1,$AC52/SUMIFS($AC$6:$AC$205,$C$6:$C$205,$C52,$Y$6:$Y$205,1),"") | AE52: =IF($Y52=1,(INDEX(Fournisseurs!$J$5:$J$24,MATCH($C52,Fournisseurs!$A$5:$A$24,0))+INDEX(Fournisseurs!$K$5:$K$24,MATCH($C52,Fournisseurs!$A$5:$A$24,0)))*$U52*$AD52/($I52*$M52),"") | AF52: =IF($Y52=1,INDEX(Fournisseurs!$L$5:$L$24,MATCH($C52,Fournisseurs!$A$5:$A$24,0))*$AD52/($I52*$M52),"") | AG52: =IF($Y52=1,$AA52*$U52/$I52,"") | AH52: =IF($Y52=1,$AB52*$U52/$I52,"") | AI52: =IF($Y52=1,IF(AND(Paramètres!$B$4="EFFECTIVE",$W52="CH",$AB52>0),1,0),"") | AJ52: =IF($Y52=1,IF($X52<>"CH",($AG52+$AE52+$AF52)*Paramètres!$B$14,0),"") | AK52: =IF($Y52=1,$AG52+IF($AI52=1,0,$AH52)+$AE52+$AF52+IF(Paramètres!$B$4="NOT_REGISTERED",$AJ52,0),"") | AL52: =IF($Y52=1,($AK52+Paramètres!$B$7+Paramètres!$B$8+Paramètres!$B$9+Paramètres!$B$10)/((1-Paramètres!$B$11)/(1+Paramètres!$B$5)-Paramètres!$B$6),"") | AM52: =IF(AND($Y52=1,ISNUMBER($R52)),IF($R52>0,$AL52/$R52-1,""),"") | AN52: =IF(AND($Y52=1,ISNUMBER($R52)),IF($R52>0,$R52/(1+Paramètres!$B$5)-$AK52-($R52*Paramètres!$B$6+Paramètres!$B$7)-Paramètres!$B$8-Paramètres!$B$9-Paramètres!$B$10,""),"") | AO52: =IF(ISNUMBER($AN52),$AN52/($R52/(1+Paramètres!$B$5)),"") | AP52: =IF($A52="","",IF($Y52<>1,"INCOMPLET",IF(NOT(ISNUMBER($AM52)),"SANS RÉF. MARCHÉ",IF($AM52<=Paramètres!$B$12,"OK",IF(AND($AO52>=Paramètres!$B$15,$AN52>=Paramètres!$B$16),"À REVOIR","NON RENTABLE"))))) -> INCOMPLET | AQ52: =TRIM(IF(AND($Y52=1,ISNUMBER($N52)),IF($M52<$N52,"MOQ ",""),"")&IF(AND($Y52=1,ISNUMBER($O52)),IF($O52<$I52*$M52,"DISPO ",""),"")&IF($S52="O","FICTIF ","")&IF($Y52=1,IF(AND($K52="TTC",$W52<>"CH"),"TVA-ÉTRANGÈRE ",""),"")) | AR52: =IF($Y52=1,COUNTIFS($A$6:$A$205,$A52,$AK$6:$AK$205,"<"&$AK52,$Y$6:$Y$205,1)+1,"") | AS52: =IF(ISNUMBER($AR52),$A52&"|"&$AR52,"") | AT52: =IF($Y52=1,$AK52*$I52*$M52,"")
A53: REF-02 | B53: Bundle 30ᵉ Anniversaire – FR | C53: TCG Distribution | G53: 30ᵉ Anniversaire | H53: bundle | S53: N | T53: =IF($C53="","",IFERROR(INDEX(Fournisseurs!$C$5:$C$24,MATCH($C53,Fournisseurs!$A$5:$A$24,0)),"")) -> 0 | U53: =IF($C53="","",IFERROR(INDEX(Fournisseurs!$D$5:$D$24,MATCH($C53,Fournisseurs!$A$5:$A$24,0)),"")) -> 0 | V53: =IF($C53="","",IFERROR(INDEX(Fournisseurs!$G$5:$G$24,MATCH($C53,Fournisseurs!$A$5:$A$24,0)),"")) -> 0 | W53: =IF($C53="","",IFERROR(INDEX(Fournisseurs!$H$5:$H$24,MATCH($C53,Fournisseurs!$A$5:$A$24,0)),"")) -> 0 | X53: =IF($C53="","",IFERROR(INDEX(Fournisseurs!$B$5:$B$24,MATCH($C53,Fournisseurs!$A$5:$A$24,0)),"")) -> 0 | Y53: =IF($A53="","",IF(AND($A53<>"",$C53<>"",ISNUMBER($I53),ISNUMBER($J53),ISNUMBER($M53)),IF(AND($I53>=1,$J53>0,OR($K53="HT",$K53="TTC"),$M53>=1,IFERROR(INDEX(Fournisseurs!$T$5:$T$24,MATCH($C53,Fournisseurs!$A$5:$A$24,0)),0)=1),1,0),0)) -> 0 | Z53: =IF($Y53=1,$J53*(1-N($L53)),"") | AA53: =IF($Y53=1,IF($K53="TTC",$Z53/(1+$V53),$Z53),"") | AB53: =IF($Y53=1,IF($K53="TTC",$Z53-$AA53,$AA53*$V53),"") | AC53: =IF($Y53=1,$AA53*$U53*$M53,"") | AD53: =IF($Y53=1,$AC53/SUMIFS($AC$6:$AC$205,$C$6:$C$205,$C53,$Y$6:$Y$205,1),"") | AE53: =IF($Y53=1,(INDEX(Fournisseurs!$J$5:$J$24,MATCH($C53,Fournisseurs!$A$5:$A$24,0))+INDEX(Fournisseurs!$K$5:$K$24,MATCH($C53,Fournisseurs!$A$5:$A$24,0)))*$U53*$AD53/($I53*$M53),"") | AF53: =IF($Y53=1,INDEX(Fournisseurs!$L$5:$L$24,MATCH($C53,Fournisseurs!$A$5:$A$24,0))*$AD53/($I53*$M53),"") | AG53: =IF($Y53=1,$AA53*$U53/$I53,"") | AH53: =IF($Y53=1,$AB53*$U53/$I53,"") | AI53: =IF($Y53=1,IF(AND(Paramètres!$B$4="EFFECTIVE",$W53="CH",$AB53>0),1,0),"") | AJ53: =IF($Y53=1,IF($X53<>"CH",($AG53+$AE53+$AF53)*Paramètres!$B$14,0),"") | AK53: =IF($Y53=1,$AG53+IF($AI53=1,0,$AH53)+$AE53+$AF53+IF(Paramètres!$B$4="NOT_REGISTERED",$AJ53,0),"") | AL53: =IF($Y53=1,($AK53+Paramètres!$B$7+Paramètres!$B$8+Paramètres!$B$9+Paramètres!$B$10)/((1-Paramètres!$B$11)/(1+Paramètres!$B$5)-Paramètres!$B$6),"") | AM53: =IF(AND($Y53=1,ISNUMBER($R53)),IF($R53>0,$AL53/$R53-1,""),"") | AN53: =IF(AND($Y53=1,ISNUMBER($R53)),IF($R53>0,$R53/(1+Paramètres!$B$5)-$AK53-($R53*Paramètres!$B$6+Paramètres!$B$7)-Paramètres!$B$8-Paramètres!$B$9-Paramètres!$B$10,""),"") | AO53: =IF(ISNUMBER($AN53),$AN53/($R53/(1+Paramètres!$B$5)),"") | AP53: =IF($A53="","",IF($Y53<>1,"INCOMPLET",IF(NOT(ISNUMBER($AM53)),"SANS RÉF. MARCHÉ",IF($AM53<=Paramètres!$B$12,"OK",IF(AND($AO53>=Paramètres!$B$15,$AN53>=Paramètres!$B$16),"À REVOIR","NON RENTABLE"))))) -> INCOMPLET | AQ53: =TRIM(IF(AND($Y53=1,ISNUMBER($N53)),IF($M53<$N53,"MOQ ",""),"")&IF(AND($Y53=1,ISNUMBER($O53)),IF($O53<$I53*$M53,"DISPO ",""),"")&IF($S53="O","FICTIF ","")&IF($Y53=1,IF(AND($K53="TTC",$W53<>"CH"),"TVA-ÉTRANGÈRE ",""),"")) | AR53: =IF($Y53=1,COUNTIFS($A$6:$A$205,$A53,$AK$6:$AK$205,"<"&$AK53,$Y$6:$Y$205,1)+1,"") | AS53: =IF(ISNUMBER($AR53),$A53&"|"&$AR53,"") | AT53: =IF($Y53=1,$AK53*$I53*$M53,"")
A54: REF-08 | B54: Tripack Méga-Évolution – Nuit Noire – FR | C54: TCG Distribution | G54: Méga-Évolution – Nuit Noire | H54: tripack | S54: N | T54: =IF($C54="","",IFERROR(INDEX(Fournisseurs!$C$5:$C$24,MATCH($C54,Fournisseurs!$A$5:$A$24,0)),"")) -> 0 | U54: =IF($C54="","",IFERROR(INDEX(Fournisseurs!$D$5:$D$24,MATCH($C54,Fournisseurs!$A$5:$A$24,0)),"")) -> 0 | V54: =IF($C54="","",IFERROR(INDEX(Fournisseurs!$G$5:$G$24,MATCH($C54,Fournisseurs!$A$5:$A$24,0)),"")) -> 0 | W54: =IF($C54="","",IFERROR(INDEX(Fournisseurs!$H$5:$H$24,MATCH($C54,Fournisseurs!$A$5:$A$24,0)),"")) -> 0 | X54: =IF($C54="","",IFERROR(INDEX(Fournisseurs!$B$5:$B$24,MATCH($C54,Fournisseurs!$A$5:$A$24,0)),"")) -> 0 | Y54: =IF($A54="","",IF(AND($A54<>"",$C54<>"",ISNUMBER($I54),ISNUMBER($J54),ISNUMBER($M54)),IF(AND($I54>=1,$J54>0,OR($K54="HT",$K54="TTC"),$M54>=1,IFERROR(INDEX(Fournisseurs!$T$5:$T$24,MATCH($C54,Fournisseurs!$A$5:$A$24,0)),0)=1),1,0),0)) -> 0 | Z54: =IF($Y54=1,$J54*(1-N($L54)),"") | AA54: =IF($Y54=1,IF($K54="TTC",$Z54/(1+$V54),$Z54),"") | AB54: =IF($Y54=1,IF($K54="TTC",$Z54-$AA54,$AA54*$V54),"") | AC54: =IF($Y54=1,$AA54*$U54*$M54,"") | AD54: =IF($Y54=1,$AC54/SUMIFS($AC$6:$AC$205,$C$6:$C$205,$C54,$Y$6:$Y$205,1),"") | AE54: =IF($Y54=1,(INDEX(Fournisseurs!$J$5:$J$24,MATCH($C54,Fournisseurs!$A$5:$A$24,0))+INDEX(Fournisseurs!$K$5:$K$24,MATCH($C54,Fournisseurs!$A$5:$A$24,0)))*$U54*$AD54/($I54*$M54),"") | AF54: =IF($Y54=1,INDEX(Fournisseurs!$L$5:$L$24,MATCH($C54,Fournisseurs!$A$5:$A$24,0))*$AD54/($I54*$M54),"") | AG54: =IF($Y54=1,$AA54*$U54/$I54,"") | AH54: =IF($Y54=1,$AB54*$U54/$I54,"") | AI54: =IF($Y54=1,IF(AND(Paramètres!$B$4="EFFECTIVE",$W54="CH",$AB54>0),1,0),"") | AJ54: =IF($Y54=1,IF($X54<>"CH",($AG54+$AE54+$AF54)*Paramètres!$B$14,0),"") | AK54: =IF($Y54=1,$AG54+IF($AI54=1,0,$AH54)+$AE54+$AF54+IF(Paramètres!$B$4="NOT_REGISTERED",$AJ54,0),"") | AL54: =IF($Y54=1,($AK54+Paramètres!$B$7+Paramètres!$B$8+Paramètres!$B$9+Paramètres!$B$10)/((1-Paramètres!$B$11)/(1+Paramètres!$B$5)-Paramètres!$B$6),"") | AM54: =IF(AND($Y54=1,ISNUMBER($R54)),IF($R54>0,$AL54/$R54-1,""),"") | AN54: =IF(AND($Y54=1,ISNUMBER($R54)),IF($R54>0,$R54/(1+Paramètres!$B$5)-$AK54-($R54*Paramètres!$B$6+Paramètres!$B$7)-Paramètres!$B$8-Paramètres!$B$9-Paramètres!$B$10,""),"") | AO54: =IF(ISNUMBER($AN54),$AN54/($R54/(1+Paramètres!$B$5)),"") | AP54: =IF($A54="","",IF($Y54<>1,"INCOMPLET",IF(NOT(ISNUMBER($AM54)),"SANS RÉF. MARCHÉ",IF($AM54<=Paramètres!$B$12,"OK",IF(AND($AO54>=Paramètres!$B$15,$AN54>=Paramètres!$B$16),"À REVOIR","NON RENTABLE"))))) -> INCOMPLET | AQ54: =TRIM(IF(AND($Y54=1,ISNUMBER($N54)),IF($M54<$N54,"MOQ ",""),"")&IF(AND($Y54=1,ISNUMBER($O54)),IF($O54<$I54*$M54,"DISPO ",""),"")&IF($S54="O","FICTIF ","")&IF($Y54=1,IF(AND($K54="TTC",$W54<>"CH"),"TVA-ÉTRANGÈRE ",""),"")) | AR54: =IF($Y54=1,COUNTIFS($A$6:$A$205,$A54,$AK$6:$AK$205,"<"&$AK54,$Y$6:$Y$205,1)+1,"") | AS54: =IF(ISNUMBER($AR54),$A54&"|"&$AR54,"") | AT54: =IF($Y54=1,$AK54*$I54*$M54,"")
A55: REF-19 | B55: Tripack ou bundle Méga-Évolution – Chaos Ascendant – FR | C55: TCG Distribution | G55: Méga-Évolution – Chaos Ascendant | H55: tripack | S55: N | T55: =IF($C55="","",IFERROR(INDEX(Fournisseurs!$C$5:$C$24,MATCH($C55,Fournisseurs!$A$5:$A$24,0)),"")) -> 0 | U55: =IF($C55="","",IFERROR(INDEX(Fournisseurs!$D$5:$D$24,MATCH($C55,Fournisseurs!$A$5:$A$24,0)),"")) -> 0 | V55: =IF($C55="","",IFERROR(INDEX(Fournisseurs!$G$5:$G$24,MATCH($C55,Fournisseurs!$A$5:$A$24,0)),"")) -> 0 | W55: =IF($C55="","",IFERROR(INDEX(Fournisseurs!$H$5:$H$24,MATCH($C55,Fournisseurs!$A$5:$A$24,0)),"")) -> 0 | X55: =IF($C55="","",IFERROR(INDEX(Fournisseurs!$B$5:$B$24,MATCH($C55,Fournisseurs!$A$5:$A$24,0)),"")) -> 0 | Y55: =IF($A55="","",IF(AND($A55<>"",$C55<>"",ISNUMBER($I55),ISNUMBER($J55),ISNUMBER($M55)),IF(AND($I55>=1,$J55>0,OR($K55="HT",$K55="TTC"),$M55>=1,IFERROR(INDEX(Fournisseurs!$T$5:$T$24,MATCH($C55,Fournisseurs!$A$5:$A$24,0)),0)=1),1,0),0)) -> 0 | Z55: =IF($Y55=1,$J55*(1-N($L55)),"") | AA55: =IF($Y55=1,IF($K55="TTC",$Z55/(1+$V55),$Z55),"") | AB55: =IF($Y55=1,IF($K55="TTC",$Z55-$AA55,$AA55*$V55),"") | AC55: =IF($Y55=1,$AA55*$U55*$M55,"") | AD55: =IF($Y55=1,$AC55/SUMIFS($AC$6:$AC$205,$C$6:$C$205,$C55,$Y$6:$Y$205,1),"") | AE55: =IF($Y55=1,(INDEX(Fournisseurs!$J$5:$J$24,MATCH($C55,Fournisseurs!$A$5:$A$24,0))+INDEX(Fournisseurs!$K$5:$K$24,MATCH($C55,Fournisseurs!$A$5:$A$24,0)))*$U55*$AD55/($I55*$M55),"") | AF55: =IF($Y55=1,INDEX(Fournisseurs!$L$5:$L$24,MATCH($C55,Fournisseurs!$A$5:$A$24,0))*$AD55/($I55*$M55),"") | AG55: =IF($Y55=1,$AA55*$U55/$I55,"") | AH55: =IF($Y55=1,$AB55*$U55/$I55,"") | AI55: =IF($Y55=1,IF(AND(Paramètres!$B$4="EFFECTIVE",$W55="CH",$AB55>0),1,0),"") | AJ55: =IF($Y55=1,IF($X55<>"CH",($AG55+$AE55+$AF55)*Paramètres!$B$14,0),"") | AK55: =IF($Y55=1,$AG55+IF($AI55=1,0,$AH55)+$AE55+$AF55+IF(Paramètres!$B$4="NOT_REGISTERED",$AJ55,0),"") | AL55: =IF($Y55=1,($AK55+Paramètres!$B$7+Paramètres!$B$8+Paramètres!$B$9+Paramètres!$B$10)/((1-Paramètres!$B$11)/(1+Paramètres!$B$5)-Paramètres!$B$6),"") | AM55: =IF(AND($Y55=1,ISNUMBER($R55)),IF($R55>0,$AL55/$R55-1,""),"") | AN55: =IF(AND($Y55=1,ISNUMBER($R55)),IF($R55>0,$R55/(1+Paramètres!$B$5)-$AK55-($R55*Paramètres!$B$6+Paramètres!$B$7)-Paramètres!$B$8-Paramètres!$B$9-Paramètres!$B$10,""),"") | AO55: =IF(ISNUMBER($AN55),$AN55/($R55/(1+Paramètres!$B$5)),"") | AP55: =IF($A55="","",IF($Y55<>1,"INCOMPLET",IF(NOT(ISNUMBER($AM55)),"SANS RÉF. MARCHÉ",IF($AM55<=Paramètres!$B$12,"OK",IF(AND($AO55>=Paramètres!$B$15,$AN55>=Paramètres!$B$16),"À REVOIR","NON RENTABLE"))))) -> INCOMPLET | AQ55: =TRIM(IF(AND($Y55=1,ISNUMBER($N55)),IF($M55<$N55,"MOQ ",""),"")&IF(AND($Y55=1,ISNUMBER($O55)),IF($O55<$I55*$M55,"DISPO ",""),"")&IF($S55="O","FICTIF ","")&IF($Y55=1,IF(AND($K55="TTC",$W55<>"CH"),"TVA-ÉTRANGÈRE ",""),"")) | AR55: =IF($Y55=1,COUNTIFS($A$6:$A$205,$A55,$AK$6:$AK$205,"<"&$AK55,$Y$6:$Y$205,1)+1,"") | AS55: =IF(ISNUMBER($AR55),$A55&"|"&$AR55,"") | AT55: =IF($Y55=1,$AK55*$I55*$M55,"")
A56: REF-04 | B56: Coffret 30ᵉ Anniversaire Nymphali-ex – FR | C56: TCG Distribution | G56: 30ᵉ Anniversaire | H56: coffret | S56: N | T56: =IF($C56="","",IFERROR(INDEX(Fournisseurs!$C$5:$C$24,MATCH($C56,Fournisseurs!$A$5:$A$24,0)),"")) -> 0 | U56: =IF($C56="","",IFERROR(INDEX(Fournisseurs!$D$5:$D$24,MATCH($C56,Fournisseurs!$A$5:$A$24,0)),"")) -> 0 | V56: =IF($C56="","",IFERROR(INDEX(Fournisseurs!$G$5:$G$24,MATCH($C56,Fournisseurs!$A$5:$A$24,0)),"")) -> 0 | W56: =IF($C56="","",IFERROR(INDEX(Fournisseurs!$H$5:$H$24,MATCH($C56,Fournisseurs!$A$5:$A$24,0)),"")) -> 0 | X56: =IF($C56="","",IFERROR(INDEX(Fournisseurs!$B$5:$B$24,MATCH($C56,Fournisseurs!$A$5:$A$24,0)),"")) -> 0 | Y56: =IF($A56="","",IF(AND($A56<>"",$C56<>"",ISNUMBER($I56),ISNUMBER($J56),ISNUMBER($M56)),IF(AND($I56>=1,$J56>0,OR($K56="HT",$K56="TTC"),$M56>=1,IFERROR(INDEX(Fournisseurs!$T$5:$T$24,MATCH($C56,Fournisseurs!$A$5:$A$24,0)),0)=1),1,0),0)) -> 0 | Z56: =IF($Y56=1,$J56*(1-N($L56)),"") | AA56: =IF($Y56=1,IF($K56="TTC",$Z56/(1+$V56),$Z56),"") | AB56: =IF($Y56=1,IF($K56="TTC",$Z56-$AA56,$AA56*$V56),"") | AC56: =IF($Y56=1,$AA56*$U56*$M56,"") | AD56: =IF($Y56=1,$AC56/SUMIFS($AC$6:$AC$205,$C$6:$C$205,$C56,$Y$6:$Y$205,1),"") | AE56: =IF($Y56=1,(INDEX(Fournisseurs!$J$5:$J$24,MATCH($C56,Fournisseurs!$A$5:$A$24,0))+INDEX(Fournisseurs!$K$5:$K$24,MATCH($C56,Fournisseurs!$A$5:$A$24,0)))*$U56*$AD56/($I56*$M56),"") | AF56: =IF($Y56=1,INDEX(Fournisseurs!$L$5:$L$24,MATCH($C56,Fournisseurs!$A$5:$A$24,0))*$AD56/($I56*$M56),"") | AG56: =IF($Y56=1,$AA56*$U56/$I56,"") | AH56: =IF($Y56=1,$AB56*$U56/$I56,"") | AI56: =IF($Y56=1,IF(AND(Paramètres!$B$4="EFFECTIVE",$W56="CH",$AB56>0),1,0),"") | AJ56: =IF($Y56=1,IF($X56<>"CH",($AG56+$AE56+$AF56)*Paramètres!$B$14,0),"") | AK56: =IF($Y56=1,$AG56+IF($AI56=1,0,$AH56)+$AE56+$AF56+IF(Paramètres!$B$4="NOT_REGISTERED",$AJ56,0),"") | AL56: =IF($Y56=1,($AK56+Paramètres!$B$7+Paramètres!$B$8+Paramètres!$B$9+Paramètres!$B$10)/((1-Paramètres!$B$11)/(1+Paramètres!$B$5)-Paramètres!$B$6),"") | AM56: =IF(AND($Y56=1,ISNUMBER($R56)),IF($R56>0,$AL56/$R56-1,""),"") | AN56: =IF(AND($Y56=1,ISNUMBER($R56)),IF($R56>0,$R56/(1+Paramètres!$B$5)-$AK56-($R56*Paramètres!$B$6+Paramètres!$B$7)-Paramètres!$B$8-Paramètres!$B$9-Paramètres!$B$10,""),"") | AO56: =IF(ISNUMBER($AN56),$AN56/($R56/(1+Paramètres!$B$5)),"") | AP56: =IF($A56="","",IF($Y56<>1,"INCOMPLET",IF(NOT(ISNUMBER($AM56)),"SANS RÉF. MARCHÉ",IF($AM56<=Paramètres!$B$12,"OK",IF(AND($AO56>=Paramètres!$B$15,$AN56>=Paramètres!$B$16),"À REVOIR","NON RENTABLE"))))) -> INCOMPLET | AQ56: =TRIM(IF(AND($Y56=1,ISNUMBER($N56)),IF($M56<$N56,"MOQ ",""),"")&IF(AND($Y56=1,ISNUMBER($O56)),IF($O56<$I56*$M56,"DISPO ",""),"")&IF($S56="O","FICTIF ","")&IF($Y56=1,IF(AND($K56="TTC",$W56<>"CH"),"TVA-ÉTRANGÈRE ",""),"")) | AR56: =IF($Y56=1,COUNTIFS($A$6:$A$205,$A56,$AK$6:$AK$205,"<"&$AK56,$Y$6:$Y$205,1)+1,"") | AS56: =IF(ISNUMBER($AR56),$A56&"|"&$AR56,"") | AT56: =IF($Y56=1,$AK56*$I56*$M56,"")
A57: REF-20 | B57: Coffret ou collection – Équilibre Parfait ou Héros Transcendants – FR | C57: TCG Distribution | G57: Méga-Évolution – Équilibre Parfait / Héros Transcendants | H57: coffret | S57: N | T57: =IF($C57="","",IFERROR(INDEX(Fournisseurs!$C$5:$C$24,MATCH($C57,Fournisseurs!$A$5:$A$24,0)),"")) -> 0 | U57: =IF($C57="","",IFERROR(INDEX(Fournisseurs!$D$5:$D$24,MATCH($C57,Fournisseurs!$A$5:$A$24,0)),"")) -> 0 | V57: =IF($C57="","",IFERROR(INDEX(Fournisseurs!$G$5:$G$24,MATCH($C57,Fournisseurs!$A$5:$A$24,0)),"")) -> 0 | W57: =IF($C57="","",IFERROR(INDEX(Fournisseurs!$H$5:$H$24,MATCH($C57,Fournisseurs!$A$5:$A$24,0)),"")) -> 0 | X57: =IF($C57="","",IFERROR(INDEX(Fournisseurs!$B$5:$B$24,MATCH($C57,Fournisseurs!$A$5:$A$24,0)),"")) -> 0 | Y57: =IF($A57="","",IF(AND($A57<>"",$C57<>"",ISNUMBER($I57),ISNUMBER($J57),ISNUMBER($M57)),IF(AND($I57>=1,$J57>0,OR($K57="HT",$K57="TTC"),$M57>=1,IFERROR(INDEX(Fournisseurs!$T$5:$T$24,MATCH($C57,Fournisseurs!$A$5:$A$24,0)),0)=1),1,0),0)) -> 0 | Z57: =IF($Y57=1,$J57*(1-N($L57)),"") | AA57: =IF($Y57=1,IF($K57="TTC",$Z57/(1+$V57),$Z57),"") | AB57: =IF($Y57=1,IF($K57="TTC",$Z57-$AA57,$AA57*$V57),"") | AC57: =IF($Y57=1,$AA57*$U57*$M57,"") | AD57: =IF($Y57=1,$AC57/SUMIFS($AC$6:$AC$205,$C$6:$C$205,$C57,$Y$6:$Y$205,1),"") | AE57: =IF($Y57=1,(INDEX(Fournisseurs!$J$5:$J$24,MATCH($C57,Fournisseurs!$A$5:$A$24,0))+INDEX(Fournisseurs!$K$5:$K$24,MATCH($C57,Fournisseurs!$A$5:$A$24,0)))*$U57*$AD57/($I57*$M57),"") | AF57: =IF($Y57=1,INDEX(Fournisseurs!$L$5:$L$24,MATCH($C57,Fournisseurs!$A$5:$A$24,0))*$AD57/($I57*$M57),"") | AG57: =IF($Y57=1,$AA57*$U57/$I57,"") | AH57: =IF($Y57=1,$AB57*$U57/$I57,"") | AI57: =IF($Y57=1,IF(AND(Paramètres!$B$4="EFFECTIVE",$W57="CH",$AB57>0),1,0),"") | AJ57: =IF($Y57=1,IF($X57<>"CH",($AG57+$AE57+$AF57)*Paramètres!$B$14,0),"") | AK57: =IF($Y57=1,$AG57+IF($AI57=1,0,$AH57)+$AE57+$AF57+IF(Paramètres!$B$4="NOT_REGISTERED",$AJ57,0),"") | AL57: =IF($Y57=1,($AK57+Paramètres!$B$7+Paramètres!$B$8+Paramètres!$B$9+Paramètres!$B$10)/((1-Paramètres!$B$11)/(1+Paramètres!$B$5)-Paramètres!$B$6),"") | AM57: =IF(AND($Y57=1,ISNUMBER($R57)),IF($R57>0,$AL57/$R57-1,""),"") | AN57: =IF(AND($Y57=1,ISNUMBER($R57)),IF($R57>0,$R57/(1+Paramètres!$B$5)-$AK57-($R57*Paramètres!$B$6+Paramètres!$B$7)-Paramètres!$B$8-Paramètres!$B$9-Paramètres!$B$10,""),"") | AO57: =IF(ISNUMBER($AN57),$AN57/($R57/(1+Paramètres!$B$5)),"") | AP57: =IF($A57="","",IF($Y57<>1,"INCOMPLET",IF(NOT(ISNUMBER($AM57)),"SANS RÉF. MARCHÉ",IF($AM57<=Paramètres!$B$12,"OK",IF(AND($AO57>=Paramètres!$B$15,$AN57>=Paramètres!$B$16),"À REVOIR","NON RENTABLE"))))) -> INCOMPLET | AQ57: =TRIM(IF(AND($Y57=1,ISNUMBER($N57)),IF($M57<$N57,"MOQ ",""),"")&IF(AND($Y57=1,ISNUMBER($O57)),IF($O57<$I57*$M57,"DISPO ",""),"")&IF($S57="O","FICTIF ","")&IF($Y57=1,IF(AND($K57="TTC",$W57<>"CH"),"TVA-ÉTRANGÈRE ",""),"")) | AR57: =IF($Y57=1,COUNTIFS($A$6:$A$205,$A57,$AK$6:$AK$205,"<"&$AK57,$Y$6:$Y$205,1)+1,"") | AS57: =IF(ISNUMBER($AR57),$A57&"|"&$AR57,"") | AT57: =IF($Y57=1,$AK57*$I57*$M57,"")
A58: REF-16 | B58: Protège-cartes format standard (paquet) | C58: TCG Distribution | H58: accessoire | S58: N | T58: =IF($C58="","",IFERROR(INDEX(Fournisseurs!$C$5:$C$24,MATCH($C58,Fournisseurs!$A$5:$A$24,0)),"")) -> 0 | U58: =IF($C58="","",IFERROR(INDEX(Fournisseurs!$D$5:$D$24,MATCH($C58,Fournisseurs!$A$5:$A$24,0)),"")) -> 0 | V58: =IF($C58="","",IFERROR(INDEX(Fournisseurs!$G$5:$G$24,MATCH($C58,Fournisseurs!$A$5:$A$24,0)),"")) -> 0 | W58: =IF($C58="","",IFERROR(INDEX(Fournisseurs!$H$5:$H$24,MATCH($C58,Fournisseurs!$A$5:$A$24,0)),"")) -> 0 | X58: =IF($C58="","",IFERROR(INDEX(Fournisseurs!$B$5:$B$24,MATCH($C58,Fournisseurs!$A$5:$A$24,0)),"")) -> 0 | Y58: =IF($A58="","",IF(AND($A58<>"",$C58<>"",ISNUMBER($I58),ISNUMBER($J58),ISNUMBER($M58)),IF(AND($I58>=1,$J58>0,OR($K58="HT",$K58="TTC"),$M58>=1,IFERROR(INDEX(Fournisseurs!$T$5:$T$24,MATCH($C58,Fournisseurs!$A$5:$A$24,0)),0)=1),1,0),0)) -> 0 | Z58: =IF($Y58=1,$J58*(1-N($L58)),"") | AA58: =IF($Y58=1,IF($K58="TTC",$Z58/(1+$V58),$Z58),"") | AB58: =IF($Y58=1,IF($K58="TTC",$Z58-$AA58,$AA58*$V58),"") | AC58: =IF($Y58=1,$AA58*$U58*$M58,"") | AD58: =IF($Y58=1,$AC58/SUMIFS($AC$6:$AC$205,$C$6:$C$205,$C58,$Y$6:$Y$205,1),"") | AE58: =IF($Y58=1,(INDEX(Fournisseurs!$J$5:$J$24,MATCH($C58,Fournisseurs!$A$5:$A$24,0))+INDEX(Fournisseurs!$K$5:$K$24,MATCH($C58,Fournisseurs!$A$5:$A$24,0)))*$U58*$AD58/($I58*$M58),"") | AF58: =IF($Y58=1,INDEX(Fournisseurs!$L$5:$L$24,MATCH($C58,Fournisseurs!$A$5:$A$24,0))*$AD58/($I58*$M58),"") | AG58: =IF($Y58=1,$AA58*$U58/$I58,"") | AH58: =IF($Y58=1,$AB58*$U58/$I58,"") | AI58: =IF($Y58=1,IF(AND(Paramètres!$B$4="EFFECTIVE",$W58="CH",$AB58>0),1,0),"") | AJ58: =IF($Y58=1,IF($X58<>"CH",($AG58+$AE58+$AF58)*Paramètres!$B$14,0),"") | AK58: =IF($Y58=1,$AG58+IF($AI58=1,0,$AH58)+$AE58+$AF58+IF(Paramètres!$B$4="NOT_REGISTERED",$AJ58,0),"") | AL58: =IF($Y58=1,($AK58+Paramètres!$B$7+Paramètres!$B$8+Paramètres!$B$9+Paramètres!$B$10)/((1-Paramètres!$B$11)/(1+Paramètres!$B$5)-Paramètres!$B$6),"") | AM58: =IF(AND($Y58=1,ISNUMBER($R58)),IF($R58>0,$AL58/$R58-1,""),"") | AN58: =IF(AND($Y58=1,ISNUMBER($R58)),IF($R58>0,$R58/(1+Paramètres!$B$5)-$AK58-($R58*Paramètres!$B$6+Paramètres!$B$7)-Paramètres!$B$8-Paramètres!$B$9-Paramètres!$B$10,""),"") | AO58: =IF(ISNUMBER($AN58),$AN58/($R58/(1+Paramètres!$B$5)),"") | AP58: =IF($A58="","",IF($Y58<>1,"INCOMPLET",IF(NOT(ISNUMBER($AM58)),"SANS RÉF. MARCHÉ",IF($AM58<=Paramètres!$B$12,"OK",IF(AND($AO58>=Paramètres!$B$15,$AN58>=Paramètres!$B$16),"À REVOIR","NON RENTABLE"))))) -> INCOMPLET | AQ58: =TRIM(IF(AND($Y58=1,ISNUMBER($N58)),IF($M58<$N58,"MOQ ",""),"")&IF(AND($Y58=1,ISNUMBER($O58)),IF($O58<$I58*$M58,"DISPO ",""),"")&IF($S58="O","FICTIF ","")&IF($Y58=1,IF(AND($K58="TTC",$W58<>"CH"),"TVA-ÉTRANGÈRE ",""),"")) | AR58: =IF($Y58=1,COUNTIFS($A$6:$A$205,$A58,$AK$6:$AK$205,"<"&$AK58,$Y$6:$Y$205,1)+1,"") | AS58: =IF(ISNUMBER($AR58),$A58&"|"&$AR58,"") | AT58: =IF($Y58=1,$AK58*$I58*$M58,"")
A59: REF-17 | B59: Classeur 9 cases | C59: TCG Distribution | H59: accessoire | S59: N | T59: =IF($C59="","",IFERROR(INDEX(Fournisseurs!$C$5:$C$24,MATCH($C59,Fournisseurs!$A$5:$A$24,0)),"")) -> 0 | U59: =IF($C59="","",IFERROR(INDEX(Fournisseurs!$D$5:$D$24,MATCH($C59,Fournisseurs!$A$5:$A$24,0)),"")) -> 0 | V59: =IF($C59="","",IFERROR(INDEX(Fournisseurs!$G$5:$G$24,MATCH($C59,Fournisseurs!$A$5:$A$24,0)),"")) -> 0 | W59: =IF($C59="","",IFERROR(INDEX(Fournisseurs!$H$5:$H$24,MATCH($C59,Fournisseurs!$A$5:$A$24,0)),"")) -> 0 | X59: =IF($C59="","",IFERROR(INDEX(Fournisseurs!$B$5:$B$24,MATCH($C59,Fournisseurs!$A$5:$A$24,0)),"")) -> 0 | Y59: =IF($A59="","",IF(AND($A59<>"",$C59<>"",ISNUMBER($I59),ISNUMBER($J59),ISNUMBER($M59)),IF(AND($I59>=1,$J59>0,OR($K59="HT",$K59="TTC"),$M59>=1,IFERROR(INDEX(Fournisseurs!$T$5:$T$24,MATCH($C59,Fournisseurs!$A$5:$A$24,0)),0)=1),1,0),0)) -> 0 | Z59: =IF($Y59=1,$J59*(1-N($L59)),"") | AA59: =IF($Y59=1,IF($K59="TTC",$Z59/(1+$V59),$Z59),"") | AB59: =IF($Y59=1,IF($K59="TTC",$Z59-$AA59,$AA59*$V59),"") | AC59: =IF($Y59=1,$AA59*$U59*$M59,"") | AD59: =IF($Y59=1,$AC59/SUMIFS($AC$6:$AC$205,$C$6:$C$205,$C59,$Y$6:$Y$205,1),"") | AE59: =IF($Y59=1,(INDEX(Fournisseurs!$J$5:$J$24,MATCH($C59,Fournisseurs!$A$5:$A$24,0))+INDEX(Fournisseurs!$K$5:$K$24,MATCH($C59,Fournisseurs!$A$5:$A$24,0)))*$U59*$AD59/($I59*$M59),"") | AF59: =IF($Y59=1,INDEX(Fournisseurs!$L$5:$L$24,MATCH($C59,Fournisseurs!$A$5:$A$24,0))*$AD59/($I59*$M59),"") | AG59: =IF($Y59=1,$AA59*$U59/$I59,"") | AH59: =IF($Y59=1,$AB59*$U59/$I59,"") | AI59: =IF($Y59=1,IF(AND(Paramètres!$B$4="EFFECTIVE",$W59="CH",$AB59>0),1,0),"") | AJ59: =IF($Y59=1,IF($X59<>"CH",($AG59+$AE59+$AF59)*Paramètres!$B$14,0),"") | AK59: =IF($Y59=1,$AG59+IF($AI59=1,0,$AH59)+$AE59+$AF59+IF(Paramètres!$B$4="NOT_REGISTERED",$AJ59,0),"") | AL59: =IF($Y59=1,($AK59+Paramètres!$B$7+Paramètres!$B$8+Paramètres!$B$9+Paramètres!$B$10)/((1-Paramètres!$B$11)/(1+Paramètres!$B$5)-Paramètres!$B$6),"") | AM59: =IF(AND($Y59=1,ISNUMBER($R59)),IF($R59>0,$AL59/$R59-1,""),"") | AN59: =IF(AND($Y59=1,ISNUMBER($R59)),IF($R59>0,$R59/(1+Paramètres!$B$5)-$AK59-($R59*Paramètres!$B$6+Paramètres!$B$7)-Paramètres!$B$8-Paramètres!$B$9-Paramètres!$B$10,""),"") | AO59: =IF(ISNUMBER($AN59),$AN59/($R59/(1+Paramètres!$B$5)),"") | AP59: =IF($A59="","",IF($Y59<>1,"INCOMPLET",IF(NOT(ISNUMBER($AM59)),"SANS RÉF. MARCHÉ",IF($AM59<=Paramètres!$B$12,"OK",IF(AND($AO59>=Paramètres!$B$15,$AN59>=Paramètres!$B$16),"À REVOIR","NON RENTABLE"))))) -> INCOMPLET | AQ59: =TRIM(IF(AND($Y59=1,ISNUMBER($N59)),IF($M59<$N59,"MOQ ",""),"")&IF(AND($Y59=1,ISNUMBER($O59)),IF($O59<$I59*$M59,"DISPO ",""),"")&IF($S59="O","FICTIF ","")&IF($Y59=1,IF(AND($K59="TTC",$W59<>"CH"),"TVA-ÉTRANGÈRE ",""),"")) | AR59: =IF($Y59=1,COUNTIFS($A$6:$A$205,$A59,$AK$6:$AK$205,"<"&$AK59,$Y$6:$Y$205,1)+1,"") | AS59: =IF(ISNUMBER($AR59),$A59&"|"&$AR59,"") | AT59: =IF($Y59=1,$AK59*$I59*$M59,"")
A60: REF-03 | B60: Mini-Tin 30ᵉ Anniversaire – FR | C60: TCG Distribution | G60: 30ᵉ Anniversaire | H60: coffret | S60: N | T60: =IF($C60="","",IFERROR(INDEX(Fournisseurs!$C$5:$C$24,MATCH($C60,Fournisseurs!$A$5:$A$24,0)),"")) -> 0 | U60: =IF($C60="","",IFERROR(INDEX(Fournisseurs!$D$5:$D$24,MATCH($C60,Fournisseurs!$A$5:$A$24,0)),"")) -> 0 | V60: =IF($C60="","",IFERROR(INDEX(Fournisseurs!$G$5:$G$24,MATCH($C60,Fournisseurs!$A$5:$A$24,0)),"")) -> 0 | W60: =IF($C60="","",IFERROR(INDEX(Fournisseurs!$H$5:$H$24,MATCH($C60,Fournisseurs!$A$5:$A$24,0)),"")) -> 0 | X60: =IF($C60="","",IFERROR(INDEX(Fournisseurs!$B$5:$B$24,MATCH($C60,Fournisseurs!$A$5:$A$24,0)),"")) -> 0 | Y60: =IF($A60="","",IF(AND($A60<>"",$C60<>"",ISNUMBER($I60),ISNUMBER($J60),ISNUMBER($M60)),IF(AND($I60>=1,$J60>0,OR($K60="HT",$K60="TTC"),$M60>=1,IFERROR(INDEX(Fournisseurs!$T$5:$T$24,MATCH($C60,Fournisseurs!$A$5:$A$24,0)),0)=1),1,0),0)) -> 0 | Z60: =IF($Y60=1,$J60*(1-N($L60)),"") | AA60: =IF($Y60=1,IF($K60="TTC",$Z60/(1+$V60),$Z60),"") | AB60: =IF($Y60=1,IF($K60="TTC",$Z60-$AA60,$AA60*$V60),"") | AC60: =IF($Y60=1,$AA60*$U60*$M60,"") | AD60: =IF($Y60=1,$AC60/SUMIFS($AC$6:$AC$205,$C$6:$C$205,$C60,$Y$6:$Y$205,1),"") | AE60: =IF($Y60=1,(INDEX(Fournisseurs!$J$5:$J$24,MATCH($C60,Fournisseurs!$A$5:$A$24,0))+INDEX(Fournisseurs!$K$5:$K$24,MATCH($C60,Fournisseurs!$A$5:$A$24,0)))*$U60*$AD60/($I60*$M60),"") | AF60: =IF($Y60=1,INDEX(Fournisseurs!$L$5:$L$24,MATCH($C60,Fournisseurs!$A$5:$A$24,0))*$AD60/($I60*$M60),"") | AG60: =IF($Y60=1,$AA60*$U60/$I60,"") | AH60: =IF($Y60=1,$AB60*$U60/$I60,"") | AI60: =IF($Y60=1,IF(AND(Paramètres!$B$4="EFFECTIVE",$W60="CH",$AB60>0),1,0),"") | AJ60: =IF($Y60=1,IF($X60<>"CH",($AG60+$AE60+$AF60)*Paramètres!$B$14,0),"") | AK60: =IF($Y60=1,$AG60+IF($AI60=1,0,$AH60)+$AE60+$AF60+IF(Paramètres!$B$4="NOT_REGISTERED",$AJ60,0),"") | AL60: =IF($Y60=1,($AK60+Paramètres!$B$7+Paramètres!$B$8+Paramètres!$B$9+Paramètres!$B$10)/((1-Paramètres!$B$11)/(1+Paramètres!$B$5)-Paramètres!$B$6),"") | AM60: =IF(AND($Y60=1,ISNUMBER($R60)),IF($R60>0,$AL60/$R60-1,""),"") | AN60: =IF(AND($Y60=1,ISNUMBER($R60)),IF($R60>0,$R60/(1+Paramètres!$B$5)-$AK60-($R60*Paramètres!$B$6+Paramètres!$B$7)-Paramètres!$B$8-Paramètres!$B$9-Paramètres!$B$10,""),"") | AO60: =IF(ISNUMBER($AN60),$AN60/($R60/(1+Paramètres!$B$5)),"") | AP60: =IF($A60="","",IF($Y60<>1,"INCOMPLET",IF(NOT(ISNUMBER($AM60)),"SANS RÉF. MARCHÉ",IF($AM60<=Paramètres!$B$12,"OK",IF(AND($AO60>=Paramètres!$B$15,$AN60>=Paramètres!$B$16),"À REVOIR","NON RENTABLE"))))) -> INCOMPLET | AQ60: =TRIM(IF(AND($Y60=1,ISNUMBER($N60)),IF($M60<$N60,"MOQ ",""),"")&IF(AND($Y60=1,ISNUMBER($O60)),IF($O60<$I60*$M60,"DISPO ",""),"")&IF($S60="O","FICTIF ","")&IF($Y60=1,IF(AND($K60="TTC",$W60<>"CH"),"TVA-ÉTRANGÈRE ",""),"")) | AR60: =IF($Y60=1,COUNTIFS($A$6:$A$205,$A60,$AK$6:$AK$205,"<"&$AK60,$Y$6:$Y$205,1)+1,"") | AS60: =IF(ISNUMBER($AR60),$A60&"|"&$AR60,"") | AT60: =IF($Y60=1,$AK60*$I60*$M60,"")
A61: REF-05 | B61: Collection Classeur 30ᵉ Anniversaire – FR | C61: TCG Distribution | G61: 30ᵉ Anniversaire | H61: coffret | S61: N | T61: =IF($C61="","",IFERROR(INDEX(Fournisseurs!$C$5:$C$24,MATCH($C61,Fournisseurs!$A$5:$A$24,0)),"")) -> 0 | U61: =IF($C61="","",IFERROR(INDEX(Fournisseurs!$D$5:$D$24,MATCH($C61,Fournisseurs!$A$5:$A$24,0)),"")) -> 0 | V61: =IF($C61="","",IFERROR(INDEX(Fournisseurs!$G$5:$G$24,MATCH($C61,Fournisseurs!$A$5:$A$24,0)),"")) -> 0 | W61: =IF($C61="","",IFERROR(INDEX(Fournisseurs!$H$5:$H$24,MATCH($C61,Fournisseurs!$A$5:$A$24,0)),"")) -> 0 | X61: =IF($C61="","",IFERROR(INDEX(Fournisseurs!$B$5:$B$24,MATCH($C61,Fournisseurs!$A$5:$A$24,0)),"")) -> 0 | Y61: =IF($A61="","",IF(AND($A61<>"",$C61<>"",ISNUMBER($I61),ISNUMBER($J61),ISNUMBER($M61)),IF(AND($I61>=1,$J61>0,OR($K61="HT",$K61="TTC"),$M61>=1,IFERROR(INDEX(Fournisseurs!$T$5:$T$24,MATCH($C61,Fournisseurs!$A$5:$A$24,0)),0)=1),1,0),0)) -> 0 | Z61: =IF($Y61=1,$J61*(1-N($L61)),"") | AA61: =IF($Y61=1,IF($K61="TTC",$Z61/(1+$V61),$Z61),"") | AB61: =IF($Y61=1,IF($K61="TTC",$Z61-$AA61,$AA61*$V61),"") | AC61: =IF($Y61=1,$AA61*$U61*$M61,"") | AD61: =IF($Y61=1,$AC61/SUMIFS($AC$6:$AC$205,$C$6:$C$205,$C61,$Y$6:$Y$205,1),"") | AE61: =IF($Y61=1,(INDEX(Fournisseurs!$J$5:$J$24,MATCH($C61,Fournisseurs!$A$5:$A$24,0))+INDEX(Fournisseurs!$K$5:$K$24,MATCH($C61,Fournisseurs!$A$5:$A$24,0)))*$U61*$AD61/($I61*$M61),"") | AF61: =IF($Y61=1,INDEX(Fournisseurs!$L$5:$L$24,MATCH($C61,Fournisseurs!$A$5:$A$24,0))*$AD61/($I61*$M61),"") | AG61: =IF($Y61=1,$AA61*$U61/$I61,"") | AH61: =IF($Y61=1,$AB61*$U61/$I61,"") | AI61: =IF($Y61=1,IF(AND(Paramètres!$B$4="EFFECTIVE",$W61="CH",$AB61>0),1,0),"") | AJ61: =IF($Y61=1,IF($X61<>"CH",($AG61+$AE61+$AF61)*Paramètres!$B$14,0),"") | AK61: =IF($Y61=1,$AG61+IF($AI61=1,0,$AH61)+$AE61+$AF61+IF(Paramètres!$B$4="NOT_REGISTERED",$AJ61,0),"") | AL61: =IF($Y61=1,($AK61+Paramètres!$B$7+Paramètres!$B$8+Paramètres!$B$9+Paramètres!$B$10)/((1-Paramètres!$B$11)/(1+Paramètres!$B$5)-Paramètres!$B$6),"") | AM61: =IF(AND($Y61=1,ISNUMBER($R61)),IF($R61>0,$AL61/$R61-1,""),"") | AN61: =IF(AND($Y61=1,ISNUMBER($R61)),IF($R61>0,$R61/(1+Paramètres!$B$5)-$AK61-($R61*Paramètres!$B$6+Paramètres!$B$7)-Paramètres!$B$8-Paramètres!$B$9-Paramètres!$B$10,""),"") | AO61: =IF(ISNUMBER($AN61),$AN61/($R61/(1+Paramètres!$B$5)),"") | AP61: =IF($A61="","",IF($Y61<>1,"INCOMPLET",IF(NOT(ISNUMBER($AM61)),"SANS RÉF. MARCHÉ",IF($AM61<=Paramètres!$B$12,"OK",IF(AND($AO61>=Paramètres!$B$15,$AN61>=Paramètres!$B$16),"À REVOIR","NON RENTABLE"))))) -> INCOMPLET | AQ61: =TRIM(IF(AND($Y61=1,ISNUMBER($N61)),IF($M61<$N61,"MOQ ",""),"")&IF(AND($Y61=1,ISNUMBER($O61)),IF($O61<$I61*$M61,"DISPO ",""),"")&IF($S61="O","FICTIF ","")&IF($Y61=1,IF(AND($K61="TTC",$W61<>"CH"),"TVA-ÉTRANGÈRE ",""),"")) | AR61: =IF($Y61=1,COUNTIFS($A$6:$A$205,$A61,$AK$6:$AK$205,"<"&$AK61,$Y$6:$Y$205,1)+1,"") | AS61: =IF(ISNUMBER($AR61),$A61&"|"&$AR61,"") | AT61: =IF($Y61=1,$AK61*$I61*$M61,"")
A62: REF-10 | B62: Coffret Dresseur d'Élite (ETB) Méga-Évolution – Chaos Ascendant – FR | C62: TCG Distribution | G62: Méga-Évolution – Chaos Ascendant | H62: etb | S62: N | T62: =IF($C62="","",IFERROR(INDEX(Fournisseurs!$C$5:$C$24,MATCH($C62,Fournisseurs!$A$5:$A$24,0)),"")) -> 0 | U62: =IF($C62="","",IFERROR(INDEX(Fournisseurs!$D$5:$D$24,MATCH($C62,Fournisseurs!$A$5:$A$24,0)),"")) -> 0 | V62: =IF($C62="","",IFERROR(INDEX(Fournisseurs!$G$5:$G$24,MATCH($C62,Fournisseurs!$A$5:$A$24,0)),"")) -> 0 | W62: =IF($C62="","",IFERROR(INDEX(Fournisseurs!$H$5:$H$24,MATCH($C62,Fournisseurs!$A$5:$A$24,0)),"")) -> 0 | X62: =IF($C62="","",IFERROR(INDEX(Fournisseurs!$B$5:$B$24,MATCH($C62,Fournisseurs!$A$5:$A$24,0)),"")) -> 0 | Y62: =IF($A62="","",IF(AND($A62<>"",$C62<>"",ISNUMBER($I62),ISNUMBER($J62),ISNUMBER($M62)),IF(AND($I62>=1,$J62>0,OR($K62="HT",$K62="TTC"),$M62>=1,IFERROR(INDEX(Fournisseurs!$T$5:$T$24,MATCH($C62,Fournisseurs!$A$5:$A$24,0)),0)=1),1,0),0)) -> 0 | Z62: =IF($Y62=1,$J62*(1-N($L62)),"") | AA62: =IF($Y62=1,IF($K62="TTC",$Z62/(1+$V62),$Z62),"") | AB62: =IF($Y62=1,IF($K62="TTC",$Z62-$AA62,$AA62*$V62),"") | AC62: =IF($Y62=1,$AA62*$U62*$M62,"") | AD62: =IF($Y62=1,$AC62/SUMIFS($AC$6:$AC$205,$C$6:$C$205,$C62,$Y$6:$Y$205,1),"") | AE62: =IF($Y62=1,(INDEX(Fournisseurs!$J$5:$J$24,MATCH($C62,Fournisseurs!$A$5:$A$24,0))+INDEX(Fournisseurs!$K$5:$K$24,MATCH($C62,Fournisseurs!$A$5:$A$24,0)))*$U62*$AD62/($I62*$M62),"") | AF62: =IF($Y62=1,INDEX(Fournisseurs!$L$5:$L$24,MATCH($C62,Fournisseurs!$A$5:$A$24,0))*$AD62/($I62*$M62),"") | AG62: =IF($Y62=1,$AA62*$U62/$I62,"") | AH62: =IF($Y62=1,$AB62*$U62/$I62,"") | AI62: =IF($Y62=1,IF(AND(Paramètres!$B$4="EFFECTIVE",$W62="CH",$AB62>0),1,0),"") | AJ62: =IF($Y62=1,IF($X62<>"CH",($AG62+$AE62+$AF62)*Paramètres!$B$14,0),"") | AK62: =IF($Y62=1,$AG62+IF($AI62=1,0,$AH62)+$AE62+$AF62+IF(Paramètres!$B$4="NOT_REGISTERED",$AJ62,0),"") | AL62: =IF($Y62=1,($AK62+Paramètres!$B$7+Paramètres!$B$8+Paramètres!$B$9+Paramètres!$B$10)/((1-Paramètres!$B$11)/(1+Paramètres!$B$5)-Paramètres!$B$6),"") | AM62: =IF(AND($Y62=1,ISNUMBER($R62)),IF($R62>0,$AL62/$R62-1,""),"") | AN62: =IF(AND($Y62=1,ISNUMBER($R62)),IF($R62>0,$R62/(1+Paramètres!$B$5)-$AK62-($R62*Paramètres!$B$6+Paramètres!$B$7)-Paramètres!$B$8-Paramètres!$B$9-Paramètres!$B$10,""),"") | AO62: =IF(ISNUMBER($AN62),$AN62/($R62/(1+Paramètres!$B$5)),"") | AP62: =IF($A62="","",IF($Y62<>1,"INCOMPLET",IF(NOT(ISNUMBER($AM62)),"SANS RÉF. MARCHÉ",IF($AM62<=Paramètres!$B$12,"OK",IF(AND($AO62>=Paramètres!$B$15,$AN62>=Paramètres!$B$16),"À REVOIR","NON RENTABLE"))))) -> INCOMPLET | AQ62: =TRIM(IF(AND($Y62=1,ISNUMBER($N62)),IF($M62<$N62,"MOQ ",""),"")&IF(AND($Y62=1,ISNUMBER($O62)),IF($O62<$I62*$M62,"DISPO ",""),"")&IF($S62="O","FICTIF ","")&IF($Y62=1,IF(AND($K62="TTC",$W62<>"CH"),"TVA-ÉTRANGÈRE ",""),"")) | AR62: =IF($Y62=1,COUNTIFS($A$6:$A$205,$A62,$AK$6:$AK$205,"<"&$AK62,$Y$6:$Y$205,1)+1,"") | AS62: =IF(ISNUMBER($AR62),$A62&"|"&$AR62,"") | AT62: =IF($Y62=1,$AK62*$I62*$M62,"")
A63: REF-12 | B63: Coffret Dresseur d'Élite (ETB) Méga-Évolution – Héros Transcendants – FR | C63: TCG Distribution | G63: Méga-Évolution – Héros Transcendants | H63: etb | S63: N | T63: =IF($C63="","",IFERROR(INDEX(Fournisseurs!$C$5:$C$24,MATCH($C63,Fournisseurs!$A$5:$A$24,0)),"")) -> 0 | U63: =IF($C63="","",IFERROR(INDEX(Fournisseurs!$D$5:$D$24,MATCH($C63,Fournisseurs!$A$5:$A$24,0)),"")) -> 0 | V63: =IF($C63="","",IFERROR(INDEX(Fournisseurs!$G$5:$G$24,MATCH($C63,Fournisseurs!$A$5:$A$24,0)),"")) -> 0 | W63: =IF($C63="","",IFERROR(INDEX(Fournisseurs!$H$5:$H$24,MATCH($C63,Fournisseurs!$A$5:$A$24,0)),"")) -> 0 | X63: =IF($C63="","",IFERROR(INDEX(Fournisseurs!$B$5:$B$24,MATCH($C63,Fournisseurs!$A$5:$A$24,0)),"")) -> 0 | Y63: =IF($A63="","",IF(AND($A63<>"",$C63<>"",ISNUMBER($I63),ISNUMBER($J63),ISNUMBER($M63)),IF(AND($I63>=1,$J63>0,OR($K63="HT",$K63="TTC"),$M63>=1,IFERROR(INDEX(Fournisseurs!$T$5:$T$24,MATCH($C63,Fournisseurs!$A$5:$A$24,0)),0)=1),1,0),0)) -> 0 | Z63: =IF($Y63=1,$J63*(1-N($L63)),"") | AA63: =IF($Y63=1,IF($K63="TTC",$Z63/(1+$V63),$Z63),"") | AB63: =IF($Y63=1,IF($K63="TTC",$Z63-$AA63,$AA63*$V63),"") | AC63: =IF($Y63=1,$AA63*$U63*$M63,"") | AD63: =IF($Y63=1,$AC63/SUMIFS($AC$6:$AC$205,$C$6:$C$205,$C63,$Y$6:$Y$205,1),"") | AE63: =IF($Y63=1,(INDEX(Fournisseurs!$J$5:$J$24,MATCH($C63,Fournisseurs!$A$5:$A$24,0))+INDEX(Fournisseurs!$K$5:$K$24,MATCH($C63,Fournisseurs!$A$5:$A$24,0)))*$U63*$AD63/($I63*$M63),"") | AF63: =IF($Y63=1,INDEX(Fournisseurs!$L$5:$L$24,MATCH($C63,Fournisseurs!$A$5:$A$24,0))*$AD63/($I63*$M63),"") | AG63: =IF($Y63=1,$AA63*$U63/$I63,"") | AH63: =IF($Y63=1,$AB63*$U63/$I63,"") | AI63: =IF($Y63=1,IF(AND(Paramètres!$B$4="EFFECTIVE",$W63="CH",$AB63>0),1,0),"") | AJ63: =IF($Y63=1,IF($X63<>"CH",($AG63+$AE63+$AF63)*Paramètres!$B$14,0),"") | AK63: =IF($Y63=1,$AG63+IF($AI63=1,0,$AH63)+$AE63+$AF63+IF(Paramètres!$B$4="NOT_REGISTERED",$AJ63,0),"") | AL63: =IF($Y63=1,($AK63+Paramètres!$B$7+Paramètres!$B$8+Paramètres!$B$9+Paramètres!$B$10)/((1-Paramètres!$B$11)/(1+Paramètres!$B$5)-Paramètres!$B$6),"") | AM63: =IF(AND($Y63=1,ISNUMBER($R63)),IF($R63>0,$AL63/$R63-1,""),"") | AN63: =IF(AND($Y63=1,ISNUMBER($R63)),IF($R63>0,$R63/(1+Paramètres!$B$5)-$AK63-($R63*Paramètres!$B$6+Paramètres!$B$7)-Paramètres!$B$8-Paramètres!$B$9-Paramètres!$B$10,""),"") | AO63: =IF(ISNUMBER($AN63),$AN63/($R63/(1+Paramètres!$B$5)),"") | AP63: =IF($A63="","",IF($Y63<>1,"INCOMPLET",IF(NOT(ISNUMBER($AM63)),"SANS RÉF. MARCHÉ",IF($AM63<=Paramètres!$B$12,"OK",IF(AND($AO63>=Paramètres!$B$15,$AN63>=Paramètres!$B$16),"À REVOIR","NON RENTABLE"))))) -> INCOMPLET | AQ63: =TRIM(IF(AND($Y63=1,ISNUMBER($N63)),IF($M63<$N63,"MOQ ",""),"")&IF(AND($Y63=1,ISNUMBER($O63)),IF($O63<$I63*$M63,"DISPO ",""),"")&IF($S63="O","FICTIF ","")&IF($Y63=1,IF(AND($K63="TTC",$W63<>"CH"),"TVA-ÉTRANGÈRE ",""),"")) | AR63: =IF($Y63=1,COUNTIFS($A$6:$A$205,$A63,$AK$6:$AK$205,"<"&$AK63,$Y$6:$Y$205,1)+1,"") | AS63: =IF(ISNUMBER($AR63),$A63&"|"&$AR63,"") | AT63: =IF($Y63=1,$AK63*$I63*$M63,"")
A64: REF-13 | B64: Display 36 boosters Méga-Évolution – Règne Delta (ME06) – FR | C64: TCG Distribution | G64: Méga-Évolution – Règne Delta | H64: display | S64: N | T64: =IF($C64="","",IFERROR(INDEX(Fournisseurs!$C$5:$C$24,MATCH($C64,Fournisseurs!$A$5:$A$24,0)),"")) -> 0 | U64: =IF($C64="","",IFERROR(INDEX(Fournisseurs!$D$5:$D$24,MATCH($C64,Fournisseurs!$A$5:$A$24,0)),"")) -> 0 | V64: =IF($C64="","",IFERROR(INDEX(Fournisseurs!$G$5:$G$24,MATCH($C64,Fournisseurs!$A$5:$A$24,0)),"")) -> 0 | W64: =IF($C64="","",IFERROR(INDEX(Fournisseurs!$H$5:$H$24,MATCH($C64,Fournisseurs!$A$5:$A$24,0)),"")) -> 0 | X64: =IF($C64="","",IFERROR(INDEX(Fournisseurs!$B$5:$B$24,MATCH($C64,Fournisseurs!$A$5:$A$24,0)),"")) -> 0 | Y64: =IF($A64="","",IF(AND($A64<>"",$C64<>"",ISNUMBER($I64),ISNUMBER($J64),ISNUMBER($M64)),IF(AND($I64>=1,$J64>0,OR($K64="HT",$K64="TTC"),$M64>=1,IFERROR(INDEX(Fournisseurs!$T$5:$T$24,MATCH($C64,Fournisseurs!$A$5:$A$24,0)),0)=1),1,0),0)) -> 0 | Z64: =IF($Y64=1,$J64*(1-N($L64)),"") | AA64: =IF($Y64=1,IF($K64="TTC",$Z64/(1+$V64),$Z64),"") | AB64: =IF($Y64=1,IF($K64="TTC",$Z64-$AA64,$AA64*$V64),"") | AC64: =IF($Y64=1,$AA64*$U64*$M64,"") | AD64: =IF($Y64=1,$AC64/SUMIFS($AC$6:$AC$205,$C$6:$C$205,$C64,$Y$6:$Y$205,1),"") | AE64: =IF($Y64=1,(INDEX(Fournisseurs!$J$5:$J$24,MATCH($C64,Fournisseurs!$A$5:$A$24,0))+INDEX(Fournisseurs!$K$5:$K$24,MATCH($C64,Fournisseurs!$A$5:$A$24,0)))*$U64*$AD64/($I64*$M64),"") | AF64: =IF($Y64=1,INDEX(Fournisseurs!$L$5:$L$24,MATCH($C64,Fournisseurs!$A$5:$A$24,0))*$AD64/($I64*$M64),"") | AG64: =IF($Y64=1,$AA64*$U64/$I64,"") | AH64: =IF($Y64=1,$AB64*$U64/$I64,"") | AI64: =IF($Y64=1,IF(AND(Paramètres!$B$4="EFFECTIVE",$W64="CH",$AB64>0),1,0),"") | AJ64: =IF($Y64=1,IF($X64<>"CH",($AG64+$AE64+$AF64)*Paramètres!$B$14,0),"") | AK64: =IF($Y64=1,$AG64+IF($AI64=1,0,$AH64)+$AE64+$AF64+IF(Paramètres!$B$4="NOT_REGISTERED",$AJ64,0),"") | AL64: =IF($Y64=1,($AK64+Paramètres!$B$7+Paramètres!$B$8+Paramètres!$B$9+Paramètres!$B$10)/((1-Paramètres!$B$11)/(1+Paramètres!$B$5)-Paramètres!$B$6),"") | AM64: =IF(AND($Y64=1,ISNUMBER($R64)),IF($R64>0,$AL64/$R64-1,""),"") | AN64: =IF(AND($Y64=1,ISNUMBER($R64)),IF($R64>0,$R64/(1+Paramètres!$B$5)-$AK64-($R64*Paramètres!$B$6+Paramètres!$B$7)-Paramètres!$B$8-Paramètres!$B$9-Paramètres!$B$10,""),"") | AO64: =IF(ISNUMBER($AN64),$AN64/($R64/(1+Paramètres!$B$5)),"") | AP64: =IF($A64="","",IF($Y64<>1,"INCOMPLET",IF(NOT(ISNUMBER($AM64)),"SANS RÉF. MARCHÉ",IF($AM64<=Paramètres!$B$12,"OK",IF(AND($AO64>=Paramètres!$B$15,$AN64>=Paramètres!$B$16),"À REVOIR","NON RENTABLE"))))) -> INCOMPLET | AQ64: =TRIM(IF(AND($Y64=1,ISNUMBER($N64)),IF($M64<$N64,"MOQ ",""),"")&IF(AND($Y64=1,ISNUMBER($O64)),IF($O64<$I64*$M64,"DISPO ",""),"")&IF($S64="O","FICTIF ","")&IF($Y64=1,IF(AND($K64="TTC",$W64<>"CH"),"TVA-ÉTRANGÈRE ",""),"")) | AR64: =IF($Y64=1,COUNTIFS($A$6:$A$205,$A64,$AK$6:$AK$205,"<"&$AK64,$Y$6:$Y$205,1)+1,"") | AS64: =IF(ISNUMBER($AR64),$A64&"|"&$AR64,"") | AT64: =IF($Y64=1,$AK64*$I64*$M64,"")
A65: REF-14 | B65: Coffret Dresseur d'Élite (ETB) Méga-Évolution – Règne Delta – FR | C65: TCG Distribution | G65: Méga-Évolution – Règne Delta | H65: etb | S65: N | T65: =IF($C65="","",IFERROR(INDEX(Fournisseurs!$C$5:$C$24,MATCH($C65,Fournisseurs!$A$5:$A$24,0)),"")) -> 0 | U65: =IF($C65="","",IFERROR(INDEX(Fournisseurs!$D$5:$D$24,MATCH($C65,Fournisseurs!$A$5:$A$24,0)),"")) -> 0 | V65: =IF($C65="","",IFERROR(INDEX(Fournisseurs!$G$5:$G$24,MATCH($C65,Fournisseurs!$A$5:$A$24,0)),"")) -> 0 | W65: =IF($C65="","",IFERROR(INDEX(Fournisseurs!$H$5:$H$24,MATCH($C65,Fournisseurs!$A$5:$A$24,0)),"")) -> 0 | X65: =IF($C65="","",IFERROR(INDEX(Fournisseurs!$B$5:$B$24,MATCH($C65,Fournisseurs!$A$5:$A$24,0)),"")) -> 0 | Y65: =IF($A65="","",IF(AND($A65<>"",$C65<>"",ISNUMBER($I65),ISNUMBER($J65),ISNUMBER($M65)),IF(AND($I65>=1,$J65>0,OR($K65="HT",$K65="TTC"),$M65>=1,IFERROR(INDEX(Fournisseurs!$T$5:$T$24,MATCH($C65,Fournisseurs!$A$5:$A$24,0)),0)=1),1,0),0)) -> 0 | Z65: =IF($Y65=1,$J65*(1-N($L65)),"") | AA65: =IF($Y65=1,IF($K65="TTC",$Z65/(1+$V65),$Z65),"") | AB65: =IF($Y65=1,IF($K65="TTC",$Z65-$AA65,$AA65*$V65),"") | AC65: =IF($Y65=1,$AA65*$U65*$M65,"") | AD65: =IF($Y65=1,$AC65/SUMIFS($AC$6:$AC$205,$C$6:$C$205,$C65,$Y$6:$Y$205,1),"") | AE65: =IF($Y65=1,(INDEX(Fournisseurs!$J$5:$J$24,MATCH($C65,Fournisseurs!$A$5:$A$24,0))+INDEX(Fournisseurs!$K$5:$K$24,MATCH($C65,Fournisseurs!$A$5:$A$24,0)))*$U65*$AD65/($I65*$M65),"") | AF65: =IF($Y65=1,INDEX(Fournisseurs!$L$5:$L$24,MATCH($C65,Fournisseurs!$A$5:$A$24,0))*$AD65/($I65*$M65),"") | AG65: =IF($Y65=1,$AA65*$U65/$I65,"") | AH65: =IF($Y65=1,$AB65*$U65/$I65,"") | AI65: =IF($Y65=1,IF(AND(Paramètres!$B$4="EFFECTIVE",$W65="CH",$AB65>0),1,0),"") | AJ65: =IF($Y65=1,IF($X65<>"CH",($AG65+$AE65+$AF65)*Paramètres!$B$14,0),"") | AK65: =IF($Y65=1,$AG65+IF($AI65=1,0,$AH65)+$AE65+$AF65+IF(Paramètres!$B$4="NOT_REGISTERED",$AJ65,0),"") | AL65: =IF($Y65=1,($AK65+Paramètres!$B$7+Paramètres!$B$8+Paramètres!$B$9+Paramètres!$B$10)/((1-Paramètres!$B$11)/(1+Paramètres!$B$5)-Paramètres!$B$6),"") | AM65: =IF(AND($Y65=1,ISNUMBER($R65)),IF($R65>0,$AL65/$R65-1,""),"") | AN65: =IF(AND($Y65=1,ISNUMBER($R65)),IF($R65>0,$R65/(1+Paramètres!$B$5)-$AK65-($R65*Paramètres!$B$6+Paramètres!$B$7)-Paramètres!$B$8-Paramètres!$B$9-Paramètres!$B$10,""),"") | AO65: =IF(ISNUMBER($AN65),$AN65/($R65/(1+Paramètres!$B$5)),"") | AP65: =IF($A65="","",IF($Y65<>1,"INCOMPLET",IF(NOT(ISNUMBER($AM65)),"SANS RÉF. MARCHÉ",IF($AM65<=Paramètres!$B$12,"OK",IF(AND($AO65>=Paramètres!$B$15,$AN65>=Paramètres!$B$16),"À REVOIR","NON RENTABLE"))))) -> INCOMPLET | AQ65: =TRIM(IF(AND($Y65=1,ISNUMBER($N65)),IF($M65<$N65,"MOQ ",""),"")&IF(AND($Y65=1,ISNUMBER($O65)),IF($O65<$I65*$M65,"DISPO ",""),"")&IF($S65="O","FICTIF ","")&IF($Y65=1,IF(AND($K65="TTC",$W65<>"CH"),"TVA-ÉTRANGÈRE ",""),"")) | AR65: =IF($Y65=1,COUNTIFS($A$6:$A$205,$A65,$AK$6:$AK$205,"<"&$AK65,$Y$6:$Y$205,1)+1,"") | AS65: =IF(ISNUMBER($AR65),$A65&"|"&$AR65,"") | AT65: =IF($Y65=1,$AK65*$I65*$M65,"")
A66: REF-15 | B66: Tripack Méga-Évolution – Règne Delta – FR | C66: TCG Distribution | G66: Méga-Évolution – Règne Delta | H66: tripack | S66: N | T66: =IF($C66="","",IFERROR(INDEX(Fournisseurs!$C$5:$C$24,MATCH($C66,Fournisseurs!$A$5:$A$24,0)),"")) -> 0 | U66: =IF($C66="","",IFERROR(INDEX(Fournisseurs!$D$5:$D$24,MATCH($C66,Fournisseurs!$A$5:$A$24,0)),"")) -> 0 | V66: =IF($C66="","",IFERROR(INDEX(Fournisseurs!$G$5:$G$24,MATCH($C66,Fournisseurs!$A$5:$A$24,0)),"")) -> 0 | W66: =IF($C66="","",IFERROR(INDEX(Fournisseurs!$H$5:$H$24,MATCH($C66,Fournisseurs!$A$5:$A$24,0)),"")) -> 0 | X66: =IF($C66="","",IFERROR(INDEX(Fournisseurs!$B$5:$B$24,MATCH($C66,Fournisseurs!$A$5:$A$24,0)),"")) -> 0 | Y66: =IF($A66="","",IF(AND($A66<>"",$C66<>"",ISNUMBER($I66),ISNUMBER($J66),ISNUMBER($M66)),IF(AND($I66>=1,$J66>0,OR($K66="HT",$K66="TTC"),$M66>=1,IFERROR(INDEX(Fournisseurs!$T$5:$T$24,MATCH($C66,Fournisseurs!$A$5:$A$24,0)),0)=1),1,0),0)) -> 0 | Z66: =IF($Y66=1,$J66*(1-N($L66)),"") | AA66: =IF($Y66=1,IF($K66="TTC",$Z66/(1+$V66),$Z66),"") | AB66: =IF($Y66=1,IF($K66="TTC",$Z66-$AA66,$AA66*$V66),"") | AC66: =IF($Y66=1,$AA66*$U66*$M66,"") | AD66: =IF($Y66=1,$AC66/SUMIFS($AC$6:$AC$205,$C$6:$C$205,$C66,$Y$6:$Y$205,1),"") | AE66: =IF($Y66=1,(INDEX(Fournisseurs!$J$5:$J$24,MATCH($C66,Fournisseurs!$A$5:$A$24,0))+INDEX(Fournisseurs!$K$5:$K$24,MATCH($C66,Fournisseurs!$A$5:$A$24,0)))*$U66*$AD66/($I66*$M66),"") | AF66: =IF($Y66=1,INDEX(Fournisseurs!$L$5:$L$24,MATCH($C66,Fournisseurs!$A$5:$A$24,0))*$AD66/($I66*$M66),"") | AG66: =IF($Y66=1,$AA66*$U66/$I66,"") | AH66: =IF($Y66=1,$AB66*$U66/$I66,"") | AI66: =IF($Y66=1,IF(AND(Paramètres!$B$4="EFFECTIVE",$W66="CH",$AB66>0),1,0),"") | AJ66: =IF($Y66=1,IF($X66<>"CH",($AG66+$AE66+$AF66)*Paramètres!$B$14,0),"") | AK66: =IF($Y66=1,$AG66+IF($AI66=1,0,$AH66)+$AE66+$AF66+IF(Paramètres!$B$4="NOT_REGISTERED",$AJ66,0),"") | AL66: =IF($Y66=1,($AK66+Paramètres!$B$7+Paramètres!$B$8+Paramètres!$B$9+Paramètres!$B$10)/((1-Paramètres!$B$11)/(1+Paramètres!$B$5)-Paramètres!$B$6),"") | AM66: =IF(AND($Y66=1,ISNUMBER($R66)),IF($R66>0,$AL66/$R66-1,""),"") | AN66: =IF(AND($Y66=1,ISNUMBER($R66)),IF($R66>0,$R66/(1+Paramètres!$B$5)-$AK66-($R66*Paramètres!$B$6+Paramètres!$B$7)-Paramètres!$B$8-Paramètres!$B$9-Paramètres!$B$10,""),"") | AO66: =IF(ISNUMBER($AN66),$AN66/($R66/(1+Paramètres!$B$5)),"") | AP66: =IF($A66="","",IF($Y66<>1,"INCOMPLET",IF(NOT(ISNUMBER($AM66)),"SANS RÉF. MARCHÉ",IF($AM66<=Paramètres!$B$12,"OK",IF(AND($AO66>=Paramètres!$B$15,$AN66>=Paramètres!$B$16),"À REVOIR","NON RENTABLE"))))) -> INCOMPLET | AQ66: =TRIM(IF(AND($Y66=1,ISNUMBER($N66)),IF($M66<$N66,"MOQ ",""),"")&IF(AND($Y66=1,ISNUMBER($O66)),IF($O66<$I66*$M66,"DISPO ",""),"")&IF($S66="O","FICTIF ","")&IF($Y66=1,IF(AND($K66="TTC",$W66<>"CH"),"TVA-ÉTRANGÈRE ",""),"")) | AR66: =IF($Y66=1,COUNTIFS($A$6:$A$205,$A66,$AK$6:$AK$205,"<"&$AK66,$Y$6:$Y$205,1)+1,"") | AS66: =IF(ISNUMBER($AR66),$A66&"|"&$AR66,"") | AT66: =IF($Y66=1,$AK66*$I66*$M66,"")
A67: REF-18 | B67: Boîte de rangement de deck (deck box) | C67: TCG Distribution | H67: accessoire | S67: N | T67: =IF($C67="","",IFERROR(INDEX(Fournisseurs!$C$5:$C$24,MATCH($C67,Fournisseurs!$A$5:$A$24,0)),"")) -> 0 | U67: =IF($C67="","",IFERROR(INDEX(Fournisseurs!$D$5:$D$24,MATCH($C67,Fournisseurs!$A$5:$A$24,0)),"")) -> 0 | V67: =IF($C67="","",IFERROR(INDEX(Fournisseurs!$G$5:$G$24,MATCH($C67,Fournisseurs!$A$5:$A$24,0)),"")) -> 0 | W67: =IF($C67="","",IFERROR(INDEX(Fournisseurs!$H$5:$H$24,MATCH($C67,Fournisseurs!$A$5:$A$24,0)),"")) -> 0 | X67: =IF($C67="","",IFERROR(INDEX(Fournisseurs!$B$5:$B$24,MATCH($C67,Fournisseurs!$A$5:$A$24,0)),"")) -> 0 | Y67: =IF($A67="","",IF(AND($A67<>"",$C67<>"",ISNUMBER($I67),ISNUMBER($J67),ISNUMBER($M67)),IF(AND($I67>=1,$J67>0,OR($K67="HT",$K67="TTC"),$M67>=1,IFERROR(INDEX(Fournisseurs!$T$5:$T$24,MATCH($C67,Fournisseurs!$A$5:$A$24,0)),0)=1),1,0),0)) -> 0 | Z67: =IF($Y67=1,$J67*(1-N($L67)),"") | AA67: =IF($Y67=1,IF($K67="TTC",$Z67/(1+$V67),$Z67),"") | AB67: =IF($Y67=1,IF($K67="TTC",$Z67-$AA67,$AA67*$V67),"") | AC67: =IF($Y67=1,$AA67*$U67*$M67,"") | AD67: =IF($Y67=1,$AC67/SUMIFS($AC$6:$AC$205,$C$6:$C$205,$C67,$Y$6:$Y$205,1),"") | AE67: =IF($Y67=1,(INDEX(Fournisseurs!$J$5:$J$24,MATCH($C67,Fournisseurs!$A$5:$A$24,0))+INDEX(Fournisseurs!$K$5:$K$24,MATCH($C67,Fournisseurs!$A$5:$A$24,0)))*$U67*$AD67/($I67*$M67),"") | AF67: =IF($Y67=1,INDEX(Fournisseurs!$L$5:$L$24,MATCH($C67,Fournisseurs!$A$5:$A$24,0))*$AD67/($I67*$M67),"") | AG67: =IF($Y67=1,$AA67*$U67/$I67,"") | AH67: =IF($Y67=1,$AB67*$U67/$I67,"") | AI67: =IF($Y67=1,IF(AND(Paramètres!$B$4="EFFECTIVE",$W67="CH",$AB67>0),1,0),"") | AJ67: =IF($Y67=1,IF($X67<>"CH",($AG67+$AE67+$AF67)*Paramètres!$B$14,0),"") | AK67: =IF($Y67=1,$AG67+IF($AI67=1,0,$AH67)+$AE67+$AF67+IF(Paramètres!$B$4="NOT_REGISTERED",$AJ67,0),"") | AL67: =IF($Y67=1,($AK67+Paramètres!$B$7+Paramètres!$B$8+Paramètres!$B$9+Paramètres!$B$10)/((1-Paramètres!$B$11)/(1+Paramètres!$B$5)-Paramètres!$B$6),"") | AM67: =IF(AND($Y67=1,ISNUMBER($R67)),IF($R67>0,$AL67/$R67-1,""),"") | AN67: =IF(AND($Y67=1,ISNUMBER($R67)),IF($R67>0,$R67/(1+Paramètres!$B$5)-$AK67-($R67*Paramètres!$B$6+Paramètres!$B$7)-Paramètres!$B$8-Paramètres!$B$9-Paramètres!$B$10,""),"") | AO67: =IF(ISNUMBER($AN67),$AN67/($R67/(1+Paramètres!$B$5)),"") | AP67: =IF($A67="","",IF($Y67<>1,"INCOMPLET",IF(NOT(ISNUMBER($AM67)),"SANS RÉF. MARCHÉ",IF($AM67<=Paramètres!$B$12,"OK",IF(AND($AO67>=Paramètres!$B$15,$AN67>=Paramètres!$B$16),"À REVOIR","NON RENTABLE"))))) -> INCOMPLET | AQ67: =TRIM(IF(AND($Y67=1,ISNUMBER($N67)),IF($M67<$N67,"MOQ ",""),"")&IF(AND($Y67=1,ISNUMBER($O67)),IF($O67<$I67*$M67,"DISPO ",""),"")&IF($S67="O","FICTIF ","")&IF($Y67=1,IF(AND($K67="TTC",$W67<>"CH"),"TVA-ÉTRANGÈRE ",""),"")) | AR67: =IF($Y67=1,COUNTIFS($A$6:$A$205,$A67,$AK$6:$AK$205,"<"&$AK67,$Y$6:$Y$205,1)+1,"") | AS67: =IF(ISNUMBER($AR67),$A67&"|"&$AR67,"") | AT67: =IF($Y67=1,$AK67*$I67*$M67,"")
T68: =IF($C68="","",IFERROR(INDEX(Fournisseurs!$C$5:$C$24,MATCH($C68,Fournisseurs!$A$5:$A$24,0)),"")) | U68: =IF($C68="","",IFERROR(INDEX(Fournisseurs!$D$5:$D$24,MATCH($C68,Fournisseurs!$A$5:$A$24,0)),"")) | V68: =IF($C68="","",IFERROR(INDEX(Fournisseurs!$G$5:$G$24,MATCH($C68,Fournisseurs!$A$5:$A$24,0)),"")) | W68: =IF($C68="","",IFERROR(INDEX(Fournisseurs!$H$5:$H$24,MATCH($C68,Fournisseurs!$A$5:$A$24,0)),"")) | X68: =IF($C68="","",IFERROR(INDEX(Fournisseurs!$B$5:$B$24,MATCH($C68,Fournisseurs!$A$5:$A$24,0)),"")) | Y68: =IF($A68="","",IF(AND($A68<>"",$C68<>"",ISNUMBER($I68),ISNUMBER($J68),ISNUMBER($M68)),IF(AND($I68>=1,$J68>0,OR($K68="HT",$K68="TTC"),$M68>=1,IFERROR(INDEX(Fournisseurs!$T$5:$T$24,MATCH($C68,Fournisseurs!$A$5:$A$24,0)),0)=1),1,0),0)) | Z68: =IF($Y68=1,$J68*(1-N($L68)),"") | AA68: =IF($Y68=1,IF($K68="TTC",$Z68/(1+$V68),$Z68),"") | AB68: =IF($Y68=1,IF($K68="TTC",$Z68-$AA68,$AA68*$V68),"") | AC68: =IF($Y68=1,$AA68*$U68*$M68,"") | AD68: =IF($Y68=1,$AC68/SUMIFS($AC$6:$AC$205,$C$6:$C$205,$C68,$Y$6:$Y$205,1),"") | AE68: =IF($Y68=1,(INDEX(Fournisseurs!$J$5:$J$24,MATCH($C68,Fournisseurs!$A$5:$A$24,0))+INDEX(Fournisseurs!$K$5:$K$24,MATCH($C68,Fournisseurs!$A$5:$A$24,0)))*$U68*$AD68/($I68*$M68),"") | AF68: =IF($Y68=1,INDEX(Fournisseurs!$L$5:$L$24,MATCH($C68,Fournisseurs!$A$5:$A$24,0))*$AD68/($I68*$M68),"") | AG68: =IF($Y68=1,$AA68*$U68/$I68,"") | AH68: =IF($Y68=1,$AB68*$U68/$I68,"") | AI68: =IF($Y68=1,IF(AND(Paramètres!$B$4="EFFECTIVE",$W68="CH",$AB68>0),1,0),"") | AJ68: =IF($Y68=1,IF($X68<>"CH",($AG68+$AE68+$AF68)*Paramètres!$B$14,0),"") | AK68: =IF($Y68=1,$AG68+IF($AI68=1,0,$AH68)+$AE68+$AF68+IF(Paramètres!$B$4="NOT_REGISTERED",$AJ68,0),"") | AL68: =IF($Y68=1,($AK68+Paramètres!$B$7+Paramètres!$B$8+Paramètres!$B$9+Paramètres!$B$10)/((1-Paramètres!$B$11)/(1+Paramètres!$B$5)-Paramètres!$B$6),"") | AM68: =IF(AND($Y68=1,ISNUMBER($R68)),IF($R68>0,$AL68/$R68-1,""),"") | AN68: =IF(AND($Y68=1,ISNUMBER($R68)),IF($R68>0,$R68/(1+Paramètres!$B$5)-$AK68-($R68*Paramètres!$B$6+Paramètres!$B$7)-Paramètres!$B$8-Paramètres!$B$9-Paramètres!$B$10,""),"") | AO68: =IF(ISNUMBER($AN68),$AN68/($R68/(1+Paramètres!$B$5)),"") | AP68: =IF($A68="","",IF($Y68<>1,"INCOMPLET",IF(NOT(ISNUMBER($AM68)),"SANS RÉF. MARCHÉ",IF($AM68<=Paramètres!$B$12,"OK",IF(AND($AO68>=Paramètres!$B$15,$AN68>=Paramètres!$B$16),"À REVOIR","NON RENTABLE"))))) | AQ68: =TRIM(IF(AND($Y68=1,ISNUMBER($N68)),IF($M68<$N68,"MOQ ",""),"")&IF(AND($Y68=1,ISNUMBER($O68)),IF($O68<$I68*$M68,"DISPO ",""),"")&IF($S68="O","FICTIF ","")&IF($Y68=1,IF(AND($K68="TTC",$W68<>"CH"),"TVA-ÉTRANGÈRE ",""),"")) | AR68: =IF($Y68=1,COUNTIFS($A$6:$A$205,$A68,$AK$6:$AK$205,"<"&$AK68,$Y$6:$Y$205,1)+1,"") | AS68: =IF(ISNUMBER($AR68),$A68&"|"&$AR68,"") | AT68: =IF($Y68=1,$AK68*$I68*$M68,"")
T69: =IF($C69="","",IFERROR(INDEX(Fournisseurs!$C$5:$C$24,MATCH($C69,Fournisseurs!$A$5:$A$24,0)),"")) | U69: =IF($C69="","",IFERROR(INDEX(Fournisseurs!$D$5:$D$24,MATCH($C69,Fournisseurs!$A$5:$A$24,0)),"")) | V69: =IF($C69="","",IFERROR(INDEX(Fournisseurs!$G$5:$G$24,MATCH($C69,Fournisseurs!$A$5:$A$24,0)),"")) | W69: =IF($C69="","",IFERROR(INDEX(Fournisseurs!$H$5:$H$24,MATCH($C69,Fournisseurs!$A$5:$A$24,0)),"")) | X69: =IF($C69="","",IFERROR(INDEX(Fournisseurs!$B$5:$B$24,MATCH($C69,Fournisseurs!$A$5:$A$24,0)),"")) | Y69: =IF($A69="","",IF(AND($A69<>"",$C69<>"",ISNUMBER($I69),ISNUMBER($J69),ISNUMBER($M69)),IF(AND($I69>=1,$J69>0,OR($K69="HT",$K69="TTC"),$M69>=1,IFERROR(INDEX(Fournisseurs!$T$5:$T$24,MATCH($C69,Fournisseurs!$A$5:$A$24,0)),0)=1),1,0),0)) | Z69: =IF($Y69=1,$J69*(1-N($L69)),"") | AA69: =IF($Y69=1,IF($K69="TTC",$Z69/(1+$V69),$Z69),"") | AB69: =IF($Y69=1,IF($K69="TTC",$Z69-$AA69,$AA69*$V69),"") | AC69: =IF($Y69=1,$AA69*$U69*$M69,"") | AD69: =IF($Y69=1,$AC69/SUMIFS($AC$6:$AC$205,$C$6:$C$205,$C69,$Y$6:$Y$205,1),"") | AE69: =IF($Y69=1,(INDEX(Fournisseurs!$J$5:$J$24,MATCH($C69,Fournisseurs!$A$5:$A$24,0))+INDEX(Fournisseurs!$K$5:$K$24,MATCH($C69,Fournisseurs!$A$5:$A$24,0)))*$U69*$AD69/($I69*$M69),"") | AF69: =IF($Y69=1,INDEX(Fournisseurs!$L$5:$L$24,MATCH($C69,Fournisseurs!$A$5:$A$24,0))*$AD69/($I69*$M69),"") | AG69: =IF($Y69=1,$AA69*$U69/$I69,"") | AH69: =IF($Y69=1,$AB69*$U69/$I69,"") | AI69: =IF($Y69=1,IF(AND(Paramètres!$B$4="EFFECTIVE",$W69="CH",$AB69>0),1,0),"") | AJ69: =IF($Y69=1,IF($X69<>"CH",($AG69+$AE69+$AF69)*Paramètres!$B$14,0),"") | AK69: =IF($Y69=1,$AG69+IF($AI69=1,0,$AH69)+$AE69+$AF69+IF(Paramètres!$B$4="NOT_REGISTERED",$AJ69,0),"") | AL69: =IF($Y69=1,($AK69+Paramètres!$B$7+Paramètres!$B$8+Paramètres!$B$9+Paramètres!$B$10)/((1-Paramètres!$B$11)/(1+Paramètres!$B$5)-Paramètres!$B$6),"") | AM69: =IF(AND($Y69=1,ISNUMBER($R69)),IF($R69>0,$AL69/$R69-1,""),"") | AN69: =IF(AND($Y69=1,ISNUMBER($R69)),IF($R69>0,$R69/(1+Paramètres!$B$5)-$AK69-($R69*Paramètres!$B$6+Paramètres!$B$7)-Paramètres!$B$8-Paramètres!$B$9-Paramètres!$B$10,""),"") | AO69: =IF(ISNUMBER($AN69),$AN69/($R69/(1+Paramètres!$B$5)),"") | AP69: =IF($A69="","",IF($Y69<>1,"INCOMPLET",IF(NOT(ISNUMBER($AM69)),"SANS RÉF. MARCHÉ",IF($AM69<=Paramètres!$B$12,"OK",IF(AND($AO69>=Paramètres!$B$15,$AN69>=Paramètres!$B$16),"À REVOIR","NON RENTABLE"))))) | AQ69: =TRIM(IF(AND($Y69=1,ISNUMBER($N69)),IF($M69<$N69,"MOQ ",""),"")&IF(AND($Y69=1,ISNUMBER($O69)),IF($O69<$I69*$M69,"DISPO ",""),"")&IF($S69="O","FICTIF ","")&IF($Y69=1,IF(AND($K69="TTC",$W69<>"CH"),"TVA-ÉTRANGÈRE ",""),"")) | AR69: =IF($Y69=1,COUNTIFS($A$6:$A$205,$A69,$AK$6:$AK$205,"<"&$AK69,$Y$6:$Y$205,1)+1,"") | AS69: =IF(ISNUMBER($AR69),$A69&"|"&$AR69,"") | AT69: =IF($Y69=1,$AK69*$I69*$M69,"")
